Workbook
Name density: #REF!

Sheet Sheet7 (2)
E1: PROFORMA Order（外贸订单 预售发票） | R1: Order Production（内贸订单） | AK1: Prepared（准备好的） | AX1: shipments
A2: No | B2: Incoterms | C2: Data 日期 | D2: INV No 发票号 | E2: SPEC 规格 | F2: INV No 发票号 | G2: Knife No. | H2: Buyer 买家 | I2: SPEC 规格 | J2: QTY 数量 | K2: CNY/ton 单价 | L2: Total 总价 | M2: RECEIVABLE ADV 应收预付款 | N2: Received ADV 已收到预付款 | O2: Balance 尾款 | R2: Supplyer 供应商 | S2: Inv No 发票号（供应商） | T2: Order date 下单日期 | U2: Expect preparation date 预计货好时间 | V2: Actual preparation date 实际货好时间 | W2: Delay date 延迟日期 | X2: Notes 备注 | Y2: QTY 数量 | Z2: CNY/ton 单价 | AA2: Total 总价 | AB2: PAID ADV 已付（供应商） | AC2: Balance 尾款（供应商） | AD2: QTY CASH 数量 现金 | AE2: CNY/ton CASH 单价 现金 | AF2: Total CASH 总价 现金 | AG2: PAID ADV CASH 已付现金（供应商） | AH2: Balance CASH 尾款现金（供应商） | AK2: QTY 数量 | AL2: CNY/ton 单价 | AM2: Total 总价 | AN2: Received ADV 已收到预付款 | AO2: Balance 国外尾款 | AQ2: Actual preparation date 实际货好时间 | AR2: Booking date 订舱时间 | AS2: Notes | AT2: Port | AU2: Booking 预定 | AV2: No containers | AW2: ETD 预计开船日期 | AX2: QTY 出口数量 | AY2: CNY/ton 出口单价 | AZ2: Total 出口总价 | BA2: Received 已收到预付款 | BB2: PAID 国外已付 | BC2: Balance 国外尾款 | BD2: Agents 货代名称 | BE2: Line 船公司 | BF2: ETD 开船时间 | BG2: SEA RATE 海运运费 | BH2: Balance MT | BI2: Status | BL2: TJTW Invoice | BM2: Clent 客户 | BN2: Contract/ Invoice 国外合同号 | BO2: SPEC 规格 | BP2: QTY 数量 | BQ2: Expect preparation date 预计货好时间 | BR2: 应受到
C3: 45580 | D3: INTW-3 | E3: 0.16x782x1033 | F3: INTW-3 | H3: INDX | I3: 0.16x782x1033 | J3: 13 | K3: 6860 | L3: =J3*K3 -> 89180 | M3: =L3*0.3 -> 26754 | N3: 0 | O3: =L3-N3 -> 89180 | R3: CRC | S3: BJHS-XWST-241022-01 | T3: 45589 | U3: =T3+60 -> 45649 | Y3: 16.475 | Z3: 3660 | AA3: =Y3*Z3 -> 60298.5 | AB3: =AA3 -> 60298.5 | AC3: =AA3-AB3 -> 0 | AK3: 12.46 | AL3: 6860 | AM3: =AK3*AL3 -> 85475.6 | AX3: 12.46 | AY3: 8462 | AZ3: =AX3*AY3 -> 105436.52 | BA3: 0 | BB3: 105436.52 | BC3: =AZ3-BB3 -> 0 | BD3: Andy | BE3: XINHELU | BF3: 45653 | BI3: closed | BL3: =D3 -> INTW-3 | BR3: =M3 -> 26754
D4: INTW-3 | S4: обрубки 修边 | AD4: 16.475 | AE4: 30 | AF4: =AD4*AE4 -> 494.25 | AG4: 0 | AH4: =AF4-AG4 -> 494.25 | BR4: =M4 -> 0
D5: INTW-3 | S5: продажа обрубков 卖修边 | Y5: 3.406 | Z5: -3200 | AA5: =Y5*Z5 -> -10899.2 | AB5: =AA5 -> -10899.2 | AC5: =AB5 -> -10899.2 | AD5: 0.033575833 | AE5: -2300 | AF5: =AD5*AE5 -> -77.224415 | BR5: =M5 -> 0
D6: INTW-3 | S6: Логистика 运费 | AD6: 13.125 | AE6: 20 | AF6: =AD6*AE6 -> 262.5 | BR6: =M6 -> 0
D7: INTW-3 | R7: YH | S7: BZJY202411-18 | T7: 45610 | U7: =T7+21 -> 45631 | Y7: 12.695 | Z7: 810 | AA7: =Y7*Z7 -> 10282.95 | BR7: =M7 -> 0
D8: INTW-3 | S8: Логистика 运费 | Y8: 12.695 | Z8: 30 | AA8: =Y8*Z8 -> 380.85 | BR8: =M8 -> 0
D9: INTW-3 | R9: JHL | S9: Олово 镀锡 | Y9: 12.773 | Z9: 1615 | AA9: =Y9*Z9 -> 20628.395 | AB9: 333278.82 | BR9: =M9 -> 0
C10: 45580 | D10: INTW-3 | E10: 0.15x890x866 | F10: INTW-3 | H10: INDX | I10: 0.15x890x866 | J10: 13 | K10: 6950 | L10: =J10*K10 -> 90350 | M10: =L10*0.3 -> 27105 | N10: 0 | O10: =L10-N10 -> 90350 | R10: CRC | S10: BJHS-XWST-241022-01 | T10: 45589 | U10: =T10+60 -> 45649 | Y10: 16.41 | Z10: 3660 | AA10: =Y10*Z10 -> 60060.6 | AB10: =AA10 -> 60060.6 | AC10: =AA10-AB10 -> 0 | AK10: 14.154 | AL10: 6950 | AM10: =AK10*AL10 -> 98370.3 | AX10: 14.154 | AY10: 8552 | AZ10: =AX10*AY10 -> 121045.01 | BA10: 0 | BB10: 121045.01 | BC10: =AZ10-BB10 -> -0.002 | BD10: Andy | BE10: XINHELU | BF10: 45653 | BI10: closed | BR10: =M10 -> 27105
D11: INTW-3 | S11: обрубки 修边 | AD11: 16.41 | AE11: 30 | AF11: =AD11*AE11 -> 492.3 | AG11: 0 | AH11: =AF11-AG11 -> 492.3 | BR11: =M11 -> 0
D12: INTW-3 | S12: продажа обрубков 卖修边 | Y12: 1.596 | Z12: -3200 | AA12: =Y12*Z12 -> -5107.2 | AB12: =AA12 -> -5107.2 | AC12: =AB12 -> -5107.2 | AD12: 0.033443364 | AE12: -2300 | AF12: =AD12*AE12 -> -76.919736 | BR12: =M12 -> 0
D13: INTW-3 | S13: Логистика 运费 | AD13: 14.565 | AE13: 20 | AF13: =AD13*AE13 -> 291.3 | BR13: =M13 -> 0
D14: INTW-3 | R14: YH | S14: BZJY202411-18 | T14: 45610 | U14: =T14+21 -> 45631 | Y14: 13.77 | Z14: 830 | AA14: =Y14*Z14 -> 11429.1 | BR14: =M14 -> 0
D15: INTW-3 | S15: Логистика 运费 | Y15: 17.77 | Z15: 30 | AA15: =Y15*Z15 -> 533.1 | BR15: =M15 -> 0
D16: INTW-3 | R16: JHL | S16: Олово 镀锡 | Y16: 13.906 | Z16: 1695 | AA16: =Y16*Z16 -> 23570.67 | AB16: 333278.82 | BR16: =M16 -> 0
C17: 总数 | D17: INTW-3 | E17: 0.16*782*1033 0.15*890*866 | F17: INTW-3 | H17: INDEX | I17: 0.16*782*1033 0.15*890*866 | J17: =SUM(J3:J16) -> 26 | AA17: =SUM(AA3:AA16) -> 171177.77 | AB17: =AB9+AB16 -> 666557.64 | BI17: closed
D18: NBE-2-3 | E18: 0.23x905x720 T3 2.0/2.0 | F18: NBE-2 | H18: “I.C.E.” LLC | I18: 0.23x905x720 T3 2.0/2.0 | J18: 60 | K18: 7009 | L18: =J18*K18 -> 420540 | M18: =L18*0.3 -> 126162 | N18: =L18*0.3 -> 126162 | O18: =N18-L18 -> -294378 | R18: 海钢云翼 | S18: HY2501015V | T18: 45656 | U18: 45748 | Y18: 63.495 | Z18: 4560 | AA18: =Y18*Z18 -> 289537.2 | AB18: =AA18 -> 289537.2 | AC18: =SUM(AA18:AA19) -> 353621.88 | AK18: =0.588+63.371 -> 63.959 | AL18: 7009 | AM18: =AL18*AK18 -> 448288.63 | AO18: =AM18-AN18 -> 448288.63 | AX18: 63.371 | AY18: 7009 | AZ18: =AY18*AX18 -> 444167.34 | BA18: 239337 | BB18: 298717.96 | BC18: =BB18+BA18-AZ18 -> 93887.621 | BR18: =M18 -> 126162
N19: 298717.96 | S19: Олово 镀锡 | Y19: 64.732 | Z19: 990 | AA19: =Z19*Y19 -> 64084.68 | AB19: =AA19 -> 64084.68 | BR19: =M19 -> 0
S20: Логистика 运费 | BR20: =M20 -> 0
D21: NBE-2-1-905 | E21: 0.23x905x720 T3 1.5/1.5 | F21: NBE-2 | H21: “I.C.E.” LLC | I21: 0.23x905x720 T3 1.5/1.5 | J21: 30 | K21: 6857 | L21: =J21*K21 -> 205710 | M21: =L21*0.3 -> 61713 | N21: =L21*0.3 -> 61713 | O21: =N21-L21 -> -143997 | R21: 海钢云翼 | S21: HY2501015V | T21: 45656 | U21: 45748 | Y21: 31.34 | Z21: 4560 | AA21: =Y21*Z21 -> 142910.4 | AB21: =AA21 -> 142910.4 | AC21: =SUM(AA21:AA22) -> 168132.24 | AK21: =1.112+7.645+20.624 -> 29.381 | AL21: 6857 | AM21: =AL21*AK21 -> 201465.52 | AO21: =AM21-AN21 -> 201465.52 | AX21: 7.645 | AY21: 6857 | AZ21: =AY21*AX21 -> 52421.765 | BA21: 37059.77 | BC21: =BB21+BA21-AZ21 -> -15361.995 | BR21: =M21 -> 61713
D22: NBE-2-2 | N22: 98993.14 | S22: Олово 镀锡 | Y22: 30.026 | Z22: 840 | AA22: =Z22*Y22 -> 25221.84 | AB22: =AA22 -> 25221.84 | AX22: 20.624 | AY22: 6857 | AZ22: =AY22*AX22 -> 141418.77 | BA22: 98993.14 | BC22: =BB22+BA22-AZ22 -> -42425.628 | BR22: =M22 -> 0
S23: Логистика 运费 | BR23: =M23 -> 0
D24: NBE-2-1 | E24: 0.23*850*1040 T3 1.5/1.5 | F24: NBE-2 | H24: “I.C.E.” LLC | I24: 0.23*850*1040 T3 1.5/1.5 | J24: 30 | K24: 5718 | L24: =J24*K24 -> 171540 | M24: =L24*0.3 -> 51462 | N24: =L24*0.3 -> 51462 | O24: =N24-L24 -> -120078 | R24: 海钢云翼 | S24: HY2501015V | T24: 45656 | U24: 45734 | Y24: 25.545 | Z24: 4530 | AA24: =Y24*Z24 -> 115718.85 | AB24: =AA24 -> 115718.85 | AC24: =SUM(AA24:AA25) -> 138789.45 | AK24: 25.634 | AL24: 5718 | AM24: =AL24*AK24 -> 146575.21 | AO24: =AM24-AN24 -> 146575.21 | AX24: 25.634 | AY24: 5718 | AZ24: =AY24*AX24 -> 146575.21 | BA24: 110475.21 | BC24: =BB24+BA24-AZ24 -> -36100.002 | BR24: =M24 -> 51462
S25: Олово 镀锡 | Y25: 25.634 | Z25: 900 | AA25: =Z25*Y25 -> 23070.6 | AB25: =AA25 -> 23070.6 | BR25: =M25 -> 0
S26: Логистика 运费 | BR26: =M26 -> 0
D27: NBE-2-4 | E27: 0.23x905x720 T3 2.0/2.0 | AK27: 0.588 | AL27: 7009 | AM27: =AL27*AK27 -> 4121.292 | AN27: 4121.292 | AO27: =AM27-AN27 -> 0 | AX27: 0.588 | AY27: 7009 | AZ27: =AY27*AX27 -> 4121.292 | BA27: 0 | BR27: =M27 -> 0
E28: 0.23x905x720 T3 1.5/1.5 | AK28: 1.529 | AL28: 6857 | AM28: =AL28*AK28 -> 10484.353 | AN28: 10484.353 | AO28: =AM28-AN28 -> 0 | AX28: 1.529 | AY28: 6857 | AZ28: =AY28*AX28 -> 10484.353 | BA28: 0 | BR28: =M28 -> 0
D29: NBE-2 | E29: 0.23x905x720 T3 2.0/2.0 0.23x905x720 T3 1.5/1.5 0.23*850*1040 T3 1.5/1.5 | L29: =SUM(L18:L28) -> 797790 | N29: =SUM(N18:N28) -> 637048.1 | AA29: =SUM(AA18:AA25) -> 660543.57 | AB29: =SUM(AB18:AB25) -> 660543.57 | AC29: =SUM(AC18:AC24) -> 660543.57 | AN29: =SUM(AN27:AN28) -> 14605.645 | AO29: =SUM(AO27:AO28) -> 0 | AZ29: =SUM(AZ18:AZ28) -> 799188.73 | BA29: =SUM(BA18:BA28) -> 485865.12 | BB29: =SUM(BB18:BB28) -> 298717.96 | BC29: =SUM(BC18:BC28) -> -0.004 | BI29: active
C30: 45729 | D30: INTW-8 | E30: 98.9mm 0.20 #401 SE*2 | H30: INDEX | J30: 1160000 | K30: =157.05/1000 -> 0.15705 | L30: =K30*J30 -> 182178 | M30: =L30*0.3 -> 54653.4 | N30: =54653.4+127524.6 -> 182178 | O30: =L30-N30 -> 0 | R30: ZM | S30: ZM20250403-A1 | T30: 45750 | U30: 45772 | X30: shipped | Y30: 1160000 | Z30: 0.165 | AA30: =Z30*Y30 -> 191400 | AB30: 191400 | AC30: =AA30-AB30 -> 0 | AK30: 1160000 | AL30: =157.05/1000 -> 0.15705 | AM30: =AK30*AL30 -> 182178 | AX30: 1160000 | AY30: =157.05/1000 -> 0.15705 | AZ30: =AX30*AY30 -> 182178 | BR30: =M30 -> 54653.4
C31: 总数 | D31: =D30 -> INTW-8 | E31: =E30 -> 98.9mm 0.20 #401 SE*2 | H31: =H30 -> INDEX | J31: =J30 -> 1160000 | L31: =L30 -> 182178 | X31: shipped | BI31: closed
C32: 45008 | D32: TJTW-1L | E32: 99.8mm 0.21 #401 | F32: TJTW-1L | H32: TW | I32: 99.8mm 0.21 #401 | J32: 923400 | K32: 0.285 | L32: =J32*K32 -> 263169 | R32: ZM | S32: ZM20221229-A11 | T32: 44924 | Y32: 954000 | Z32: 0.285 | AA32: =Y32*Z32 -> 271890 | AK32: 954000 | AL32: 0.257 | AM32: =AK32*AL32 -> 245178 | AX32: 954000 | AY32: 0.257 | AZ32: =AX32*AY32 -> 245178 | BA32: 0 | BC32: =BA32-AZ32 -> -245178 | BR32: =M32 -> 0
R33: 退税 | AA33: =-(AZ32*0.13/1.13) -> -28206.319 | BR33: =M33 -> 0
C34: 45014 | D34: TJTW-1L-2 | E34: 99.8mm 0.21 #401 | F34: TJTW-1L-2 | H34: TW | I34: 99.8mm 0.21 #401 | J34: 923400 | K34: 0.285 | L34: =J34*K34 -> 263169 | R34: ZM | S34: ZM20221229-A11 | Y34: 957600 | Z34: 0.285 | AA34: =Y34*Z34 -> 272916 | AK34: 957600 | AL34: 0.257 | AM34: =AK34*AL34 -> 246103.2 | AX34: 957600 | AY34: 0.257 | AZ34: =AX34*AY34 -> 246103.2 | BA34: 200 | BC34: =BA34-AZ34 -> -245903.2 | BR34: =M34 -> 0
AA35: =-(AZ34*0.13/1.13) -> -28312.758 | BR35: =M35 -> 0
C36: 45022 | D36: TJTW-1L-3 | E36: 99.8mm 0.21 #401 | F36: TJTW-1L-3 | H36: TW | I36: 99.8mm 0.21 #401 | J36: 923400 | K36: 0.285 | L36: =J36*K36 -> 263169 | R36: ZM | S36: ZM20221229-A11 | Y36: 955980 | Z36: 0.285 | AA36: =Y36*Z36 -> 272454.3 | AK36: 955980 | AL36: 0.257 | AM36: =AK36*AL36 -> 245686.86 | AX36: 955980 | AY36: 0.257 | AZ36: =AX36*AY36 -> 245686.86 | BA36: 315602.8 | BC36: =BA36-AZ36 -> 69915.94 | BR36: =M36 -> 0
AA37: =-(AZ36*0.13/1.13) -> -28264.86 | BR37: =M37 -> 0
C38: 45030 | D38: TJTW-1L-4 | E38: 99.8mm 0.21 #401 | F38: TJTW-1L-4 | H38: TW | I38: 99.8mm 0.21 #401 | J38: 923400 | K38: 0.285 | L38: =J38*K38 -> 263169 | R38: ZM | S38: ZM20221229-A11 | Y38: 957600 | Z38: 0.285 | AA38: =Y38*Z38 -> 272916 | AK38: 957600 | AL38: 0.2577 | AM38: =AK38*AL38 -> 246773.52 | AX38: 957600 | AY38: 0.2577 | AZ38: =AX38*AY38 -> 246773.52 | BA38: 246052.1 | BC38: =BA38-AZ38 -> -721.42 | BR38: =M38 -> 0
AA39: =-(AZ38*0.13/1.13) -> -28389.874 | BR39: =M39 -> 0
C40: 45035 | D40: 国外打款 | F40: 国外打款 | BA40: 274770.33 | BC40: =BA40-AZ40 -> 274770.33 | BR40: =M40 -> 0
C41: 45063 | D41: 国外打款 | F41: 国外打款 | BA41: 147125.56 | BC41: =BA41-AZ41 -> 147125.56 | BR41: =M41 -> 0
A42: 1 | C42: 总数 | D42: TJTW-1L | E42: 99.8mm 0.21 #401 | F42: TJTW-1L | H42: TW | I42: 99.8mm 0.21 #401 | J42: =AX42 -> 3825180 | AA42: =SUM(AA32:AA41) -> 977002.49 | AM42: =SUM(AM32:AM41) -> 983741.58 | AX42: =SUM(AX32:AX41) -> 3825180 | AZ42: =SUM(AZ32:AZ41) -> 983741.58 | BA42: =SUM(BA32:BA41) -> 983750.79 | BC42: =SUM(BC32:BC41) -> 9.21 | BI42: closed
C43: 45127 | D43: TJTW-2-1 | E43: 0.18*905*669.5 | F43: TJTW-2-1 | H43: TW | I43: 0.18*905*669.5 | J43: 163.62 | K43: 7230 | L43: =J43*K43 -> 1182972.6 | R43: ZM | Y43: 163.62 | Z43: 7100 | AA43: =Y43*Z43 -> 1161702 | AK43: 163.62 | AL43: 7230 | AM43: =AK43*AL43 -> 1182972.6 | AX43: 163.62 | AY43: 7230 | AZ43: =AX43*AY43 -> 1182972.6 | BA43: 0 | BC43: =BA43-AZ43 -> -1182972.6 | BR43: =M43 -> 0
C44: 45002 | D44: TJTW-2-2 | E44: 0.18*905*836.5 | F44: TJTW-2-2 | H44: TW | I44: 0.18*905*836.5 | J44: 79.101 | K44: 7230 | L44: =J44*K44 -> 571900.23 | R44: ZM | Y44: 79.101 | Z44: 7100 | AA44: =Y44*Z44 -> 561617.1 | AK44: 79.101 | AL44: 7230 | AM44: =AK44*AL44 -> 571900.23 | AX44: 79.101 | AY44: 7230 | AZ44: =AX44*AY44 -> 571900.23 | BA44: 429000 | BC44: =BA44-AZ44 -> -142900.23 | BR44: =M44 -> 0
C45: 45063 | D45: TJTW-2-3 | E45: 0.18*905*836.5 | F45: TJTW-2-3 | H45: TW | I45: 0.18*905*836.5 | J45: 78.501 | K45: 9630 | L45: =J45*K45 -> 755964.63 | R45: ZM | Y45: 78.501 | Z45: 9500 | AA45: =Y45*Z45 -> 745759.5 | AK45: 78.501 | AL45: 9630 | AM45: =AK45*AL45 -> 755964.63 | AX45: 78.501 | AY45: 9630 | AZ45: =AX45*AY45 -> 755964.63 | BA45: 210000 | BC45: =BA45-AZ45 -> -545964.63 | BR45: =M45 -> 0
C46: 45090 | D46: 国外打款 | F46: 国外打款 | BA46: 37698.79 | BC46: =BA46-AZ46 -> 37698.79 | BR46: =M46 -> 0
C47: 45121 | D47: 国外打款 | F47: 国外打款 | BA47: 1182972.6 | BC47: =BA47-AZ47 -> 1182972.6 | BR47: =M47 -> 0
C48: 45132 | D48: 国外打款 | F48: 国外打款 | BA48: 500000 | BC48: =BA48-AZ48 -> 500000 | BR48: =M48 -> 0
C49: 45190 | D49: 国外打款 | F49: 国外打款 | BA49: 151166.07 | BC49: =BA49-AZ49 -> 151166.07 | BR49: =M49 -> 0
A50: 2 | C50: 总数 | D50: TJTW-2 | E50: 0.18*905 | F50: TJTW-2 | H50: TW | I50: 0.18*905 | J50: =SUM(J43:J45) -> 321.222 | AX50: =SUM(AX43:AX49) -> 321.222 | AZ50: =SUM(AZ43:AZ49) -> 2510837.5 | BA50: =SUM(BA43:BA49) -> 2510837.5 | BC50: =SUM(BC43:BC49) -> 1.7462298e-10 | BI50: closed
C51: 45257 | D51: TJTW-3-1 | E51: 0.18*905*669.5 | F51: TJTW-3-1 | H51: TW | I51: 0.18*905*669.5 | J51: 19.695 | K51: 6950 | L51: =J51*K51 -> 136880.25 | R51: JHL | S51: JHL2023-5-23 | T51: 45069 | Y51: 98.873 | Z51: 6760 | AA51: =Z51*Y51 -> 668381.48 | AK51: 19.695 | AL51: 6950 | AM51: =AL51*AK51 -> 136880.25 | AX51: 19.695 | AY51: 6950 | AZ51: =AY51*AX51 -> 136880.25 | BA51: 0 | BC51: =BA51-AZ51 -> -136880.25 | BR51: =M51 -> 0
C52: 45282 | D52: TJTW-3-2 | E52: 0.18*905*669.5 | F52: TJTW-3-2 | H52: TW | I52: 0.18*905*669.5 | J52: 72.467 | K52: 6950 | L52: =J52*K52 -> 503645.65 | AK52: 72.467 | AL52: =AM52/AK52 -> 6950 | AM52: 503645.65 | AX52: 72.467 | AY52: =AZ52/AX52 -> 6950 | AZ52: 503645.65 | BA52: 202800 | BC52: =BA52-AZ52 -> -300845.65 | BR52: =M52 -> 0
C53: 45370 | D53: TJTW-3-3 | E53: 0.18*904*836.5 | F53: TJTW-3-3 | H53: TW | I53: 0.18*904*836.5 | J53: 6.711 | K53: 8500 | L53: =J53*K53 -> 57043.5 | AK53: 6.711 | AL53: 8500 | AM53: =AL53*AK53 -> 57043.5 | AX53: 6.711 | AY53: 8500 | AZ53: =AY53*AX53 -> 57043.5 | BA53: 202800 | BC53: =BA53-AZ53 -> 145756.5 | BR53: =M53 -> 0
C54: 45148 | D54: 国外打款 | F54: 国外打款 | BA54: 270866.44 | BC54: =BA54-AZ54 -> 270866.44 | BR54: =M54 -> 0
C55: 45471 | D55: 国外打款 | F55: 国外打款 | BA55: 27560.73 | BC55: =BA55-AZ55 -> 27560.73 | BR55: =M55 -> 0
A56: 3 | C56: 总数 | D56: TJTW-3 | E56: 0.18*904 | F56: TJTW-3 | H56: TW | I56: 0.18*904 | J56: =AX56 -> 98.873 | Y56: =SUM(Y51:Y55) -> 98.873 | AK56: =SUM(AK51:AK55) -> 98.873 | AX56: =SUM(AX51:AX55) -> 98.873 | AZ56: =SUM(AZ51:AZ55) -> 697569.4 | BA56: =SUM(BA51:BA55) -> 704027.17 | BC56: =SUM(BC51,BC52,BC53,BC54,BC55) -> 6457.77 | BI56: closed
H57: TW | BR57: =M57 -> 0
C58: 45215 | D58: TJTW-4-1 | E58: 0.18*822*764.2 | F58: TJTW-4-1 | H58: TW | I58: 0.18*822*764.2 | J58: 25 | K58: 6760 | L58: =J58*K58 -> 169000 | R58: JHL | S58: JHL2023-5-23 | T58: 45069 | Y58: 21.87 | Z58: 6760 | AA58: =Z58*Y58 -> 147841.2 | AK58: 21 | AL58: 6920 | AM58: =AL58*AK58 -> 145320 | AX58: 21 | AY58: 6920 | AZ58: =AY58*AX58 -> 145320 | BA58: 0 | BC58: =BA58-AZ58 -> -145320 | BR58: =M58 -> 0
C59: 45257 | D59: TJTW-4-2 | F59: TJTW-4-2 | H59: TW | AK59: 0.87 | AL59: 6920 | AM59: =AL59*AK59 -> 6020.4 | AX59: 0.87 | AY59: 6920 | AZ59: =AY59*AX59 -> 6020.4 | BA59: 50700 | BC59: =BA59-AZ59 -> 44679.6 | BR59: =M59 -> 0
C60: 45142 | D60: 国外打款 | F60: 国外打款 | H60: TW | BA60: 50700 | BC60: =BA60-AZ60 -> 50700 | BR60: =M60 -> 0
C61: 45148 | D61: 国外打款 | F61: 国外打款 | H61: TW | BA61: 46495.28 | BC61: =BA61-AZ61 -> 46495.28 | BR61: =M61 -> 0
C62: 45471 | D62: 国外打款 | F62: 国外打款 | H62: TW | BA62: 4298.05 | BC62: =BA62-AZ62 -> 4298.05 | BR62: =M62 -> 0
A63: 4 | C63: 总数 | D63: TJTW-4 | E63: 0.18*822 | F63: TJTW-4 | H63: TW | I63: 0.18*822 | J63: =AX63 -> 21.87 | AX63: =SUM(AX58:AX62) -> 21.87 | AZ63: =SUM(AZ58:AZ62) -> 151340.4 | BA63: =SUM(BA58:BA62) -> 152193.33 | BC63: =SUM(BC58:BC62) -> 852.93 | BI63: closed
H64: TW | R64: ZM | Y64: 54.296 | Z64: 6520 | AA64: =Y64*Z64 -> 354009.92 | BR64: =M64 -> 0
C65: 45177 | D65: TJTW-5-1 | E65: 0.24*1023*957 | F65: TJTW-5-1 | H65: TW | I65: 0.24*1023*957 | J65: 27 | K65: 8650 | AK65: =23.604+3.688 -> 27.292 | AL65: =AM65/AK65 -> 7671.1197 | AM65: 209360.2 | AX65: =23.604+3.688 -> 27.292 | AY65: =AZ65/AX65 -> 7671.1197 | AZ65: 209360.2 | BA65: 0 | BC65: =BA65-AZ65 -> -209360.2 | BR65: =M65 -> 0
C66: 45215 | D66: TJTW-5-2 | E66: 0.24*1023*957 | F66: TJTW-5-2 | H66: TW | I66: 0.24*1023*957 | J66: 8.5 | K66: 8585 | AK66: 27.004 | AL66: =AM66/AK66 -> 9732.867 | AM66: 262826.34 | AX66: 27.004 | AY66: =AZ66/AX66 -> 9732.867 | AZ66: 262826.34 | BA66: 105624 | BC66: =BA66-AZ66 -> -157202.34 | BR66: =M66 -> 0
C67: 45190 | D67: 国外打款 | E67: 0.24*1023*957 | F67: 国外打款 | H67: TW | I67: 0.24*1023*957 | J67: 10.5 | K67: 8740 | BA67: 140000 | BC67: =BA67-AZ67 -> 140000 | BR67: =M67 -> 0
C68: 45216 | D68: 国外打款 | E68: 0.24*1023*957 | F68: 国外打款 | H68: TW | I68: 0.24*1023*957 | J68: 8.5 | K68: 8888 | BA68: 226562.54 | BC68: =BA68-AZ68 -> 226562.54 | BR68: =M68 -> 0
A69: 5 | C69: 总数 | D69: TJTW-5 | E69: 0.24*1023*957 | F69: TJTW-5 | H69: TW | I69: 0.24*1023*957 | J69: =AX69 -> 54.296 | AX69: =SUM(AX65:AX68) -> 54.296 | AZ69: =SUM(AZ65:AZ68) -> 472186.54 | BA69: =SUM(BA65:BA68) -> 472186.54 | BC69: =SUM(BC65:BC68) -> 0 | BI69: closed
H70: TW | BR70: =M70 -> 0
C71: 45215 | D71: TJTW-6-1 | E71: 0.17*818*913.6 | F71: TJTW-6-1 | H71: TW | I71: 0.17*818*913.6 | J71: 25 | K71: 9700 | L71: =J71*K71 -> 242500 | R71: JHL | S71: JHL2023-6-2 | Y71: 25 | Z71: 6860 | AA71: =Y71*Z71 -> 171500 | AK71: 33.095 | AL71: 9700 | AM71: =AL71*AK71 -> 321021.5 | AX71: 33.095 | AY71: 9700 | AZ71: =AY71*AX71 -> 321021.5 | BA71: 0 | BC71: =BA71-AZ71 -> -321021.5 | BR71: =M71 -> 0
C72: 45083 | D72: 国外打款 | F72: 国外打款 | H72: TW | R72: ZM | Y72: 33.095 | Z72: 2650 | AA72: =Y72*Z72 -> 87701.75 | BA72: 51450 | BC72: =BA72-AZ72 -> 51450 | BR72: =M72 -> 0
C73: 45170 | D73: 国外打款 | F73: 国外打款 | H73: TW | BA73: 157611.24 | BC73: =BA73-AZ73 -> 157611.24 | BR73: =M73 -> 0
C74: 45216 | D74: 国外打款 | F74: 国外打款 | H74: TW | BA74: 111960.26 | BC74: =BA74-AZ74 -> 111960.26 | BR74: =M74 -> 0
A75: 6 | C75: 总数 | D75: TJTW-6 | E75: 0.17*818*913.6 | F75: TJTW-6 | H75: TW | I75: 0.17*818*913.6 | J75: =AX75 -> 33.095 | AX75: =SUM(AX71:AX74) -> 33.095 | AZ75: =SUM(AZ71:AZ74) -> 321021.5 | BA75: =SUM(BA71:BA74) -> 321021.5 | BC75: =SUM(BC71:BC74) -> 0 | BI75: closed
H76: TW | BR76: =M76 -> 0
C77: 45142 | D77: TJTW-7-1 | E77: 99.8mm 0.21 #401 | F77: TJTW-7-1 | H77: TW | I77: 99.8mm 0.21 #401 | J77: 957600 | K77: 0.2439 | L77: =J77*K77 -> 233558.64 | R77: ZM | S77: ZM20230621-A1 | T77: 45098 | Y77: 957600 | Z77: 0.27 | AA77: =Y77*Z77 -> 258552 | AK77: 957600 | AL77: 0.244 | AM77: =AL77*AK77 -> 233654.4 | AN77: 154931.2 | AX77: 957600 | AY77: 0.244 | AZ77: =AY77*AX77 -> 233654.4 | BA77: 154931.2 | BC77: =BA77-AZ77 -> -78723.2 | BR77: =M77 -> 0
R78: 退税 | AA78: =-(AZ77*0.13/1.13) -> -26880.595 | BR78: =M78 -> 0
C79: 45151 | D79: TJTW-7-2 | E79: 99.8mm 0.21 #401 | F79: TJTW-7-2 | H79: TW | I79: 99.8mm 0.21 #401 | J79: 957600 | K79: 0.2439 | L79: =J79*K79 -> 233558.64 | R79: ZM | S79: ZM20230621-A1 | T79: 45098 | Y79: 957600 | Z79: 0.27 | AA79: =Y79*Z79 -> 258552 | AK79: 957600 | AL79: 0.244 | AM79: =AL79*AK79 -> 233654.4 | AN79: 241896.8 | AX79: 957600 | AY79: 0.244 | AZ79: =AY79*AX79 -> 233654.4 | BA79: 241896.8 | BC79: =BA79-AZ79 -> 8242.4 | BR79: =M79 -> 0
R80: 退税 | AA80: =-(AZ79*0.13/1.13) -> -26880.595 | BR80: =M80 -> 0
C81: 45170 | D81: 国外打款 | F81: 国外打款 | H81: TW | AN81: 70480.8 | BA81: 70480.8 | BC81: =BA81-AZ81 -> 70480.8 | BR81: =M81 -> 0
A82: 7 | C82: 总数 | D82: TJTW-7 | E82: 99.8mm 0.21 #401 | F82: TJTW-7 | H82: TW | I82: 99.8mm 0.21 #401 | J82: =AX82 -> 1915200 | Y82: =SUM(Y76:Y81) -> 1915200 | AA82: =SUM(AA76:AA81) -> 463342.81 | AM82: =SUM(AM76:AM81) -> 467308.8 | AN82: =SUM(AN76:AN81) -> 467308.8 | AX82: =SUM(AX77:AX81) -> 1915200 | AZ82: =SUM(AZ77:AZ81) -> 467308.8 | BA82: =SUM(BA77:BA81) -> 467308.8 | BC82: =SUM(BC77:BC81) -> 0 | BI82: closed
C83: 45215 | D83: TJTW-8-1 | E83: 0.18*905*669.5 | F83: TJTW-8-1 | H83: TW | I83: 0.18*905*669.5 | J83: 81 | K83: 6950 | L83: =J83*K83 -> 562950 | R83: ZM | Y83: 81.81 | Z83: 6750 | AA83: =Y83*Z83 -> 552217.5 | AK83: 81.81 | AL83: 6950 | AM83: =AL83*AK83 -> 568579.5 | AX83: 81.81 | AY83: 6950 | AZ83: =AY83*AX83 -> 568579.5 | BA83: 0 | BC83: =BA83-AZ83 -> -568579.5 | BR83: =M83 -> 0
C84: 45215 | D84: TJTW-8-2 | E84: 0.18*905*669.5 | F84: TJTW-8-2 | H84: TW | I84: 0.18*905*669.5 | J84: 81 | K84: 6950 | L84: =J84*K84 -> 562950 | R84: ZM | Y84: 82.298 | Z84: 6750 | AA84: =Y84*Z84 -> 555511.5 | AK84: 82.298 | AL84: 6950 | AM84: =AL84*AK84 -> 571971.1 | AX84: 82.298 | AY84: 6950 | AZ84: =AY84*AX84 -> 571971.1 | BA84: 607500 | BC84: =BA84-AZ84 -> 35528.9 | BR84: =M84 -> 0
C85: 45215 | D85: TJTW-8-3 | E85: 0.18*905*836.5 | F85: TJTW-8-3 | H85: TW | I85: 0.18*905*836.5 | J85: 81 | K85: 9375 | L85: =J85*K85 -> 759375 | R85: ZM | Y85: 81.651 | Z85: 9150 | AA85: =Y85*Z85 -> 747106.65 | AK85: 81.651 | AL85: 9375 | AM85: =AL85*AK85 -> 765478.12 | AX85: 81.651 | AY85: 9375 | AZ85: =AY85*AX85 -> 765478.12 | BA85: 59489.84 | BC85: =BA85-AZ85 -> -705988.29 | BR85: =M85 -> 0
C86: 45215 | D86: TJTW-8-4 | E86: 0.18*905*836.5 | F86: TJTW-8-4 | H86: TW | I86: 0.18*905*836.5 | J86: 81 | K86: 9375 | L86: =J86*K86 -> 759375 | R86: ZM | Y86: 81.473 | Z86: 9150 | AA86: =Y86*Z86 -> 745477.95 | AK86: 81.473 | AL86: 9375 | AM86: =AL86*AK86 -> 763809.38 | AX86: 81.473 | AY86: 9375 | AZ86: =AY86*AX86 -> 763809.38 | BA86: 1800000 | BC86: =BA86-AZ86 -> 1036190.6 | BR86: =M86 -> 0
C87: 45216 | D87: 国外打款 | F87: 国外打款 | H87: TW | BA87: 202848.26 | BC87: =BA87-AZ87 -> 202848.26 | BR87: =M87 -> 0
A88: 8 | C88: 总数 | D88: TJTW-8 | E88: 0.18*905* | F88: TJTW-8 | H88: TW | I88: 0.18*905* | J88: =AX88 -> 327.232 | AX88: =SUM(AX83:AX87) -> 327.232 | AZ88: =SUM(AZ83:AZ87) -> 2669838.1 | BA88: =SUM(BA83:BA87) -> 2669838.1 | BC88: =BA88-AZ88 -> 0 | BI88: closed
C89: 45177 | D89: TJTW-9-1 | E89: 99.8mm 0.21 #401 | F89: TJTW-9-1 | H89: TW | I89: 99.8mm 0.21 #401 | J89: 957600 | K89: 0.2524 | L89: =J89*K89 -> 241698.24 | R89: ZM | Y89: 957600 | Z89: 0.27 | AA89: =Y89*Z89 -> 258552 | AK89: 957600 | AL89: 0.2524 | AM89: =AL89*AK89 -> 241698.24 | AN89: 154931.2 | AX89: 957600 | AY89: 0.2524 | AZ89: =AY89*AX89 -> 241698.24 | BA89: 154931.2 | BC89: =BA89-AZ89 -> -86767.04
AA90: =-(AZ89*0.13/1.13) -> -27805.992
C91: 45191 | D91: TJTW-9-2 | E91: 99.8mm 0.21 #401 | F91: TJTW-9-2 | H91: TW | I91: 99.8mm 0.21 #401 | J91: 957600 | K91: 0.2524 | L91: =J91*K91 -> 241698.24 | R91: ZM | Y91: 957600 | Z91: 0.27 | AA91: =Y91*Z91 -> 258552 | AK91: 957600 | AL91: 0.2524 | AM91: =AL91*AK91 -> 241698.24 | AN91: 232698.6 | AX91: 957600 | AY91: 0.2524 | AZ91: =AY91*AX91 -> 241698.24 | BA91: 232698.6 | BC91: =BA91-AZ91 -> -8999.64
AA92: =-(AZ91*0.13/1.13) -> -27805.992
A93: 9 | C93: 总数 | D93: TJTW-9 | E93: 99.8mm 0.21 #401 | F93: TJTW-9 | H93: TW | I93: 99.8mm 0.21 #401 | J93: =AX93 -> 1915200 | Y93: =SUM(Y89:Y92) -> 1915200 | AA93: =SUM(AA89:AA92) -> 461492.02 | AM93: =SUM(AM89:AM92) -> 483396.48 | AN93: =SUM(AN89:AN92) -> 387629.8 | AX93: =SUM(AX89:AX91) -> 1915200 | AZ93: =SUM(AZ89:AZ91) -> 483396.48 | BA93: =SUM(BA89:BA91) -> 387629.8 | BC93: =SUM(BC89:BC91) -> -95766.68 | BI93: closed
C94: 45218 | D94: TJTW-10 | E94: 72.9 mm 0.19#300 | F94: TJTW-10 | H94: NF | I94: 72.9 mm 0.19#300 | J94: 1747200 | K94: 0.02123 | L94: =J94*K94 -> 37093.056 | R94: ZM | Y94: 1738240 | Z94: 0.155 | AA94: =Y94*Z94 -> 269427.2 | AK94: 1738240 | AL94: 0.02123 | AM94: =AL94*AK94 -> 36902.835 | AN94: 7458.61 | AX94: 1738240 | AY94: 0.02123 | AZ94: =AY94*AX94 -> 36902.835 | BA94: 7458.61 | BC94: =BA94-AZ94 -> -29444.225
R95: 退税 | AA95: =-(AZ94*0.13/1.13)*7.18 -> -30482.395 | AN95: 29444.23 | BA95: 29444.23 | BC95: =BA95-AZ95 -> 29444.23
A96: 10 | C96: 总数 | D96: TJTW-10 | E96: 72.9 mm 0.19#300 | F96: TJTW-10 | H96: NF | I96: 72.9 mm 0.19#300 | J96: =AX96 -> 1738240 | AA96: =SUM(AA94:AA95) -> 238944.8 | AM96: =SUM(AM94:AM95) -> 36902.835 | AN96: =SUM(AN94:AN95) -> 36902.84 | AX96: =SUM(AX94:AX95) -> 1738240 | AZ96: =SUM(AZ94:AZ95) -> 36902.835 | BA96: =SUM(BA94:BA95) -> 36902.84 | BC96: =SUM(BC94:BC95) -> 0.0048 | BI96: closed
C97: 45212 | D97: TJTW-11 | E97: #401 ETP BPA FREE | F97: TJTW-11 | H97: TW | I97: #401 ETP BPA FREE | J97: 933520 | K97: 0.27 | L97: =J97*K97 -> 252050.4 | R97: ZM | Y97: 933520 | Z97: 0.27 | AA97: =Y97*Z97 -> 252050.4 | AK97: 933520 | AL97: 0.244 | AM97: =AK97*AL97 -> 227778.88 | AN97: 152976.6 | AX97: 933520 | AY97: 0.244 | AZ97: =AX97*AY97 -> 227778.88 | BA97: 152976.6 | BC97: =BA97-AZ97 -> -74802.28
R98: 退税 | AA98: =-(AZ97*0.13/1.13) -> -26204.65
E99: #401 TFS BPA FREE | I99: #401 TFS BPA FREE | J99: 478800 | K99: 0.265 | L99: =J99*K99 -> 126882 | R99: ZM | Y99: 478800 | Z99: 0.265 | AA99: =Y99*Z99 -> 126882 | AK99: 478800 | AL99: 0.24 | AM99: =AK99*AL99 -> 114912 | AX99: 478800 | AY99: 0.24 | AZ99: =AX99*AY99 -> 114912 | BC99: =BA99-AZ99 -> -114912
R100: 退税 | AA100: =-(AZ99*0.13/1.13) -> -13219.965
...

Sheet knife
A1: SKARDA
A2: No. | B2: 直径diam | C2: 厚度thickness | E2: 规格specification | F2: 磨刀费Sharpening fee | H2: Total | I2: TW-67 | J2: TW-70 | K2: TW-76 | L2: TJTW-91 | M2: TJTW-86 | N2: TJTW-90 | O2: TJTW-93 | P2: TJTW-100 | Q2: TJTW-107 | R2: TJTW-124 | S2: TJTW-127 | T2: TJTW-136 | U2: TJTW-137 | V2: TJTW-144
A3: 13 | B3: 96 | C3: 0.18 | D3: 80.3 end | E3: 862*782 | F3: 1493 | G3: * | H3: =SUM(I3:V3) -> 362.939 | J3: 25.585 | K3: 24.956 | N3: 27.566 | O3: 30.576 | P3: 59.371 | R3: 54.18 | S3: 59.705 | U3: 54 | V3: 27
A4: 8 | B4: 107.8 | C4: 0.18 | D4: Twist off | E4: 868*872.4 | F4: 1760 | G4: + | H4: =SUM(I4:V4) -> 1171.068 | I4: 24.544 | J4: 76.278 | K4: 118.963 | M4: 153.728 | N4: 139.77 | O4: 57.168 | P4: 107.273 | Q4: 60.12 | S4: 55.224 | T4: 108 | U4: 135 | V4: 135
A5: 12 | B5: 115.5 | C5: 0.18 | D5: 99 end | E5: 928*934.7 | G5: * | H5: =SUM(I5:V5) -> 167.954 | J5: 32.594 | S5: 27.36 | T5: 27 | U5: 54 | V5: 27
A6: ? | C6: 0.18 | D6: 2pcs can | E6: 936*906.5 | H6: =SUM(I6:V6) -> 54 | J6: 0 | U6: 27 | V6: 27
A7: 7 | B7: 99.8 | C7: 0.16/0.20 | D7: SKO | E7: 892*808.4 | G7: + | H7: =SUM(I7:V7) -> 814.936 | I7: 146.338 | J7: 150.579 | K7: 19.808 | M7: 82.987 | N7: 114.386 | O7: 116.556 | P7: =47.856+27.984 -> 75.84 | Q7: 27.442 | V7: =54+27 -> 81
A8: 11 | B8: 162.8 | C8: 0.18 | D8: 2pcs can | E8: 880*824 | F8: 1493 | G8: * | H8: =SUM(I8:V8) -> 375.095 | J8: 21.729 | R8: 55.79 | S8: 54.576 | T8: 81 | U8: 81 | V8: 81
A9: 10 | B9: 99.54 | C9: 0.18 | D9: 83 end | E9: 890*807.3 | G9: * | H9: =SUM(I9:V9) -> 299.506 | J9: 0 | K9: 37.343 | N9: 30.582 | O9: 26.388 | P9: 48.457 | S9: 48.736 | T9: 54 | U9: 27 | V9: 27
A10: 9 | B10: 90.5 | C10: 0.15 | D10: TO 66mm | E10: 890*917 | H10: =SUM(I10:V10) -> 119.015 | K10: 33.392 | N10: 28.054 | O10: 57.569
A11: TOTAL | H11: =SUM(I11:V11) -> 3127.798 | I11: =SUM(I3:I10) -> 170.882 | J11: =SUM(J3:J10) -> 306.765 | K11: =SUM(K3:K10) -> 234.462 | L11: =SUM(L3:L10) -> 0 | N11: =SUM(N3:N10) -> 340.358 | O11: =SUM(O3:O10) -> 288.257 | P11: =SUM(P3:P10) -> 290.941 | Q11: =SUM(Q3:Q10) -> 87.562 | R11: =SUM(R3:R10) -> 109.97 | S11: =SUM(S3:S10) -> 245.601 | T11: =SUM(T3:T10) -> 270 | U11: =SUM(U3:U10) -> 378 | V11: =SUM(V3:V10) -> 405
A13: OTHERS
A14: No. | B14: 直径diam | C14: 厚度thickness | D14: Customer | E14: 规格specification | H14: Total | I14: 10AN | J14: 15AN | K14: TJTW-64 | L14: 8AN | M14: TJTW-3 | N14: TJTW-13 | O14: 12AN | P14: TJTW-18 | Q14: 20AN | R14: 21AN | S14: 22AN | T14: TJTW-21 | U14: TJTW-38 | V14: TPTW-5 | W14: TJTW-40 | X14: TJTW-33 | Y14: TJTW-49 | Z14: TJTW-50 | AA14: TJTW-55 | AB14: TJTW-61 | AC14: TJTW-999 | AD14: TJTW-74 | AE14: TJTW-85 | AF14: TJTW-75 | AG14: TJTW-80 | AH14: TJTW-125 | AI14: TJTW-115
A15: 1 | B15: 99.8 | C15: 0.15/0.16 | D15: CKO | E15: 820*712 | H15: =SUM(I15:AI15) -> 86.859 | I15: 44.146 | J15: 42.713
A16: 2 | B16: 116.7 | C16: 0.2 | D16: SPEC | E16: 751*710.7 | H16: =SUM(I16:AI16) -> 14.79 | K16: 14.79
A17: 3 | B17: 151 | C17: 0.18 | D17: AMT #2 | E17: 822*764.2 | H17: =SUM(I17:AI17) -> 501.812 | N17: 27.896 | P17: 41.472 | Q17: 52.984 | X17: 41.339 | Y17: 83.654 | AB17: 81.355 | AD17: 122.112 | AF17: 36 | AG17: 15
A18: 5 | B18: 108 | C18: 0.16 | D18: EXIM twist | E18: 775*765 | H18: =SUM(I18:AI18) -> 23.49 | I18: 23.49
A19: 6 | B19: 149 | C19: 0.17 | D19: KML#2 | E19: 818*913 | H19: =SUM(I19:AI19) -> 640.616 | L19: 4.503 | N19: 54.171 | P19: 40.155 | W19: 14.243 | Y19: 13.59 | AA19: 118.484 | AB19: 88.986 | AD19: 134.423 | AF19: 138.284 | AG19: 33.777
A20: 14 | B20: 118 | D20: KLM EOE | E20: 952*959 | H20: =SUM(I20:AI20) -> 0
A21: 15 | B21: 117.5 | C21: 0.2 | D21: SPEC | E21: 963*837.5 | H21: =SUM(I21:AI21) -> 76.054 | AE21: 56.307 | AI21: 19.747
A22: 16 | B22: 160.8 | C22: 0.22 | D22: SPEC | E22: 740*823 | H22: =SUM(I22:AI22) -> 205.875 | AE22: 205.875
A23: 17 | B23: 164.5 | C23: 0.17/0.18 | D23: KML#3 | E23: 905*669.5/836.5 | G23: zhongmin | H23: =SUM(I23:AI23) -> 3622 | L23: 38.81 | M23: 6.711 | N23: 316.478 | O23: 26.906 | P23: 163.523 | Q23: 120.322 | R23: 79.587 | S23: 17.06 | T23: 162.968 | U23: 31.318 | V23: 157.852 | W23: 325.052 | Z23: 368.543 | AB23: 466.824 | AC23: 136.35 | AD23: 522.537 | AF23: 276.964 | AG23: 228.682 | AH23: 175.513
A24: TOTAL | H24: =SUM(I24:AI24) -> 5171.496 | I24: =SUM(I15:I23) -> 67.636 | J24: =SUM(J15:J23) -> 42.713 | K24: =SUM(K15:K23) -> 14.79 | L24: =SUM(L15:L23) -> 43.313 | M24: =SUM(M15:M23) -> 6.711 | N24: =SUM(N15:N23) -> 398.545 | O24: =SUM(O15:O23) -> 26.906 | P24: =SUM(P15:P23) -> 245.15 | ... AI24: =SUM(AI15:AI23) -> 19.747

Sheet payment
A1: 付款的客户 Payer | B1: 发票号 invoice | C1: 规格 specifications | D1: 数量 QTY | E1: 单价 UNT | F1: 总价 TOTAL | G1: 国外已付 paid | H1: 国外未付 Unpaid | I1: 货好时间 Ready date | J1: 状态 Status | K1: 供应商 | O1: LF | P1: 800 | R1: BOC | S1: 752804.58 | U1: VAT | V1: 30446.92 | X1: TRC | Y1: 443.06 | AA1: ABC | AB1: 2756671.4 | AD1: VTB | AE1: 2010 | AG1: 总额 | AH1: =P1+S1+Y1+AB1+AE1 -> 3512729.1
A2: TW | B2: TJTW-9-1 | C2: 99.8mm 0.21 #401 | D2: 957600 | E2: 0.2524 | F2: =E2*D2 -> 241698.24 | G2: =154931.2+86767.04 -> 241698.24 | H2: =F2-G2 -> 0 | I2: 45807 | J2: Shipped | V2: 576408
A3: TW | B3: TJTW-9-2 | C3: 99.8mm 0.21 #401 | D3: 957600 | E3: 0.2524 | F3: =E3*D3 -> 241698.24 | G3: =232698.6+9001.44000000001 -> 241700.04 | H3: =F3-G3+1.8 -> 1.1641577e-11 | I3: 45807 | J3: Shipped
A4: TW | B4: TJTW-11 | C4: #401 ETP BPA FREE | D4: 933520 | E4: 0.244 | F4: =E4*D4 -> 227778.88 | G4: =152976.6+74802.28 -> 227778.88 | H4: =F4-G4 -> 0 | I4: 45807 | J4: Shipped
A5: TW | B5: TJTW-11 | C5: #401 TFS BPA FREE | D5: 478800 | E5: 0.24 | F5: =E5*D5 -> 114912 | G5: 114912 | H5: =F5-G5 -> 0 | I5: 45807 | J5: Shipped
A6: TW | B6: TJTW-11 | C6: #401 TFS | D6: 478800 | E6: 0.235 | F6: =E6*D6 -> 112518 | G6: 112518 | H6: =F6-G6 -> 0 | I6: 45807 | J6: Shipped
A7: TW | B7: TJTW-13 | C7: 0.18*822；0.17*818 | D7: 436.345 | F7: 3603352.9 | G7: =4089971.12-486618.26 -> 3603352.9 | H7: =F7-G7 -> 0 | I7: 45807 | J7: Shipped
A8: TW | B8: TJTW-18 | C8: 0.18*905*836.5 | D8: 374.036 | F8: 2898776.7 | G8: =2842096+458.33+56222.35 -> 2898776.7 | H8: =F8-G8 -> 0 | I8: 45807 | J8: Shipped
A9: TW | B9: TJTW-20 | C9: 99.8mm 0.21 #401 | D9: 2246000 | E9: 0.2344 | F9: =E9*D9 -> 526462.4 | G9: =521173.68+5288.72 -> 526462.4 | H9: =F9-G9 -> 0 | I9: 45807 | J9: Shipped
A10: TW | B10: TJTW-21 | C10: 0.18*905*836.5 | D10: 162.968 | F10: 1225563.1 | G10: =1359750-134186.86 -> 1225563.1 | H10: =F10-G10 -> 0 | I10: 45807 | J10: Shipped
A11: TW | B11: TJTW-23 | C11: 0.16*875*C | D11: 274.657 | E11: 6780 | F11: =E11*D11 -> 1862174.5 | G11: =1124880+737294.46 -> 1862174.5 | H11: =F11-G11 -> 0 | I11: 45807 | J11: Shipped
A12: TW | B12: TJTW-24 | C12: 0.24*963*1026 | D12: 25.164 | E12: 6390 | F12: =E12*D12 -> 160797.96 | G12: =146855.7+313226.43 -> 460082.13 | H12: =SUM(F12:F14)-G12 -> 0 | I12: 45807 | J12: Shipped
A13: TW | B13: TJTW-24 | C13: 0.26*963*1026 | D13: 25.153 | E13: 6330 | F13: =E13*D13 -> 159218.49 | I13: 45807 | J13: Shipped
A14: TW | B14: TJTW-24 | C14: 0.32*856*785 | D14: 22.812 | E14: 6140 | F14: =E14*D14 -> 140065.68 | I14: 45807 | J14: Shipped
A15: TW | B15: TJTW-27 | C15: 99.8mm 0.21 #401 | D15: 2280000 | E15: 0.2329 | F15: =E15*D15 -> 531012 | G15: =510000+21012 -> 531012 | H15: =F15-G15 -> 0 | I15: 45807 | J15: Shipped
A16: TW | B16: TJTW-28 | C16: 0.16*820*C | D16: 343.195 | F16: 1866214.3 | G16: =1000000+866214.275 -> 1866214.3 | H16: =F16-G16 -> 0 | I16: 45807 | J16: Shipped
A17: TW | B17: TJTW-29 | C17: 0.16*820*C | D17: 70.53 | E17: 6841.1 | F17: =E17*D17 -> 482502.78 | G17: =321750+160752.783 -> 482502.78 | H17: =F17-G17 -> 0 | I17: 45807 | J17: Shipped
A18: TW | B18: TJTW-30 | C18: 0.22*903*836.5 | D18: 744 | E18: 26.305 | F18: =E18*D18 -> 19570.92 | G18: =26147.17 -> 26147.17 | H18: =SUM(F18:F19)-G18 -> 0 | I18: 45807 | J18: Shipped
A19: TW | B19: TJTW-30 | C19: 0.22*295 | D19: 250 | E19: 26.305 | F19: =E19*D19 -> 6576.25 | I19: 45807 | J19: Shipped
A20: TW | B20: TJTW-31 | C20: 0.16*820*Coil | D20: 156.698 | E20: 6320 | F20: =E20*D20 -> 990331.36 | G20: =980000+10331.3600000001 -> 990331.36 | H20: =F20-G20 -> 0 | I20: 45807 | J20: Shipped
A21: TW | B21: TJTW-33 | C21: 0.18*822*764.2 | D21: 41.339 | E21: 6350 | F21: =E21*D21 -> 262502.65 | G21: =99000+63216.31+100286.34 -> 262502.65 | H21: =F21-G21 -> 0 | I21: 45807 | J21: Shipped
A22: TW | B22: TJTW-34 | C22: 99.8mm 0.21 #401 | D22: 2275275 | E22: 0.2334 | F22: =E22*D22 -> 531049.19 | G22: =500000+31049.185 -> 531049.19 | H22: =F22-G22 -> 0 | I22: 45807 | J22: Shipped
A23: TW | B23: TJTW-35 | C23: 0.16X875xC | D23: 264.507 | E23: 6160 | F23: =E23*D23 -> 1629363.1 | G23: =1688400-59036.8799999999 -> 1629363.1 | H23: =F23-G23 -> 0 | I23: 45807 | J23: Shipped
A24: TW | B24: TJTW-37 | C24: 0.21x894x1038 | D24: 42.337 | E24: 5892 | F24: =E24*D24 -> 249449.6 | G24: =547057-17480.4519999999 -> 529576.55 | H24: =SUM(F24:F25)-G24 -> 0 | I24: 45807 | J24: Shipped
A25: TW | B25: TJTW-37 | C25: 0.16x960x924 | D25: 44.592 | E25: 6282 | F25: =E25*D25 -> 280126.94 | I25: 45807 | J25: Shipped
A26: TW | B26: TJTW-40 | C26: 0.18*905*836.5 | D26: 339.295 | F26: 2337593.4 | G26: =2875989-538395.65 -> 2337593.4 | H26: =F26-G26 -> 0 | I26: 45807 | J26: Shipped
A27: TW | B27: TJTW-41 | C27: #401 | D27: 2280000 | E27: 0.2329 | F27: =E27*D27 -> 531012 | G27: =701780-170768 -> 531012 | H27: =F27-G27 -> 0 | I27: 45807 | J27: Shipped
A28: TW | B28: TJTW-44 | C28: 99.8mm 0.21 #401 | D28: 2097600 | E28: 0.23 | F28: =E28*D28 -> 482448 | G28: =499960-17512 -> 482448 | H28: =F28-G28 -> 0 | I28: 45807 | J28: Shipped
A29: TW | B29: TJTW-47 | C29: EOE ALU 0.24 #401 | D29: 934800 | E29: 0.367 | F29: =E29*D29 -> 343071.6 | G29: =120000+247000-23928.4 -> 343071.6 | H29: =F29-G29 -> 0 | I29: 45971
A30: TW | B30: TJTW-49 | C30: 0.18*822*764.2 2.8/2.8 T4 stone,BA | D30: 83.654 | E30: 6650 | F30: =E30*D30 -> 556299.1 | G30: =661150-11759.4 -> 649390.6 | H30: =SUM(F30:F31)-G30 -> 0 | I30: 45807 | J30: Shipped
A31: TW | B31: TJTW-49 | C31: 0.17*818*913.6 2.8/2.8 T4 stone,BA | D31: 13.59 | E31: 6850 | F31: =E31*D31 -> 93091.5 | I31: 45807 | J31: Shipped
A32: TW | B32: TJTW-50-1 | C32: 0.18*905*669.5 素铁 | D32: 136.35 | E32: 6570 | F32: =E32*D32 -> 895819.5 | G32: =2334554.25+134259.95 -> 2468814.2 | H32: =(SUM(F32:F38))-G32 -> 0 | I32: 45807 | J32: Shipped
A33: TW | B33: TJTW-50-2 | C33: 0.18*905*669.5 素铁 | D33: 7.575 | E33: 6640 | F33: =E33*D33 -> 50298 | I33: 45807 | J33: Shipped
A34: TW | B34: TJTW-50-2 | C34: 0.18*905*836.5 铝膏+黄 BPA free | D34: 54.339 | E34: 6640 | F34: =E34*D34 -> 360810.96 | I34: 45807 | J34: Shipped
A35: TW | B35: TJTW-50-2 | C35: 0.17*905*836.5 铝膏+有机 BPA free | D35: 43.501 | E35: 6790 | F35: =E35*D35 -> 295371.79 | I35: 45807 | J35: Shipped
A36: TW | B36: TJTW-50-3 | C36: 0.17*905*836.5 铝膏+有机 BPA free | D36: 54.54 | E36: 6790 | F36: =E36*D36 -> 370326.6 | I36: 45807 | J36: Shipped
A37: TW | B37: TJTW-50-4 | C37: 0.17*905*836.5 铝膏+有机 BPA free | D37: 9.047 | E37: 7000 | F37: =E37*D37 -> 63329 | I37: 45807 | J37: Shipped
A38: TW | B38: TJTW-50-4 | C38: 0.18*905*836.5 铝膏+有机 BPA free | D38: 63.191 | E38: 6850 | F38: =E38*D38 -> 432858.35 | I38: 45807 | J38: Shipped
A39: TW | B39: TJTW-51 | C39: 0,16x784x1040 2.0/2.0 | D39: 13.806 | E39: 6330 | F39: =E39*D39 -> 87391.98 | G39: 87391.98 | H39: =F39-G39 -> 0 | I39: 45807 | J39: Shipped
A40: TW | B40: TJTW-53 | C40: ETP EOE 99 BPA FREE | D40: 2097600 | E40: 0.23 | F40: =E40*D40 -> 482448 | G40: =476364.96+6083.04 -> 482448 | H40: =F40-G40 -> 0 | I40: 45807 | J40: Shipped
A41: TW | B41: TJTW-55 | C41: 0.17*818*913 铝膏+有机 BPA free | D41: 58.443 | E41: 6750 | F41: =E41*D41 -> 394490.25 | G41: =770000+29767 -> 799767 | H41: =SUM(F41:F43)-G41 -> 0 | I41: 45807 | J41: Shipped
A42: TW | B42: TJTW-55 | C42: 0.17*818*913 铝膏+黄 BPA free | D42: 53.981 | E42: 6750 | F42: =E42*D42 -> 364371.75 | I42: 45807 | J42: Shipped
A43: TW | B43: TJTW-55-2 | C43: 0.17*818*913 铝膏+黄 BPA free | D43: 6.06 | E43: 6750 | F43: =E43*D43 -> 40905 | I43: 45807 | J43: Shipped
A44: TW | B44: TJTW-56 | C44: 0.17*857*730 2.8/2.8 T4BA | D44: 27.104 | E44: 6800 | F44: =E44*D44 -> 184307.2 | G44: =182952+1355.2 -> 184307.2 | H44: =F44-G44 -> 0 | I44: 45807 | J44: Shipped
A45: TW | B45: TJTW-59 | C45: EOE.99.8mm 0.21 #401 | D45: 2320000 | E45: 0.2329 | F45: =E45*D45 -> 540328 | G45: ='Sheet7 (2)'!AN360 -> 540328 | H45: ='Sheet7 (2)'!AO360 -> 0 | I45: 45836 | J45: Shipped | O45: =H45 -> 0 | P45: 0.9
A46: TW | B46: TJTW-60 | C46: 0.16*820*Coil | D46: 109.252 | E46: 6380 | F46: =E46*D46 -> 697027.76 | G46: =F46 -> 697027.76 | H46: =F46-G46 -> 0 | I46: 45823 | J46: Shipped
A47: TW | B47: TJTW-60 | C47: 0.165*875*Coil | D47: 25.515 | E47: 6480 | F47: =E47*D47 -> 165337.2 | G47: =F47 -> 165337.2 | H47: =F47-G47 -> 0 | I47: 45818 | J47: Shipped | O47: =H46 -> 0
A48: TW | B48: TJTW-60 | C48: 0.17*875*Coil | D48: 26.005 | E48: 6380 | F48: =E48*D48 -> 165911.9 | G48: =41595.04+124316.86 -> 165911.9 | H48: =F48-G48 -> 0 | I48: 45818 | J48: Shipped
A49: TW | B49: TJTW-60-1 | C49: 0.16*820*Coil | D49: 6.248 | E49: 6380 | F49: =E49*D49 -> 39862.24 | G49: 39862.24 | H49: =F49-G49 -> 0 | I49: 45861 | J49: Shipped
A50: TW | B50: TJTW-61-4 | C50: 0.18*905*836.5 2.8/2.8 T4 BA | D50: 7.918 | E50: 6570 | F50: =E50*D50 -> 52021.26 | G50: 52021.26 | H50: =F50-G50 -> 0 | I50: 45853 | J50: Shipped | O50: =H50*R50 -> 0 | R50: 0.9
A51: TW | B51: TJTW-61-3 | C51: 0.18*905*836.5 2.8/2.8 T4 BA | D51: 149.193 | E51: 6575 | F51: =E51*D51 -> 980943.97 | G51: 980943.97 | H51: =F51-G51 -> 0 | I51: 45853 | J51: Shipped
A52: TW | B52: TJTW-61-6 | C52: 0.17*905*836.5 2.8/2.8 T4 BA | D52: 10.605 | E52: 6720 | F52: =E52*D52 -> 71265.6 | G52: =69674.85+9828-6377.3075-1859.9425 -> 71265.6 | H52: =F52-G52 -> 0 | I52: 45853 | J52: Shipped | O52: =H52*R50 -> 0
A53: TW | B53: TJTW-61-3 | C53: 0.17*905*836.5 2.8/2.8 T4 BA | D53: 13.616 | E53: 6725 | F53: =E53*D53 -> 91567.6 | G53: 91567.6 | H53: =F53-G53 -> 0 | I53: 45853 | J53: Shipped
A54: TW | B54: TJTW-61-4 | C54: 0.17*905*836.5 2.8/2.8 T4 BA | D54: 27.27 | E54: 6720 | F54: =E54*D54 -> 183254.4 | G54: 183254.4 | H54: =F54-G54 -> 0 | I54: 45853 | J54: Shipped
A55: TW | B55: TJTW-61-5 | C55: 0.17*905*836.5 2.8/2.8 T4 BA | D55: 94.602 | E55: 6720 | F55: =E55*D55 -> 635725.44 | G55: 635725.44 | H55: =F55-G55 -> 0 | I55: 45853 | J55: Shipped
A56: TW | B56: TJTW-61-4 | C56: 0.17*818*913.6 2.8/2.8 T4 BA | D56: 19.695 | E56: 6720 | F56: =E56*D56 -> 132350.4 | G56: 132350.4 | H56: =F56-G56 -> 0 | I56: 45853 | J56: Shipped | L56: 7.14
A57: TW | B57: TJTW-61-5 | C57: 0.17*818*913.6 2.8/2.8 T4 BA | D57: 69.291 | E57: 6720 | F57: =E57*D57 -> 465635.52 | G57: 465635.52 | H57: =F57-G57 -> 0 | I57: 45853 | J57: Shipped
A58: TW | B58: TJTW-61-6 | C58: 0.18*900*712 2.8/2.8 T3 BA | D58: 52.223 | E58: 6570 | F58: =E58*D58 -> 343105.11 | G58: 343105.11 | H58: =F58-G58 -> 0 | I58: 45853 | J58: shipped | L58: 7.14 | O58: 0.9
A59: TW | B59: TJTW-61-6 | C59: 0.17*857*730 2.8/2.8 T4 BA | D59: 46.172 | E59: 6720 | F59: =E59*D59 -> 310275.84 | G59: 310275.84 | H59: =F59-G59 -> 0 | I59: 45853 | J59: shipped | L59: 7.14
A60: TW | B60: TJTW-61-2 | C60: 0.18*905*669.5 2.8/2.8 T4 BA | D60: =54.54 -> 54.54 | E60: 6575 | F60: =E60*D60 -> 358600.5 | G60: 358600.5 | H60: =F60-G60 -> 0 | I60: 45853 | J60: Shipped | L60: 7.14 | O60: =H60 -> 0
A61: TW | B61: TJTW-61-4 | C61: 0.18*822*764.2 2.8/2.8 T4 BA | D61: 81.355 | E61: 6570 | F61: =E61*D61 -> 534502.35 | G61: 534502.35 | H61: =F61-G61 -> 0 | I61: 45853 | J61: Shipped | L61: 7.14 | O61: =H61*R50 -> 0
A62: TW | B62: TJTW-61-1 | C62: 0.18*905*669.5 2.8/2.8 T4 BA | D62: 109.08 | E62: 6500 | F62: =E62*D62 -> 709020 | G62: 709020 | H62: =F62-G62 -> 0 | I62: 45853 | J62: Shipped | L62: 7.14
A63: TW | B63: TJTW-62 | C63: 0.3*790*850 2.0/2.0 T3 | D63: =1.502*19+1.85 -> 30.388 | E63: 5500 | F63: =E63*D63 -> 167134 | G63: 167134 | H63: =F63-G63 -> 0 | I63: 45823 | J63: Shipped
A64: TW | B64: TJTW-62 | C64: 0.3*790*855 2.0/2.0 T3 | D64: =1.511*6+1.193 -> 10.259 | E64: 5500 | F64: =E64*D64 -> 56424.5 | G64: 56424.5 | H64: =F64-G64 -> 0 | I64: 45823 | J64: Shipped
A65: TW | B65: TJTW-62 | C65: 0.31*1000*665 2.0/2.0 T3 | D65: 17.179 | E65: 5480 | F65: =E65*D65 -> 94140.92 | G65: 94140.92 | H65: =F65-G65 -> 0 | I65: 45823 | J65: Shipped | O65: =H63 -> 0
A66: TW | B66: TJTW-62 | C66: 0.31*960*640 2.0/2.0 T3 | D66: 17.27 | E66: 5480 | F66: =E66*D66 -> 94639.6 | G66: 94639.6 | H66: =F66-G66 -> 0 | I66: 45823 | J66: Shipped
A67: TW | B67: TJTW-63 | C67: 0.155*963*961 2.0/2.0 TH 620 | D67: 35.054 | E67: 6430 | F67: =E67*D67 -> 225397.22 | G67: 225397.22 | H67: =F67-G67 -> 0 | I67: 45823 | J67: Shipped | O67: =H67 -> 0
A68: TW | B68: TJTW-63 | C68: 0.155*931.927 2.0/2.0 TH 620 | D68: 33.915 | E68: 6430 | F68: =E68*D68 -> 218073.45 | G68: =218073.45 -> 218073.45 | H68: =F68-G68 -> 0 | I68: 45823 | J68: Shipped
A69: TW | B69: TJTW-64 | C69: 0.20х751х710.7 2.0/2.0 Т4 | D69: 14.79 | E69: 5860 | F69: =E69*D69 -> 86669.4 | G69: 86669.4 | H69: =F69-G69 -> 0 | I69: 45838 | J69: Shipped | O69: =H69 -> 0
A70: TW | B70: TJTW-64 | C70: 0.22х875х890 2.0/2.0 T3 | D70: 11.215 | E70: 5710 | F70: =E70*D70 -> 64037.65 | G70: 64037.65 | H70: =F70-G70 -> 0 | I70: 45838 | J70: Shipped
A71: TW | B71: TJTW-65 | C71: sample | F71: 126922.58 | G71: 126922.58 | H71: =F71-G71 -> 0 | I71: 45839 | J71: Shipped
A72: NF | B72: TJTW-66 | C72: TFS EOE 72.9 BPAni FREE | D72: 1960400 | E72: 0.0178 | F72: =E72*D72 -> 34895.12 | G72: =6960.52+27934.6 -> 34895.12 | H72: =F72-G72 -> 0 | I72: 45814 | J72: shipped | L72: =I72+97 -> 45911 | O72: =H72 -> 0
A73: TW | B73: TJTW-67 | C73: 0.16*892*808.4 2.0/2.0 Т4 Stone BA | D73: 136.664 | E73: 6150 | F73: =E73*D73 -> 840483.6 | G73: 840483.6 | H73: =F73-G73 -> 0 | I73: 45867 | J73: shipped
A74: TW | B74: TJTW-67 | C74: 0.15*868*872.4 1.0/1.0 DR9 Stone BA | D74: 24.544 | E74: 6000 | F74: =E74*D74 -> 147264 | G74: 147264 | H74: =F74-G74 -> 0 | I74: 45867 | J74: shipped | O74: =H74*90% -> 0
A75: TW | B75: TJTW-67-2 | C75: 0.16*892*808.4 2.0/2.0 Т4 Stone BA | D75: 6.268 | E75: 6150 | F75: =E75*D75 -> 38548.2 | G75: =36981.2+1567 -> 38548.2 | H75: =F75-G75 -> 0 | I75: 45926 | J75: Shipped
A76: TW | B76: TJTW-67-3 | C76: 0.16*892*808.4 2.0/2.0 Т4 Stone BA | D76: 3.406 | E76: 6150 | F76: =E76*D76 -> 20946.9 | G76: 20946.9 | H76: =F76-G76 -> 0 | I76: 45945 | J76: Shipped
A77: TW | B77: TJTW-68 | C77: EOE 99.8 0.22 #401 | D77: 2097600 | E77: 0.23 | F77: =E77*D77*0.3 -> 144734.4 | G77: 144734.4 | H77: =F77-G77 -> 0 | I77: 45834 | J77: shipped
A78: TW | B78: TJTW-68 | F78: =D77*E77*0.7 -> 337713.6 | G78: =130260.96+207452.64 -> 337713.6 | H78: =F78-G78 -> 0 | I78: 45847 | J78: shipped | L78: 45863 | O78: =H78 -> 0
A79: TW | B79: TJTW-69 | C79: 0.16*875*Coil | D79: 74.548 | E79: 5980 | F79: =E79*D79 -> 445797.04 | G79: 445797.04 | H79: =F79-G79 -> 0 | I79: 45859 | J79: Shipped | L79: 45863 | O79: =H79*#REF! -> #REF!
A80: TW | B80: TJTW-70-2 | C80: 0.18*862*783 2.8/2.8 T5 | D80: 25.585 | E80: =280+5750 -> 6030 | F80: =E80*D80 -> 154277.55 | G80: =162810-8321.39999999999-211.050000000017 -> 154277.55 | H80: =F80-G80 -> 0 | I80: 45920 | J80: Shipped
A81: TW | B81: TJTW-70-2 | C81: 0.18*890*C | D81: 25.39 | E81: =280+5750 -> 6030 | F81: =E81*D81 -> 153101.7 | G81: =31477.55+579162-41075.96+8321.39999999999+147523.95-1567-20946.9-541282.5-8510.84000000014 -> 153101.7 | H81: =F81-G81 -> 0 | I81: 45928 | J81: Shipped
A82: TW | B82: TJTW-70-2 | C82: 0.17*944*795 2.8/2.8 T4 | D82: 48.865 | E82: =280+5850 -> 6130 | F82: =E82*D82 -> 299542.45 | G82: =331020-31477.55 -> 299542.45 | H82: =F82-G82 -> 0 | I82: 45920 | J82: Shipped
A83: TW | B83: TJTW-70-3 | C83: 0.18*880*824 2.8/2.8 T3 | D83: 21.729 | E83: =280+5700 -> 5980 | F83: =E83*D83 -> 129939.42 | G83: =161460-31520.58 -> 129939.42 | H83: =F83-G83 -> 0 | I83: 45920 | J83: Shipped
A84: TW | B84: TJTW-70-3 | C84: 0.18*928*934.7 2.8/2.8 T5 | D84: 32.594 | E84: =280+5750 -> 6030 | F84: =E84*D84 -> 196541.82 | G84: =31520.58+162810+2211.23999999999 -> 196541.82 | H84: =F84-G84 -> 0 | I84: 45920 | J84: Shipped
A85: TW | B85: TJTW-70 | C85: 0.16*892*808.4 2.0/2.0 T4 | D85: 116.855 | E85: =5480+340 -> 5820 | F85: =E85*D85*0.3 -> 204028.83 | G85: 204028.83 | H85: =F85-G85 -> 0 | I85: 45825
A86: TW | B86: TJTW-70 | F86: =E85*D85*0.7 -> 476067.27 | G86: 476067.27 | H86: =F86-G86 -> 0 | I86: =I85+50 -> 45875
A87: TW | B87: TJTW-70-3 | C87: 0.2*893*808.4 2.8/2.8 T3 | D87: 33.724 | E87: =280+5500 -> 5780 | F87: =E87*D87 -> 194924.72 | G87: =156060-2211.23999999999+41075.96 -> 194924.72 | H87: =F87-G87 -> 0 | I87: 45920 | J87: Shipped
A88: TW | B88: TJTW-70 | C88: 0.15*868*872.4 1.0/1.0 DR9 | D88: 78.578 | E88: =5150+340 -> 5490 | F88: =E88*D88*0.3 -> 129417.97 | G88: 129417.97 | H88: =F88-G88 -> 0 | I88: 45825 | P88: =H88*90% -> 0
A89: TW | B89: TJTW-70 | F89: =E88*D88*0.7 -> 301975.25 | G89: 301975.25 | H89: =F89-G89 -> 0 | I89: =I88+50 -> 45875
A90: NBE | B90: NBE-1 | C90: Tool for Lid diameter 200 mm, | D90: 1 | E90: 74530 | F90: =E90*D90 -> 74530 | G90: 74530 | H90: =F90-G90 -> 0 | I90: 45807 | J90: shipped
A91: NBE | B91: NBE-3 | C91: Tool for Lid diameter 200 mm, | D91: 1 | E91: 103000 | F91: =E91*D91 -> 103000 | G91: 103000 | H91: =F91-G91 -> 0 | I91: 45807
A92: NBE | B92: NBE-4 | C92: 0.22*765*1040 2.0/2.0 TS260(T3) | D92: 18.29 | E92: 7000 | F92: =E92*D92 -> 128030 | G92: =F92 -> 128030 | H92: =F92-G92 -> 0 | I92: 45807 | J92: shipped
A93: NBE | B93: NBE-4-2 | C93: 0.18*712*826 | D93: 0.769 | E93: 8500 | F93: =E93*D93 -> 6536.5 | G93: =F93 -> 6536.5 | H93: =F93-G93 -> 0 | I93: 45807 | J93: shipped
A94: NBE | B94: NBE-5 | C94: 0,23x905x720 with lamination | D94: 24.464 | E94: 7003 | F94: =E94*D94 -> 171321.39 | G94: 171321.39 | H94: =F94-G94 -> 0.002 | I94: 45838 | L94: =I94+22 -> 45860 | O94: =9316+124316.86+25022.02+6230.67+10658.05+34895.12+130260.96 -> 340699.68
A95: NBE | B95: NBE-5-2 | C95: 0,23x905x720 with lamination | D95: 6.654 | E95: 7003 | F95: =E95*D95 -> 46597.962 | G95: 46597.96 | H95: =F95-G95 -> 0.002 | I95: 45838 | O95: =9316+124316.86+25022.02+6230.67+10658.05+34895.12+130260.96 -> 340699.68
A96: NBE | B96: NBE-7 | C96: sample | F96: =141135.57+8065.77 -> 149201.34 | G96: =141135.57+8065.77 -> 149201.34 | H96: =F96-G96 -> 0 | I96: 45846 | J96: shipped | L96: =I96+3 -> 45849 | N96: 8065.77处理成附加服务费
A97: PT | B97: PT-1-3 | C97: 0.26*31.8 TH620 | D97: 81.733 | E97: 9385 | F97: =E97*D97 -> 767064.2 | G97: =204120+562944.21 -> 767064.21 | H97: =F97-G97 -> -0.0049999999 | I97: 45827 | J97: shipped | O97: 68
A98: PT | B98: PT-2 | C98: 0,16 896х1057 ТН 550 2,8/2,8 CА | D98: 27.563 | E98: =9700+960 -> 10660 | F98: =E98*D98 -> 293821.58 | G98: 293821.58 | H98: =F98-G98 -> 0 | I98: 45838 | L98: 2025/7/8 + 2025/7/25
A99: PT | B99: PT-2 | C99: 0,16 862х922 ТН 620 2,8/2,8 CА | D99: 27.666 | E99: =9700+960 -> 10660 | F99: =E99*D99 -> 294919.56 | G99: 294919.56 | H99: =F99-G99 -> 0 | I99: 45838 | L99: 2025/7/8 + 2025/7/25
A100: PT | B100: PT-3 | C100: 0.14*975*941 ТН520 СА 2.8/2.8 | D100: 7.665 | E100: 9540 | F100: =E100*D100 -> 73124.1 | G100: 73124.1 | H100: =F100-G100 -> 0 | I100: 45838 | L100: =I100+20 -> 45858
...

Sheet Varnish
A1: PROFORMA Order（外贸订单 预售发票） | R1: Order Production（内贸订单） | AH1: Prepared（准备好的） | AN1: shipments
A2: No | B2: Data 日期 | C2: INV No 发票号 | D2: SPEC 规格 | E2: INV No 发票号 | G2: Preparation date 货好日期 | H2: Buyer 买家 | I2: SPEC 规格 | J2: QTY 数量 | K2: CNY/ton 单价 | L2: Total 总价 | M2: RECEIVABLE ADV 应收预付款 | N2: Received ADV 已收到预付款 | O2: Balance 尾款 | R2: Supplyer 供应商 | S2: Inv No 发票号（供应商） | T2: Order date 下单日期 | U2: Preparation date 货好时间 | V2: QTY 数量 | W2: CNY/ton 单价 | X2: Total 总价 | Y2: PAID ADV 已付（供应商） | Z2: Balance 尾款（供应商） | AA2: QTY CASH 数量 现金 | AB2: CNY/ton CASH 单价 现金 | AC2: Total CASH 总价 现金 | AD2: PAID ADV CASH 已付现金（供应商） | AE2: Balance CASH 尾款现金（供应商） | AH2: QTY 数量 | AI2: CNY/ton 单价 | AJ2: Total 总价 | AK2: Received ADV 已收到预付款 | AL2: Balance 国外尾款 | AN2: QTY 出口数量 | AO2: CNY/ton 出口单价 | AP2: Total 出口总价 | AQ2: Received 已收到预付款 | AR2: PAID 国外已付 | AS2: Balance 国外尾款 | AT2: Agents 货代名称 | AU2: Line 船公司 | AV2: ETD 开船时间 | AW2: SEA RATE 海运运费 | AX2: Balance MT | AY2: Status
B3: 45215 | C3: TJTW-8-1 | D3: 0.18*905*669.5 | E3: TJTW-8-1 | H3: TW | I3: 0.18*905*669.5 | J3: 81 | K3: 6950 | L3: =J3*K3 -> 562950 | R3: ZM | V3: 81.81 | W3: 6750 | X3: =V3*W3 -> 552217.5 | AH3: 81.81 | AI3: 6950 | AJ3: =AI3*AH3 -> 568579.5 | AN3: 81.81 | AO3: 6950 | AP3: =AO3*AN3 -> 568579.5 | AQ3: 0 | AS3: =AQ3-AP3 -> -568579.5
B4: 45215 | C4: TJTW-8-2 | D4: 0.18*905*669.5 | E4: TJTW-8-2 | H4: TW | I4: 0.18*905*669.5 | J4: 81 | K4: 6950 | L4: =J4*K4 -> 562950 | R4: ZM | V4: 82.298 | W4: 6750 | X4: =V4*W4 -> 555511.5 | AH4: 82.298 | AI4: 6950 | AJ4: =AI4*AH4 -> 571971.1 | AN4: 82.298 | AO4: 6950 | AP4: =AO4*AN4 -> 571971.1 | AQ4: 607500 | AS4: =AQ4-AP4 -> 35528.9
B5: 45215 | C5: TJTW-8-3 | D5: 0.18*905*836.5 | E5: TJTW-8-3 | H5: TW | I5: 0.18*905*836.5 | J5: 81 | K5: 9375 | L5: =J5*K5 -> 759375 | R5: ZM | V5: 81.651 | W5: 9150 | X5: =V5*W5 -> 747106.65 | AH5: 81.651 | AI5: 9375 | AJ5: =AI5*AH5 -> 765478.12 | AN5: 81.651 | AO5: 9375 | AP5: =AO5*AN5 -> 765478.12 | AQ5: 59489.84 | AS5: =AQ5-AP5 -> -705988.29
B6: 45215 | C6: TJTW-8-4 | D6: 0.18*905*836.5 | E6: TJTW-8-4 | H6: TW | I6: 0.18*905*836.5 | J6: 81 | K6: 9375 | L6: =J6*K6 -> 759375 | R6: ZM | V6: 81.473 | W6: 9150 | X6: =V6*W6 -> 745477.95 | AH6: 81.473 | AI6: 9375 | AJ6: =AI6*AH6 -> 763809.38 | AN6: 81.473 | AO6: 9375 | AP6: =AO6*AN6 -> 763809.38 | AQ6: 1800000 | AS6: =AQ6-AP6 -> 1036190.6
B7: 45216 | C7: 国外打款 | E7: 国外打款 | H7: TW | AQ7: 202848.26 | AS7: =AQ7-AP7 -> 202848.26
B8: 45212 | C8: TJTW-11 | D8: #401 ETP BPA FREE | E8: TJTW-11 | H8: TW | I8: #401 ETP BPA FREE | J8: 933520 | K8: 0.27 | L8: =J8*K8 -> 252050.4 | R8: ZM | V8: 933520 | W8: 0.27 | X8: =V8*W8 -> 252050.4 | AH8: 933520 | AI8: 0.244 | AJ8: =AH8*AI8 -> 227778.88 | AN8: 933520 | AO8: 0.244 | AP8: =AN8*AO8 -> 227778.88 | AQ8: 152976.6 | AS8: =AQ8-AP8 -> -74802.28
D9: #401 TFS BPA FREE | I9: #401 TFS BPA FREE | J9: 478800 | K9: 0.265 | L9: =J9*K9 -> 126882 | R9: ZM | V9: 478800 | W9: 0.265 | X9: =V9*W9 -> 126882 | AH9: 478800 | AI9: 0.24 | AJ9: =AH9*AI9 -> 114912 | AN9: 478800 | AO9: 0.24 | AP9: =AN9*AO9 -> 114912 | AS9: =AQ9-AP9 -> -114912
D10: #401 TFS | I10: #401 TFS | J10: 478800 | K10: 0.26 | L10: =J10*K10 -> 124488 | R10: ZM | V10: 478800 | W10: 0.26 | X10: =V10*W10 -> 124488 | AH10: 478800 | AI10: 0.235 | AJ10: =AH10*AI10 -> 112518 | AN10: 478800 | AO10: 0.235 | AP10: =AN10*AO10 -> 112518 | AS10: =AQ10-AP10 -> -112518
B11: 45440 | C11: TJTW-22 | D11: 72.9 mm 0.19#300 | E11: TJTW-22 | H11: TW | I11: 72.9 mm 0.19#300 | J11: 1956050 | K11: 0.01832 | L11: =J11*K11 -> 35834.836 | R11: ZM | V11: 1956050 | W11: 0.137 | X11: =V11*W11 -> 267978.85 | AH11: 1956050 | AI11: 0.01832 | AJ11: =AH11*AI11 -> 35834.836 | AN11: 1956050 | AO11: 0.01832 | AP11: =AN11*AO11 -> 35834.836 | AQ11: 7114.8 | AS11: =AQ11-AP11 -> -28720.036
H12: TW | AQ12: 28559.58 | AS12: =AQ12-AP12 -> 28559.58
B13: 45544 | C13: TJTW-33 | D13: 0.18*822*764.2 | E13: TJTW-33 | H13: TW | I13: 0.18*822*764.2 | J13: 54 | K13: 6280 | L13: =J13*K13 -> 339120 | N13: 99000 | O13: =L13-N13 -> 240120 | R13: ZM | S13: ZM20240918-A1 | T13: 45553 | U13: =T13+60 -> 45613 | V13: 50 | W13: 6100 | X13: =V13*W13 -> 305000 | AQ13: 99000 | AS13: =AR13+AQ13-AP13 -> 99000
C14: TJTW-33-1 | E14: TJTW-33-1 | H14: TW | AH14: 41.339 | AI14: 6350 | AJ14: =AH14*AI14 -> 262502.65 | AN14: 41.339 | AO14: 6350 | AP14: =AN14*AO14 -> 262502.65 | AS14: =AR14+AQ14-AP14 -> -262502.65
B15: 45546 | C15: TJTW-35 | D15: 0.16X875xC | E15: TJTW-35 | G15: =B15+60 -> 45606 | H15: TW | I15: 0.16X875xC | J15: 270 | K15: 6160 | L15: =J15*K15 -> 1663200 | N15: 608400 | O15: =L15-N15 -> 1054800 | R15: CRC | S15: BJHS-XWST-241022-01 | T15: 45587 | U15: =T15+60 -> 45647 | V15: 312.365 | W15: 3660 | X15: =V15*W15 -> 1143255.9 | Y15: 1143255.9 | Z15: =X15-Y15 -> 0 | AH15: 264.507 | AI15: 6160 | AJ15: =AH15*AI15 -> 1629363.1 | AN15: =AH15 -> 264.507 | AO15: 6160 | AP15: =AN15*AO15 -> 1629363.1 | AQ15: =N15 -> 608400 | AR15: 1080000 | AS15: =AR15+AQ15-AP15 -> 59036.88 | AT15: ANDY | AU15: EMC | AV15: 45635 | AW15: 2800 | AX15: =AH15-AN15 -> 0 | AY15: closed
S16: обрубки 修边 | AA16: 312.365 | AB16: 30 | AC16: =AA16*AB16 -> 9370.95 | AD16: 0 | AE16: =AC16-AD16 -> 9370.95 | AY16: closed
S17: продажа обрубков 卖修边 | V17: 35.258 | W17: -3200 | X17: =V17*W17 -> -112825.6 | Y17: =X17 -> -112825.6 | Z17: =Y17 -> -112825.6 | AA17: 0.63659575 | AB17: -2300 | AC17: =AA17*AB17 -> -1464.1702 | AY17: closed
S18: Логистика 运费 | AA18: 275.84 | AB18: 20 | AC18: =AA18*AB18 -> 5516.8 | AY18: closed
R19: YH | S19: BZJY202411-18 | T19: 45610 | U19: =T19+21 -> 45631 | V19: 263.883 | W19: 810 | X19: =V19*W19 -> 213745.23 | Y19: 213745.23 | Z19: =X19-Y19 -> 0 | AY19: closed
S20: Логистика 运费 | V20: 263.883 | W20: 30 | X20: =V20*W20 -> 7916.49 | Z20: =X20-Y20 -> 7916.49 | AY20: closed
R21: JHL | S21: Олово 镀锡 | T21: 45627 | U21: 45627 | V21: 264.507 | W21: 1260 | X21: =V21*W21 -> 333278.82 | Y21: 333278.82 | Z21: =X21-Y21 -> 0 | AY21: closed
AY22: closed
B23: 45560 | C23: TJTW-37 | D23: 0.21x894x1038 | E23: TJTW-37 | G23: =B23+60 -> 45620 | H23: TW | I23: 0.21x894x1038 | J23: 48 | K23: 6490 | L23: =J23*K23 -> 311520 | N23: =159057/2+388000/2 -> 273528.5 | O23: =L23-N23 -> 37991.5 | R23: CRC | S23: BJHS-XWST-241022-01 | T23: 45589 | U23: =T23+60 -> 45649 | V23: 49.09 | W23: 3660 | X23: =V23*W23 -> 179669.4 | Y23: =X23 -> 179669.4 | Z23: =X23-Y23 -> 0 | AH23: 42.337 | AI23: 5892 | AJ23: =AI23*AH23 -> 249449.6 | AK23: =N23 -> 273528.5 | AL23: =AJ23-AK23 -> -24078.896 | AN23: 42.503 | AO23: 5892 | AP23: =AO23*AN23 -> 250427.68 | AR23: 388000 | AS23: =AQ23+AR23-AP23 -> 137572.32
S24: обрубки 修边 | AA24: 49.09 | AB24: 30 | AC24: =AA24*AB24 -> 1472.7 | AD24: 0 | AE24: =AC24-AD24 -> 1472.7
S25: продажа обрубков 卖修边 | V25: 4.68 | W25: -3200 | X25: =V25*W25 -> -14976 | Y25: =X25 -> -14976 | Z25: =Y25 -> -14976 | AA25: 0.10004477 | AB25: -2300 | AC25: =AA25*AB25 -> -230.10298
S26: Логистика 运费 | AA26: 44.68 | AB26: 20 | AC26: =AA26*AB26 -> 893.6
R27: YH | S27: BZJY202411-18 | T27: 45610 | U27: =T27+21 -> 45631 | V27: 42.214 | W27: 650 | X27: =V27*W27 -> 27439.1 | Z27: =X27-Y27 -> 27439.1
S28: Логистика 运费 | V28: 42.214 | W28: 30 | X28: =V28*W28 -> 1266.42 | Z28: =X28-Y28 -> 1266.42
R29: JHL | S29: Олово 镀锡 | T29: 45627 | U29: 45627 | V29: 42.337 | W29: 1035 | X29: =V29*W29 -> 43818.795 | Z29: =X29-Y29 -> 43818.795
B30: 45560 | C30: TJTW-37 | D30: 0.16x960x924 | E30: TJTW-37 | G30: =B30+60 -> 45620 | H30: TW | I30: 0.16x960x924 | J30: 48 | K30: 6980 | L30: =J30*K30 -> 335040 | N30: =159057/2+388000/2 -> 273528.5 | O30: =L30-N30 -> 61511.5 | R30: CRC | S30: BJHS-XWST-241022-01 | T30: 45589 | U30: =T30+60 -> 45649 | V30: 49.235 | W30: 3660 | X30: =V30*W30 -> 180200.1 | Y30: =X30 -> 180200.1 | Z30: =X30-Y30 -> 0 | AH30: 44.592 | AI30: 6282 | AJ30: =AI30*AH30 -> 280126.94 | AK30: =N30 -> 273528.5 | AL30: =AJ30-AK30 -> 6598.444 | AN30: 45.198 | AO30: 6282 | AP30: =AO30*AN30 -> 283933.84 | AR30: 159057 | AS30: =AQ30+AR30-AP30 -> -124876.84
S31: обрубки 修边 | AA31: 49.235 | AB31: 30 | AC31: =AA31*AB31 -> 1477.05 | AD31: 0 | AE31: =AC31-AD31 -> 1477.05
S32: продажа обрубков 卖修边 | V32: 1.432 | W32: -3200 | X32: =V32*W32 -> -4582.4 | Y32: =X32 -> -4582.4 | Z32: =Y32 -> -4582.4 | AA32: 0.10034028 | AB32: -2300 | AC32: =AA32*AB32 -> -230.78265
S33: Логистика 运费 | AA33: 47.905 | AB33: 20 | AC33: =AA33*AB33 -> 958.1
R34: YH | S34: BZJY202411-18 | T34: 45610 | U34: =T34+21 -> 45631 | V34: 44.821 | W34: 810 | X34: =V34*W34 -> 36305.01 | Z34: =X34-Y34 -> 36305.01
S35: Логистика 运费 | V35: 44.821 | W35: 30 | X35: =V35*W35 -> 1344.63 | Z35: =X35-Y35 -> 1344.63
N36: =SUM(N23:N35) -> 547057 | O36: =SUM(O23:O35) -> 99503 | R36: JHL | S36: Олово 镀锡 | V36: 44.592 | W36: 1270 | X36: =V36*W36 -> 56631.84 | Z36: =X36-Y36 -> 56631.84 | AH36: =SUM(AH23:AH35) -> 86.929 | AJ36: =SUM(AJ23:AJ35) -> 529576.55
B37: 45587 | C37: PI TJTW-40 | D37: 0.18*905*836.5 | E37: TJTW-40 | G37: =B37+60 -> 45647 | H37: TW | I37: 0.18*905*836.5 | J37: 150 | K37: 9350 | L37: =J37*K37 -> 1402500 | N37: 300000 | O37: =L37-N37 -> 1102500 | R37: ZM | S37: ZM20241022-A1 | T37: 45587 | U37: =T37+60 -> 45647 | V37: 150 | W37: 9350 | X37: =V37*W37 -> 1402500 | AQ37: 566000 | AS37: =AQ37-AP37 -> 566000
B38: 45674 | C38: CI TJTW-40-1 | D38: 0.18*905*836.5 | E38: TJTW-40-1 | H38: TW | I38: 0.18*905*836.5 | R38: ZM | V38: 54.57 | W38: 6600 | X38: =V38*W38 -> 360162 | AH38: 54.57 | AI38: 6850 | AJ38: =AH38*AI38 -> 373804.5 | AK38: =566000/336.253*AH38 -> 91855.299 | AL38: =AK38-AJ38 -> -281949.2 | AN38: 54.57 | AO38: 6850 | AP38: =AN38*AO38 -> 373804.5 | AS38: =AQ38-AP38 -> -373804.5
B39: 45677 | C39: CI TJTW-40-2 | D39: 0.18*905*669.5 | E39: TJTW-40-2 | H39: TW | I39: 0.18*905*669.5 | R39: ZM | V39: 19.695 | W39: 6600 | X39: =V39*W39 -> 129987 | AH39: 19.695 | AI39: 6850 | AJ39: =AH39*AI39 -> 134910.75 | AK39: =566000/336.253*AH39 -> 33151.734 | AL39: =AK39-AJ39 -> -101759.02 | AN39: 19.695 | AO39: 6850 | AP39: =AN39*AO39 -> 134910.75 | AS39: =AQ39-AP39 -> -134910.75
B40: 45677 | C40: CI TJTW-40-2 | D40: 0.18*905*836.5 | H40: TW | R40: ZM | V40: 8.025 | W40: 6600 | X40: =V40*W40 -> 52965 | AH40: 8.025 | AI40: 6850 | AJ40: =AH40*AI40 -> 54971.25 | AK40: =566000/336.253*AH40 -> 13508.132 | AL40: =AK40-AJ40 -> -41463.118 | AN40: 8.025 | AO40: 6850 | AP40: =AN40*AO40 -> 54971.25 | AS40: =AQ40-AP40 -> -54971.25
B41: 45677 | C41: CI TJTW-40-3 | D41: 0.18*905*669.5 | E41: TJTW-40-3 | H41: TW | I41: 0.18*905*669.5 | R41: ZM | V41: 9.09 | W41: 6600 | X41: =V41*W41 -> 59994 | AH41: 9.09 | AI41: 6850 | AJ41: =AH41*AI41 -> 62266.5 | AK41: =566000/336.253*AH41 -> 15300.8 | AL41: =AK41-AJ41 -> -46965.7 | AN41: 9.09 | AO41: 6850 | AP41: =AN41*AO41 -> 62266.5 | AS41: =AQ41-AP41 -> -62266.5
B42: 45677 | C42: CI TJTW-40-3 | D42: 0.18*905*836.5 | E42: TJTW-40-3 | H42: TW | I42: 0.18*905*836.5 | R42: ZM | V42: 10.684 | W42: 6600 | X42: =V42*W42 -> 70514.4 | AH42: 10.684 | AI42: 6850 | AJ42: =AH42*AI42 -> 73185.4 | AK42: =566000/336.253*AH42 -> 17983.911 | AL42: =AK42-AJ42 -> -55201.489 | AN42: 10.684 | AO42: 6850 | AP42: =AN42*AO42 -> 73185.4 | AS42: =AQ42-AP42 -> -73185.4
B43: 45677 | C43: CI TJTW-40-4 | D43: 0.18*905*836.5 | E43: TJTW-40-4 | H43: TW | I43: 0.18*905*836.5 | R43: ZM | V43: 54.57 | W43: 6600 | X43: =V43*W43 -> 360162 | AH43: 54.57 | AI43: 6850 | AJ43: =AH43*AI43 -> 373804.5 | AK43: =566000/336.253*AH43 -> 91855.299 | AL43: =AK43-AJ43 -> -281949.2 | AN43: 54.57 | AO43: 6850 | AP43: =AN43*AO43 -> 373804.5 | AS43: =AQ43-AP43 -> -373804.5
B44: 45587 | C44: PI TJTW-40 | D44: 0.17*818*913.6 | E44: TJTW-40 | G44: =B44+60 -> 45647 | H44: TW | I44: 0.17*818*913.6 | J44: 25 | K44: 9600 | L44: =J44*K44 -> 240000 | N44: 50000 | O44: =L44-N44 -> 190000 | R44: ZM | S44: ZM20241022-A1 | T44: 45587 | U44: =T44+60 -> 45647 | V44: 25 | W44: 9600 | X44: =V44*W44 -> 240000 | AS44: =AQ44-AP44 -> 0
B45: 45677 | C45: CI TJTW-40-2 | D45: 0.17*818*913.6 VARNISH | E45: TJTW-40-2 | H45: TW | I45: 0.17*818*913.6 VARNISH | R45: ZM | V45: 14.243 | W45: 6750 | X45: =V45*W45 -> 96140.25 | AH45: 14.243 | AI45: 7000 | AJ45: =AH45*AI45 -> 99701 | AK45: =566000/336.253*AH45 -> 23974.62 | AL45: =AK45-AJ45 -> -75726.38 | AN45: 14.243 | AO45: 7000 | AP45: =AN45*AO45 -> 99701 | AS45: =AQ45-AP45 -> -99701
R46: BD | AA46: 14.243 | AB46: 2500 | AC46: =AA46*AB46 -> 35607.5 | AD46: 96900 | AE46: =AD46-AC46 -> 61292.5
B47: 45587 | C47: PI TJTW-40 | D47: 0.17*905*836.5 2.8/2.8 | E47: TJTW-40 | G47: =B47+60 -> 45647 | H47: TW | I47: 0.17*905*836.5 2.8/2.8 | J47: 108 | K47: 9600 | L47: =J47*K47 -> 1036800 | N47: 216000 | O47: =L47-N47 -> 820800 | R47: ZM | S47: ZM20241022-A1 | T47: 45587 | U47: =T47+60 -> 45647 | V47: 108 | W47: 9600 | X47: =V47*W47 -> 1036800
B48: 45677 | C48: CI TJTW-40-2 | D48: 0.17*905*836.5 2.8/2.8 | E48: TJTW-40-2 | H48: TW | I48: 0.17*905*836.5 | R48: ZM | V48: 16.948 | W48: 6750 | X48: =V48*W48 -> 114399 | AH48: 16.948 | AI48: 7000 | AJ48: =AH48*AI48 -> 118636 | AK48: =566000/336.253*AH48 -> 28527.829 | AL48: =AK48-AJ48 -> -90108.171 | AN48: 16.948 | AO48: 7000 | AP48: =AN48*AO48 -> 118636 | AS48: =AQ48-AP48 -> -118636
B49: 45677 | C49: CI TJTW-40-3 | D49: 0.17*905*836.5 2.8/2.8 | E49: TJTW-40-3 | H49: TW | I49: 0.17*905*836.5 | R49: ZM | V49: 49.995 | W49: 6750 | X49: =V49*W49 -> 337466.25 | AH49: 49.995 | AI49: 7000 | AJ49: =AH49*AI49 -> 349965 | AK49: =566000/336.253*AH49 -> 84154.402 | AL49: =AK49-AJ49 -> -265810.6 | AN49: 49.995 | AO49: 7000 | AP49: =AN49*AO49 -> 349965 | AS49: =AQ49-AP49 -> -349965
B50: 45677 | C50: CI TJTW-40-4 | D50: 0.17*905*836.5 2.8/2.8 | E50: TJTW-40-4 | H50: TW | I50: 0.17*905*836.5 | R50: ZM | V50: 54.54 | W50: 6750 | X50: =V50*W50 -> 368145 | AH50: 54.54 | AI50: 7000 | AJ50: =AH50*AI50 -> 381780 | AK50: =566000/336.253*AH50 -> 91804.802 | AL50: =AK50-AJ50 -> -289975.2 | AN50: 54.54 | AO50: 7000 | AP50: =AN50*AO50 -> 381780 | AS50: =AQ50-AP50 -> -381780
B51: 45587 | C51: PI TJTW-40 | D51: 0.17*905*836.5 2.0/2.0 | E51: TJTW-40 | G51: =B51+60 -> 45647 | H51: TW | I51: 0.17*905*836.5 2.0/2.0 | J51: 47 | K51: =6450+250 -> 6700 | L51: =J51*K51 -> 314900 | R51: ZM | S51: ZM20241231-A1 | T51: 45657 | V51: 47 | W51: 6450 | X51: =V51*W51 -> 303150
B52: 45677 | C52: CI TJTW-40-2 | D52: 0.17*905*836.5 VARNISH | E52: TJTW-40-2 | H52: TW | I52: 0.17*905*836.5 VARNISH | R52: ZM | V52: 22.725 | W52: 6450 | X52: =V52*W52 -> 146576.25 | AH52: 22.725 | AI52: 6700 | AJ52: =AH52*AI52 -> 152257.5 | AK52: =566000/336.253*AH52 -> 38252.001 | AL52: =AK52-AJ52 -> -114005.5 | AN52: 22.725 | AO52: 6700 | AP52: =AN52*AO52 -> 152257.5 | AS52: =AQ52-AP52 -> -152257.5
R53: BD | AA53: 22.725 | AB53: 2150 | AC53: =AA53*AB53 -> 48858.75 | AE53: =AD53-AC53 -> -48858.75
B54: 45677 | C54: CI TJTW-40-3 | D54: 0.17*905*669.5 | E54: TJTW-40-3 | H54: TW | I54: 0.17*905*669.5 | R54: ZM | V54: 21.168 | W54: 6450 | X54: =V54*W54 -> 136533.6 | AH54: 21.168 | AI54: 6700 | AJ54: =AH54*AI54 -> 141825.6 | AK54: =566000/336.253*AH54 -> 35631.171 | AL54: =AK54-AJ54 -> -106194.43 | AN54: 21.168 | AO54: 6700 | AP54: =AN54*AO54 -> 141825.6 | AS54: =AQ54-AP54 -> -141825.6
R55: ANDY | S55: THC | V55: 336.253 | W55: =X55/V55 -> 0
C56: TJTW-40-5 | D56: 0.18*905*669.5 2.8/2.8 | I56: 0.18*905*669.5 2.8/2.8 | V56: 0.693 | W56: 6850 | X56: =V56*W56 -> 4747.05 | Y56: =X56 -> 4747.05 | AH56: 0.693 | AI56: 6850 | AJ56: =AH56*AI56 -> 4747.05 | AN56: 0.693 | AO56: 6850 | AP56: =AN56*AO56 -> 4747.05 | AS56: =AQ56-AP56 -> -4747.05
C57: TJTW-40-5 | D57: 0.17*905*669.5 2.0/2.0 | I57: 0.17*905*669.5 2.0/2.0 | V57: 0.995 | W57: 6700 | X57: =V57*W57 -> 6666.5 | Y57: =X57 -> 6666.5 | AH57: 0.995 | AI57: 6700 | AJ57: =AH57*AI57 -> 6666.5 | AK57: 2309989 | AN57: 0.995 | AO57: 6700 | AP57: =AN57*AO57 -> 6666.5 | AQ57: 2309989 | AS57: =AQ57-AP57 -> 2303322.5
C58: TJTW-40-5 | D58: 0.17*905*836.5 2.0/2.0 | I58: 0.17*905*836.5 2.0/2.0 | V58: 1.354 | W58: =6450+2150 -> 8600 | X58: =V58*W58 -> 11644.4 | Y58: =X58 -> 11644.4 | Z58: 200000 | AA58: 1.354 | AB58: 2150 | AC58: =AA58*AB58 -> 2911.1 | AE58: =AD58-AC58 -> -2911.1 | AH58: 1.354 | AI58: =6450+2150 -> 8600 | AJ58: =AH58*AI58 -> 11644.4 | AN58: 1.354 | AO58: 6700 | AP58: =AN58*AO58 -> 9071.8 | AS58: =AQ58-AP58 -> -9071.8 | AT58: 200000
C59: TJTW-18-5 | D59: 0.17*818*913.6 | S59: 涂布费 | V59: 12.923 | W59: =2500/0.98 -> 2551.0204 | X59: =W59*V59 -> 32966.837 | Y59: =X59 -> 32966.837 | Z59: =Y59-X59 -> 0
C60: TJTW-18-6 | D60: 0.18*900*712 | S60: 涂布费 | V60: 1.292 | W60: =2400/0.98 -> 2448.9796 | X60: =W60*V60 -> 3164.0816 | Y60: =X60 -> 3164.0816 | Z60: =Y60-X60 -> 0
C61: TJTW-18-7 | D61: 0.18*900*712 | S61: 涂布费 | V61: 18.144 | W61: =2400/0.98 -> 2448.9796 | X61: =W61*V61 -> 44434.286 | Y61: =X61 -> 44434.286 | Z61: =Y61-X61 -> 0
C62: TJTW-18-8 | D62: 0.18*900*712 | S62: 涂布费 | V62: 12.096 | W62: =2400/0.98 -> 2448.9796 | X62: =W62*V62 -> 29622.857 | Y62: =X62 -> 29622.857 | Z62: =Y62-X62 -> 0
C63: TJTW-18-9 | D63: 0.18*900*712 | S63: 涂布费 | V63: 17.44 | W63: =2400/0.98 -> 2448.9796 | X63: =W63*V63 -> 42710.204 | Y63: =X63 -> 42710.204 | Z63: =Y63-X63 -> 0
C64: TJTW-18 | S64: 涂布费 | V64: =SUM(V59:V63) -> 61.895 | X64: =SUM(X59:X63) -> 152898.27 | Y64: =SUBTOTAL(9,Y56:Y63) -> 175956.22
C65: TJTW-40-2 | D65: 0.17*905*836.5 | S65: 涂布费 | V65: 22.725 | W65: =2150/0.98 -> 2193.8776 | X65: =W65*V65 -> 49855.867 | Y65: =X65 -> 49855.867 | Z65: =Y65-X65 -> 0
C66: TJTW-40-2 | D66: 0.17*818*913.6 | S66: 涂布费 | V66: 14.243 | W66: =2500/0.98 -> 2551.0204 | X66: =W66*V66 -> 36334.184 | Y66: =X66 -> 36334.184 | Z66: =Y66-X66 -> 0
C67: TJTW-40-5 | D67: 0.17*905*836.5 | S67: 涂布费 | V67: 1.354 | W67: =2150/0.98 -> 2193.8776 | X67: =W67*V67 -> 2970.5102 | Y67: =X67 -> 2970.5102 | Z67: =Y67-X67 -> 0
C68: TJTW-40 | S68: 涂布费 | V68: =SUM(V65:V67) -> 38.322 | X68: =SUM(X65:X67) -> 89160.561 | Y68: =SUBTOTAL(9,Y65:Y67) -> 89160.561
C69: TJTW-49 | D69: 0.17*818*913 | S69: 涂布费 | V69: 13.59 | W69: =2500/0.98 -> 2551.0204 | X69: =W69*V69 -> 34668.367 | Y69: =X69 -> 34668.367 | Z69: =Y69-X69 -> 0 | AA69: 7739,44 списали с инвойса 40-5
C70: TJTW-49 | S70: 涂布费 | V70: =V69 -> 13.59 | X70: =X69 -> 34668.367 | Y70: =SUBTOTAL(9,Y69) -> 34668.367
C71: TJTW-50-2 | D71: 0.17*905*836.5 VARNISH BPA FREE | S71: 涂布费 | V71: 43.501 | W71: 2551 | X71: =W71*V71 -> 110971.05 | Y71: =X71 -> 110971.05 | Z71: =Y71-X71 -> 0
D72: 0.18*905*836.5 VARNISH alum BPA | S72: 涂布费 | V72: 12.806 | W72: 1510.2 | X72: =W72*V72 -> 19339.621 | Y72: =X72 -> 19339.621 | Z72: =Y72-X72 -> 0 | AA72: GOD. INV 18-9 ( Final 2 244,26) INV -49 ( Final 26 928,93) INV-50-2 ( Final 226 899,56) INV-50-3 ( Final 139 131,54) INV 50-4 ( Final 177 832,39) INV-55 ( Final 286 795,92) INV-55-2 ( Final 15 459,18)
D73: 0.18*905*836.5 VARNISH gold+alum BPA | S73: 涂布费 | V73: 14.349 | W73: 2091.84 | X73: =W73*V73 -> 30015.812 | Y73: =X73 -> 30015.812 | Z73: =Y73-X73 -> 0
D74: 0.18*905*836.5 VARNISH gold+alum BPA FREE | S74: 涂布费 | V74: 27.184 | W74: 2448.98 | X74: =W74*V74 -> 66573.072 | Y74: =X74 -> 66573.072 | Z74: =Y74-X74 -> 0
C75: TJTW-50-3 | D75: 0.17*905*836.5 VARNISH BPA FREE | S75: 涂布费 | V75: 54.54 | W75: 2551 | X75: =W75*V75 -> 139131.54 | Y75: =X75 -> 139131.54 | Z75: =Y75-X75 -> 0
C76: TJTW-50-4 | D76: 0.17*905*836.5 VARNISH BPA FREE | S76: 涂布费 | V76: 9.047 | W76: 2551 | X76: =W76*V76 -> 23078.897 | Y76: =X76 -> 23078.897 | Z76: =Y76-X76 -> 0
D77: 0.18*905*836.5 VARNISH alum BPA FREE | S77: 涂布费 | V77: 63.191 | W77: 2448.98 | X77: =W77*V77 -> 154753.5 | Y77: =X77 -> 154753.5 | Z77: =Y77-X77 -> 0
C78: TJTW-50 | S78: 涂布费 | V78: =SUM(V71:V77) -> 224.618 | X78: =SUM(X71:X77) -> 543863.49 | Y78: =SUBTOTAL(9,Y71:Y77) -> 543863.49
C79: TJTW-55 | D79: 0.17*818*913 VARNISH BPA FREE | S79: 涂布费 | V79: 112.424 | W79: =2500/0.98 -> 2551.0204 | X79: =W79*V79 -> 286795.92 | Y79: =X79 -> 286795.92 | Z79: =Y79-X79 -> 0
C80: TJTW-55-2 | D80: 0.17*818*913 VARNISH BPA FREE | S80: 涂布费 | V80: 6.06 | W80: =W79 -> 2551.0204 | X80: =W80*V80 -> 15459.184 | Y80: =X80 -> 15459.184 | Z80: =Y80-X80 -> 0
C81: TJTW-55-2 | D81: 0.17*818*913 VARNISH BPA FREE | S81: 涂布费 | V81: =SUM(V79:V80) -> 118.484 | X81: =SUM(X79:X80) -> 302255.1 | Y81: =SUBTOTAL(9,Y79:Y80) -> 302255.1
C82: TJTW-56 | D82: 0.17*857*730 | S82: 涂布费 | V82: 27.104 | W82: =2500/0.98 -> 2551.0204 | X82: =W82*V82 -> 69142.857 | Y82: =X82 -> 69142.857 | Z82: =Y82-X82 -> 0
C83: =C82 -> TJTW-56 | D83: =D82 -> 0.17*857*730 | S83: 涂布费 | V83: =V82 -> 27.104 | X83: =X82 -> 69142.857 | Y83: =Y82 -> 69142.857
C84: TJTW-61-3 | D84: 0.18*905*836.5 2.8/2.8 T4 BA Gold/Alum+Gold, BPA FREE | H84: 涂布费 | K84: 162 | L84: 2449 | M84: 396738 | O84: 0 | S84: 涂布费 | V84: 136.113 | W84: 2449 | X84: =V84*W84 -> 333340.74 | Y84: 0 | Z84: =Y84-X84 -> -333340.74
C85: TJTW-61-3 | D85: 0.18*905*836.5 2.8/2.8 T4 BA Gold/Alum | S85: 涂布费 | V85: 13.08 | W85: 1510 | X85: =V85*W85 -> 19750.8 | Z85: =Y85-X85 -> -19750.8
C86: TJTW-61-3 | D86: 0.17*905*836.5 2.8/2.8 T4 BA Gold/Alum | H86: 涂布费 | K86: 140 | L86: 2551 | M86: 357140 | S86: 涂布费 | V86: 13.616 | W86: 1582 | X86: =V86*W86 -> 21540.512 | Z86: =Y86-X86 -> -21540.512
C87: TJTW-61-4 | D87: 0.17*818*913.6 2.8/2.8 T4 BA Gold/Alum+Gold, BPA FREE | H87: 涂布费 | K87: 108 | L87: 2551 | M87: 275508 | S87: 涂布费 | V87: 19.695 | W87: 2551 | X87: =V87*W87 -> 50241.945 | Z87: =Y87-X87 -> -50241.945
C88: TJTW-61-4 | D88: 0.18*905*836.5 2.8/2.8 T4 BA Gold/Aluminium+Gold,BPA FREE | S88: 涂布费 | V88: 7.918 | W88: 2449 | X88: =V88*W88 -> 19391.182 | Z88: =Y88-X88 -> -19391.182
C89: TJTW-61-4 | D89: 0.17*905*836.5 2.8/2.8 T4 BA Gold/Aluminium+Gold,BPA FREE | S89: 涂布费 | V89: 27.27 | W89: 2551 | X89: =V89*W89 -> 69565.77 | Z89: =Y89-X89 -> -69565.77
C90: TJTW-61-5 | D90: 0.17*905*836.5 2.8/2.8 T4 BA Gold/Aluminium+Gold,BPA FREE | S90: 涂布费 | V90: 94.602 | W90: 2551 | X90: =V90*W90 -> 241329.7 | Z90: =Y90-X90 -> -241329.7
C91: TJTW-61-5 | D91: 0.17*818*913.6 2.8/2.8 T4 BA Gold/Aluminium+Gold,BPA FREE | S91: 涂布费 | V91: 69.291 | W91: 2551 | X91: =V91*W91 -> 176761.34 | Z91: =Y91-X91 -> -176761.34
C92: TJTW-61-6 | D92: 0.18*900*712 2.8/2.8 T3 BA Gold/Aluminium+Gold,BPA FREE | H92: 涂布费 | K92: 54 | L92: 2449 | M92: 132246 | S92: 涂布费 | V92: 52.223 | W92: 2449 | X92: =V92*W92 -> 127894.13 | Z92: =Y92-X92 -> -127894.13
C93: TJTW-61-6 | D93: 0.17*857*730 2.8/2.8 T4 BA Gold/Aluminium+Gold,BPA FREE | H93: 涂布费 | K93: 54 | L93: 2551 | M93: 137754 | S93: 涂布费 | V93: 46.172 | W93: 2551 | X93: =V93*W93 -> 117784.77 | Z93: =Y93-X93 -> -117784.77
C94: TJTW-61-6 | D94: 0.17*905*836.5 2.8/2.8 T4 BA Gold/Aluminium+Gold,BPA FREE | S94: 涂布费 | V94: 10.605 | W94: 2551 | X94: =V94*W94 -> 27053.355 | Z94: =Y94-X94 -> -27053.355
C95: TJTW-61 | H95: 涂布费 | K95: 518 | M95: 1299386 | S95: 涂布费 | V95: =SUM(V84:V94) -> 490.585 | X95: =SUM(X84:X94) -> 1204654.2 | Y95: =SUM(Y84:Y94) -> 0 | Z95: =SUM(Z84:Z94) -> -1204654.2
C96: TJTW-74 | D96: 0.17*730*857 T4 2.8/2.8 | H96: 涂布费 | K96: 54 | L96: 2551 | M96: 137754 | S96: 涂布费 | V96: 54 | W96: 2551 | X96: 137754 | Z96: =374632.05+139198.9+418091.04+272732.25 -> 1204654.2
D97: 0.17*818*913 T4 2.8/2.8 | H97: 涂布费 | K97: 135 | L97: 2551 | M97: 344385 | S97: 涂布费 | V97: 135 | W97: 2551 | X97: 344385
D98: 0.18*900*712 T3 2.8/2.8 | H98: 涂布费 | K98: 25 | L98: 2449 | M98: 61225 | S98: 涂布费 | V98: 25 | W98: 2449 | X98: 61225
D99: 0.17*905*836.5 T4 2.8/2.8 | H99: 涂布费 | K99: 110 | L99: 2551 | M99: 280610 | S99: 涂布费 | V99: 110 | W99: 2551 | X99: 280610
D100: 0.18*905*836.5 T4 2.8/2.8 | H100: 涂布费 | K100: 220 | L100: 2449 | M100: 538780 | S100: 涂布费 | V100: 220 | W100: 2551 | X100: 538780
...

Sheet payment1
C1: Total | E1: TW | F1: BD | G1: NBE | H1: PT | I1: INDKS | J1: NF USD | K1: NF CNY 7,1 | L1: Client payments | M1: Balance
B2: Before | C2: =SUMIFS(payment!H2:H1436,payment!I2:I1436,">="&DATE(2024,6,1),payment!I2:I1436,"<="&DATE(2025,5,31)) -> 1.1641577e-11 | E2: =SUMIFS(payment!H2:H1436,payment!I2:I1436,">="&DATE(2024,6,1),payment!I2:I1436,"<="&DATE(2025,5,31),payment!A2:A1436,"=TW") -> 1.1641577e-11 | F2: 496767.44 | G2: =SUMIFS(payment!H2:H1436,payment!I2:I1436,">="&DATE(2024,6,1),payment!I2:I1436,"<="&DATE(2025,5,31),payment!A2:A1436,"=NBE") -> 0 | H2: =SUMIFS(payment!H2:H1436,payment!I2:I1436,">="&DATE(2024,6,1),payment!I2:I1436,"<="&DATE(2025,5,31),payment!A2:A1436,"=PT") -> 0 | I2: =SUMIFS(payment!H2:H1436,payment!I2:I1436,">="&DATE(2024,6,1),payment!I2:I1436,"<="&DATE(2025,5,31),payment!A2:A1436,"=IN") -> 0 | J2: =SUMIFS(payment!H2:H1436,payment!I2:I1436,">="&DATE(2024,6,1),payment!I2:I1436,"<="&DATE(2025,5,31),payment!A2:A1436,"=NF") -> 0 | K2: =J2*7.1 -> 0 | L2: =SUMIFS(payment!H2:H1436,payment!L2:L1436,">="&DATE(2024,6,1),payment!L2:L1436,"<="&DATE(2025,5,31)) -> 0 | M2: =payment!AH$1-C2+L2 -> 3512729.1
B3: June 1-7 | C3: =SUMIFS(payment!H2:H1436,payment!I2:I1436,">="&DATE(2025,6,1),payment!I2:I1436,"<="&DATE(2025,6,7)) -> 0 | E3: =SUMIFS(payment!H2:H1436,payment!I2:I1436,">="&DATE(2025,6,1),payment!I2:I1436,"<="&DATE(2025,6,7),payment!A2:A1436,"=TW") -> 0 | F3: =SUMIFS(payment!H2:H1436,payment!I2:I1436,">="&DATE(2025,6,1),payment!I2:I1436,"<="&DATE(2025,6,7),payment!A2:A1436,"=VARNISHED") -> 0 | G3: =SUMIFS(payment!H2:H1436,payment!I2:I1436,">="&DATE(2025,6,1),payment!I2:I1436,"<="&DATE(2025,6,7),payment!A2:A1436,"=NBE") -> 0 | H3: =SUMIFS(payment!H2:H1436,payment!I2:I1436,">="&DATE(2025,6,1),payment!I2:I1436,"<="&DATE(2025,6,7),payment!A2:A1436,"=PT") -> 0 | I3: =SUMIFS(payment!H2:H1436,payment!I2:I1436,">="&DATE(2025,6,1),payment!I2:I1436,"<="&DATE(2025,6,7),payment!A2:A1436,"=IN") -> 0 | J3: =SUMIFS(payment!H2:H1436,payment!I2:I1436,">="&DATE(2025,6,1),payment!I2:I1436,"<="&DATE(2025,6,7),payment!A2:A1436,"=NF") -> 0 | K3: =J3*7.1 -> 0 | L3: =SUMIFS(payment!H2:H1436,payment!L2:L1436,">="&DATE(2025,6,1),payment!L2:L1436,"<="&DATE(2025,6,7)) -> 0 | M3: =M2-C3+L3 -> 3512729.1
B4: June 8-15 | C4: =SUMIFS(payment!H2:H1436,payment!I2:I1436,">="&DATE(2025,6,8),payment!I2:I1436,"<="&DATE(2025,6,15)) -> 0 | E4: =SUMIFS(payment!H2:H1436,payment!I2:I1436,">="&DATE(2025,6,8),payment!I2:I1436,"<="&DATE(2025,6,15),payment!A2:A1436,"=TW") -> 0 | F4: =SUMIFS(payment!H2:H1436,payment!I2:I1436,">="&DATE(2025,6,8),payment!I2:I1436,"<="&DATE(2025,6,15),payment!A2:A1436,"=VARNISHED") -> 0 | G4: =SUMIFS(payment!H2:H1436,payment!I2:I1436,">="&DATE(2025,6,8),payment!I2:I1436,"<="&DATE(2025,6,15),payment!A2:A1436,"=NBE") -> 0 | H4: =SUMIFS(payment!H2:H1436,payment!I2:I1436,">="&DATE(2025,6,8),payment!I2:I1436,"<="&DATE(2025,6,15),payment!A2:A1436,"=PT") -> 0 | I4: =SUMIFS(payment!H2:H1436,payment!I2:I1436,">="&DATE(2025,6,8),payment!I2:I1436,"<="&DATE(2025,6,15),payment!A2:A1436,"=IN") -> 0 | J4: =SUMIFS(payment!H2:H1436,payment!I2:I1436,">="&DATE(2025,6,8),payment!I2:I1436,"<="&DATE(2025,6,15),payment!A2:A1436,"=NF") -> 0 | K4: =J4*7.1 -> 0 | L4: =SUMIFS(payment!H2:H1436,payment!L2:L1436,">="&DATE(2025,6,8),payment!L2:L1436,"<="&DATE(2025,6,15)) -> 0 | M4: =payment!AH$1-C4+L4 -> 3512729.1
B5: June 16-23 | C5: =SUMIFS(payment!H2:H1436,payment!I2:I1436,">="&DATE(2025,6,16),payment!I2:I1436,"<="&DATE(2025,6,23)) -> -0.0049999999 | E5: =SUMIFS(payment!H2:H1436,payment!I2:I1436,">="&DATE(2025,6,16),payment!I2:I1436,"<="&DATE(2025,6,23),payment!A2:A1436,"=TW") -> 0 | F5: =SUMIFS(payment!H2:H1436,payment!I2:I1436,">="&DATE(2025,6,16),payment!I2:I1436,"<="&DATE(2025,6,23),payment!A2:A1436,"=VARNISHED") -> 0 | G5: =SUMIFS(payment!H2:H1436,payment!I2:I1436,">="&DATE(2025,6,16),payment!I2:I1436,"<="&DATE(2025,6,23),payment!A2:A1436,"=NBE") -> 0 | H5: =SUMIFS(payment!H2:H1436,payment!I2:I1436,">="&DATE(2025,6,16),payment!I2:I1436,"<="&DATE(2025,6,23),payment!A2:A1436,"=PT") -> -0.0049999999 | I5: =SUMIFS(payment!H2:H1436,payment!I2:I1436,">="&DATE(2025,6,16),payment!I2:I1436,"<="&DATE(2025,6,23),payment!A2:A1436,"=IN") -> 0 | J5: =SUMIFS(payment!H2:H1436,payment!I2:I1436,">="&DATE(2025,6,16),payment!I2:I1436,"<="&DATE(2025,6,23),payment!A2:A1436,"=NF") -> 0 | K5: =J5*7.1 -> 0 | L5: =SUMIFS(payment!H2:H1436,payment!L2:L1436,">="&DATE(2025,6,16),payment!L2:L1436,"<="&DATE(2025,6,23)) -> 0 | M5: =M4-C5+L5 -> 3512729.1
B6: June 24-30 | C6: =SUMIFS(payment!H2:H1436,payment!I2:I1436,">="&DATE(2025,6,24),payment!I2:I1436,"<="&DATE(2025,6,30)) -> 0.004 | E6: =SUMIFS(payment!H2:H1436,payment!I2:I1436,">="&DATE(2025,6,24),payment!I2:I1436,"<="&DATE(2025,6,30),payment!A2:A1436,"=TW") -> 0 | F6: =SUMIFS(payment!H2:H1436,payment!I2:I1436,">="&DATE(2025,6,24),payment!I2:I1436,"<="&DATE(2025,6,30),payment!A2:A1436,"=VARNISHED") -> 0 | G6: =SUMIFS(payment!H2:H1436,payment!I2:I1436,">="&DATE(2025,6,24),payment!I2:I1436,"<="&DATE(2025,6,30),payment!A2:A1436,"=NBE") -> 0.004 | H6: =SUMIFS(payment!H2:H1436,payment!I2:I1436,">="&DATE(2025,6,24),payment!I2:I1436,"<="&DATE(2025,6,30),payment!A2:A1436,"=PT") -> 0 | I6: =SUMIFS(payment!H2:H1436,payment!I2:I1436,">="&DATE(2025,6,24),payment!I2:I1436,"<="&DATE(2025,6,30),payment!A2:A1436,"=IN") -> 0 | J6: =SUMIFS(payment!H2:H1436,payment!I2:I1436,">="&DATE(2025,6,24),payment!I2:I1436,"<="&DATE(2025,6,30),payment!A2:A1436,"=NF") -> 0 | K6: =J6*7.1 -> 0 | L6: =SUMIFS(payment!H2:H1436,payment!L2:L1436,">="&DATE(2025,6,24),payment!L2:L1436,"<="&DATE(2025,6,30)) -> 0 | M6: =M5-C6+L6 -> 3512729.1
B7: July 1-7 | C7: =SUMIFS(payment!H2:H1436,payment!I2:I1436,">="&DATE(2025,7,1),payment!I2:I1436,"<="&DATE(2025,7,7)) -> 0 | E7: =SUMIFS(payment!H2:H1436,payment!I2:I1436,">="&DATE(2025,7,1),payment!I2:I1436,"<="&DATE(2025,7,7),payment!A2:A1436,"=TW") -> 0 | F7: =SUMIFS(payment!H2:H1436,payment!I2:I1436,">="&DATE(2025,7,1),payment!I2:I1436,"<="&DATE(2025,7,7),payment!A2:A1436,"=VARNISHED") -> 0 | G7: =SUMIFS(payment!H2:H1436,payment!I2:I1436,">="&DATE(2025,7,1),payment!I2:I1436,"<="&DATE(2025,7,7),payment!A2:A1436,"=NBE") -> 0 | H7: =SUMIFS(payment!H2:H1436,payment!I2:I1436,">="&DATE(2025,7,1),payment!I2:I1436,"<="&DATE(2025,7,7),payment!A2:A1436,"=PT") -> 0 | I7: =SUMIFS(payment!H2:H1436,payment!I2:I1436,">="&DATE(2025,7,1),payment!I2:I1436,"<="&DATE(2025,7,7),payment!A2:A1436,"=IN") -> 0 | J7: =SUMIFS(payment!H2:H1436,payment!I2:I1436,">="&DATE(2025,7,1),payment!I2:I1436,"<="&DATE(2025,7,7),payment!A2:A1436,"=NF") -> 0 | K7: =J7*7.1 -> 0 | L7: =SUMIFS(payment!H2:H1453,payment!L2:L1453,">="&DATE(2025,7,1),payment!L2:L1453,"<="&DATE(2025,7,7)) -> 0 | M7: =M6-C7+L7 -> 3512729.1
B8: July 8-15 | C8: =SUMIFS(payment!H2:H1436,payment!I2:I1436,">="&DATE(2025,7,8),payment!I2:I1436,"<="&DATE(2025,7,15)) -> 0 | E8: =SUMIFS(payment!H2:H1436,payment!I2:I1436,">="&DATE(2025,7,8),payment!I2:I1436,"<="&DATE(2025,7,15),payment!A2:A1436,"=TW") -> 0 | F8: =SUMIFS(payment!H2:H1436,payment!I2:I1436,">="&DATE(2025,7,8),payment!I2:I1436,"<="&DATE(2025,7,15),payment!A2:A1436,"=VARNISHED") -> 0 | G8: =SUMIFS(payment!H2:H1436,payment!I2:I1436,">="&DATE(2025,7,8),payment!I2:I1436,"<="&DATE(2025,7,15),payment!A2:A1436,"=NBE") -> 0 | H8: =SUMIFS(payment!H2:H1436,payment!I2:I1436,">="&DATE(2025,7,8),payment!I2:I1436,"<="&DATE(2025,7,15),payment!A2:A1436,"=PT") -> 0 | I8: =SUMIFS(payment!H2:H1436,payment!I2:I1436,">="&DATE(2025,7,8),payment!I2:I1436,"<="&DATE(2025,7,15),payment!A2:A1436,"=IN") -> 0 | J8: =SUMIFS(payment!H2:H1436,payment!I2:I1436,">="&DATE(2025,7,8),payment!I2:I1436,"<="&DATE(2025,7,15),payment!A2:A1436,"=NF") -> 0 | K8: =J8*7.1 -> 0 | L8: =SUMIFS(payment!H2:H1453,payment!L2:L1453,">="&DATE(2025,7,8),payment!L2:L1453,"<="&DATE(2025,7,15)) -> 0 | M8: =M7-C8+L8 -> 3512729.1
B9: July 16-23 | C9: =SUMIFS(payment!H2:H1436,payment!I2:I1436,">="&DATE(2025,7,16),payment!I2:I1436,"<="&DATE(2025,7,23)) -> 0 | E9: =SUMIFS(payment!H2:H1436,payment!I2:I1436,">="&DATE(2025,7,16),payment!I2:I1436,"<="&DATE(2025,7,23),payment!A2:A1436,"=TW") -> 0 | F9: =SUMIFS(payment!H2:H1436,payment!I2:I1436,">="&DATE(2025,7,16),payment!I2:I1436,"<="&DATE(2025,7,23),payment!A2:A1436,"=VARNISHED") -> 0 | G9: =SUMIFS(payment!H2:H1436,payment!I2:I1436,">="&DATE(2025,7,16),payment!I2:I1436,"<="&DATE(2025,7,23),payment!A2:A1436,"=NBE") -> 0 | H9: =SUMIFS(payment!H2:H1436,payment!I2:I1436,">="&DATE(2025,7,16),payment!I2:I1436,"<="&DATE(2025,7,23),payment!A2:A1436,"=PT") -> 0 | I9: =SUMIFS(payment!H2:H1436,payment!I2:I1436,">="&DATE(2025,7,16),payment!I2:I1436,"<="&DATE(2025,7,23),payment!A2:A1436,"=IN") -> 0 | J9: =SUMIFS(payment!H2:H1436,payment!I2:I1436,">="&DATE(2025,7,16),payment!I2:I1436,"<="&DATE(2025,7,23),payment!A2:A1436,"=NF") -> 0 | K9: =J9*7.1 -> 0 | L9: =SUMIFS(payment!H2:H1453,payment!L2:L1453,">="&DATE(2025,7,16),payment!L2:L1453,"<="&DATE(2025,7,23)) -> 0.002 | M9: =M8-C9+L9 -> 3512729.1
B10: July 24-31 | C10: =SUMIFS(payment!H2:H1436,payment!I2:I1436,">="&DATE(2025,7,24),payment!I2:I1436,"<="&DATE(2025,7,31)) -> 0.0075 | E10: =SUMIFS(payment!H2:H1436,payment!I2:I1436,">="&DATE(2025,7,24),payment!I2:I1436,"<="&DATE(2025,7,31),payment!A2:A1436,"=TW") -> 0.0075 | F10: =SUMIFS(payment!H2:H1436,payment!I2:I1436,">="&DATE(2025,7,24),payment!I2:I1436,"<="&DATE(2025,7,31),payment!A2:A1436,"=VARNISHED") -> 0 | G10: =SUMIFS(payment!H2:H1436,payment!I2:I1436,">="&DATE(2025,7,24),payment!I2:I1436,"<="&DATE(2025,7,31),payment!A2:A1436,"=NBE") -> 0 | H10: =SUMIFS(payment!H2:H1436,payment!I2:I1436,">="&DATE(2025,7,24),payment!I2:I1436,"<="&DATE(2025,7,31),payment!A2:A1436,"=PT") -> 0 | I10: =SUMIFS(payment!H2:H1436,payment!I2:I1436,">="&DATE(2025,7,24),payment!I2:I1436,"<="&DATE(2025,7,31),payment!A2:A1436,"=IN") -> 0 | J10: =SUMIFS(payment!H2:H1436,payment!I2:I1436,">="&DATE(2025,7,24),payment!I2:I1436,"<="&DATE(2025,7,31),payment!A2:A1436,"=NF") -> 0 | K10: =J10*7.1 -> 0 | L10: =SUMIFS(payment!H2:H1453,payment!L2:L1453,">="&DATE(2025,7,24),payment!L2:L1453,"<="&DATE(2025,7,31)) -> 0 | M10: =M9-C10+L10 -> 3512729.1
B11: August 1-7 | C11: =SUMIFS(payment!H2:H1436,payment!I2:I1436,">="&DATE(2025,8,1),payment!I2:I1436,"<="&DATE(2025,8,7)) -> 0.00079999998 | E11: =SUMIFS(payment!H2:H1436,payment!I2:I1436,">="&DATE(2025,8,1),payment!I2:I1436,"<="&DATE(2025,8,7),payment!A2:A1436,"=TW") -> 0 | F11: =SUMIFS(payment!H2:H1436,payment!I2:I1436,">="&DATE(2025,8,1),payment!I2:I1436,"<="&DATE(2025,8,7),payment!A2:A1436,"=VARNISHED") -> 0 | G11: =SUMIFS(payment!H2:H1436,payment!I2:I1436,">="&DATE(2025,8,1),payment!I2:I1436,"<="&DATE(2025,8,7),payment!A2:A1436,"=NBE") -> 0 | H11: =SUMIFS(payment!H2:H1436,payment!I2:I1436,">="&DATE(2025,8,1),payment!I2:I1436,"<="&DATE(2025,8,7),payment!A2:A1436,"=PT") -> 0 | I11: =SUMIFS(payment!H2:H1436,payment!I2:I1436,">="&DATE(2025,8,1),payment!I2:I1436,"<="&DATE(2025,8,7),payment!A2:A1436,"=IN") -> 0.00079999998 | J11: =SUMIFS(payment!H2:H1436,payment!I2:I1436,">="&DATE(2025,8,1),payment!I2:I1436,"<="&DATE(2025,8,7),payment!A2:A1436,"=NF") -> 0 | K11: =J11*7.1 -> 0 | L11: =SUMIFS(payment!H2:H1453,payment!L2:L1453,">="&DATE(2025,8,1),payment!L2:L1453,"<="&DATE(2025,8,7)) -> 0 | M11: =M10-C11+L11 -> 3512729.1
B12: August 8-15 | C12: =SUMIFS(payment!H2:H1436,payment!I2:I1436,">="&DATE(2025,8,8),payment!I2:I1436,"<="&DATE(2025,8,15)) -> 0 | E12: =SUMIFS(payment!H2:H1436,payment!I2:I1436,">="&DATE(2025,8,8),payment!I2:I1436,"<="&DATE(2025,8,15),payment!A2:A1436,"=TW") -> 0 | F12: =SUMIFS(payment!H2:H1436,payment!I2:I1436,">="&DATE(2025,8,8),payment!I2:I1436,"<="&DATE(2025,8,15),payment!A2:A1436,"=VARNISHED") -> 0 | G12: =SUMIFS(payment!H2:H1436,payment!I2:I1436,">="&DATE(2025,8,8),payment!I2:I1436,"<="&DATE(2025,8,15),payment!A2:A1436,"=NBE") -> 0 | H12: =SUMIFS(payment!H2:H1436,payment!I2:I1436,">="&DATE(2025,8,8),payment!I2:I1436,"<="&DATE(2025,8,15),payment!A2:A1436,"=PT") -> 0 | I12: =SUMIFS(payment!H2:H1436,payment!I2:I1436,">="&DATE(2025,8,8),payment!I2:I1436,"<="&DATE(2025,8,15),payment!A2:A1436,"=IN") -> 0 | J12: =SUMIFS(payment!H2:H1436,payment!I2:I1436,">="&DATE(2025,8,8),payment!I2:I1436,"<="&DATE(2025,8,15),payment!A2:A1436,"=NF") -> 0 | K12: =J12*7.1 -> 0 | L12: =SUMIFS(payment!H2:H1453,payment!L2:L1453,">="&DATE(2025,8,8),payment!L2:L1453,"<="&DATE(2025,8,15)) -> 0 | M12: =M11-C12+L12 -> 3512729.1
B13: August 16-23 | C13: =SUMIFS(payment!H2:H1436,payment!I2:I1436,">="&DATE(2025,8,16),payment!I2:I1436,"<="&DATE(2025,8,23)) -> 0 | E13: =SUMIFS(payment!H2:H1436,payment!I2:I1436,">="&DATE(2025,8,16),payment!I2:I1436,"<="&DATE(2025,8,23),payment!A2:A1436,"=TW") -> 0 | F13: =SUMIFS(payment!H2:H1436,payment!I2:I1436,">="&DATE(2025,8,16),payment!I2:I1436,"<="&DATE(2025,8,23),payment!A2:A1436,"=VARNISHED") -> 0 | G13: =SUMIFS(payment!H2:H1436,payment!I2:I1436,">="&DATE(2025,8,16),payment!I2:I1436,"<="&DATE(2025,8,23),payment!A2:A1436,"=NBE") -> 0 | H13: =SUMIFS(payment!H2:H1436,payment!I2:I1436,">="&DATE(2025,8,16),payment!I2:I1436,"<="&DATE(2025,8,23),payment!A2:A1436,"=PT") -> 0 | I13: =SUMIFS(payment!H2:H1436,payment!I2:I1436,">="&DATE(2025,8,16),payment!I2:I1436,"<="&DATE(2025,8,23),payment!A2:A1436,"=IN") -> 0 | J13: =SUMIFS(payment!H2:H1436,payment!I2:I1436,">="&DATE(2025,8,16),payment!I2:I1436,"<="&DATE(2025,8,23),payment!A2:A1436,"=NF") -> 0 | K13: =J13*7.1 -> 0 | L13: =SUMIFS(payment!H2:H1453,payment!L2:L1453,">="&DATE(2025,8,16),payment!L2:L1453,"<="&DATE(2025,8,23)) -> 0 | M13: =M12-C13+L13 -> 3512729.1
B14: August 24-31 | C14: =SUMIFS(payment!H2:H1436,payment!I2:I1436,">="&DATE(2025,8,24),payment!I2:I1436,"<="&DATE(2025,8,31)) -> 0.004 | E14: =SUMIFS(payment!H2:H1436,payment!I2:I1436,">="&DATE(2025,8,24),payment!I2:I1436,"<="&DATE(2025,8,31),payment!A2:A1436,"=TW") -> 0.004 | F14: =SUMIFS(payment!H2:H1436,payment!I2:I1436,">="&DATE(2025,8,24),payment!I2:I1436,"<="&DATE(2025,8,31),payment!A2:A1436,"=VARNISHED") -> 0 | G14: =SUMIFS(payment!H2:H1436,payment!I2:I1436,">="&DATE(2025,8,24),payment!I2:I1436,"<="&DATE(2025,8,31),payment!A2:A1436,"=NBE") -> 0 | H14: =SUMIFS(payment!H2:H1436,payment!I2:I1436,">="&DATE(2025,8,24),payment!I2:I1436,"<="&DATE(2025,8,31),payment!A2:A1436,"=PT") -> 0 | I14: =SUMIFS(payment!H2:H1436,payment!I2:I1436,">="&DATE(2025,8,24),payment!I2:I1436,"<="&DATE(2025,8,31),payment!A2:A1436,"=IN") -> 0 | J14: =SUMIFS(payment!H2:H1436,payment!I2:I1436,">="&DATE(2025,8,24),payment!I2:I1436,"<="&DATE(2025,8,31),payment!A2:A1436,"=NF") -> 0 | K14: =J14*7.1 -> 0 | L14: =SUMIFS(payment!H2:H1453,payment!L2:L1453,">="&DATE(2025,8,24),payment!L2:L1453,"<="&DATE(2025,8,31)) -> 0 | M14: =M13-C14+L14 -> 3512729.1
B15: September 1-7 | C15: =SUMIFS(payment!H2:H1436,payment!I2:I1436,">="&DATE(2025,9,1),payment!I2:I1436,"<="&DATE(2025,9,7)) -> 0 | E15: =SUMIFS(payment!H2:H1436,payment!I2:I1436,">="&DATE(2025,9,1),payment!I2:I1436,"<="&DATE(2025,9,7),payment!A2:A1436,"=TW") -> 0 | F15: =SUMIFS(payment!H2:H1436,payment!I2:I1436,">="&DATE(2025,9,1),payment!I2:I1436,"<="&DATE(2025,9,7),payment!A2:A1436,"=VARNISHED") -> 0 | G15: =SUMIFS(payment!H2:H1436,payment!I2:I1436,">="&DATE(2025,9,1),payment!I2:I1436,"<="&DATE(2025,9,7),payment!A2:A1436,"=NBE") -> 0 | H15: =SUMIFS(payment!H2:H1436,payment!I2:I1436,">="&DATE(2025,9,1),payment!I2:I1436,"<="&DATE(2025,9,7),payment!A2:A1436,"=PT") -> 0 | I15: =SUMIFS(payment!H2:H1436,payment!I2:I1436,">="&DATE(2025,9,1),payment!I2:I1436,"<="&DATE(2025,9,7),payment!A2:A1436,"=IN") -> 0 | J15: =SUMIFS(payment!H2:H1436,payment!I2:I1436,">="&DATE(2025,9,1),payment!I2:I1436,"<="&DATE(2025,9,7),payment!A2:A1436,"=NF") -> 0 | K15: =J15*7.1 -> 0 | L15: =SUMIFS(payment!H2:H1453,payment!L2:L1453,">="&DATE(2025,9,1),payment!L2:L1453,"<="&DATE(2025,9,7)) -> 0 | M15: =M14-C15+L15 -> 3512729.1
B16: September 8-15 | C16: =SUMIFS(payment!H2:H1436,payment!I2:I1436,">="&DATE(2025,9,8),payment!I2:I1436,"<="&DATE(2025,9,15)) -> 0 | E16: =SUMIFS(payment!H2:H1436,payment!I2:I1436,">="&DATE(2025,9,8),payment!I2:I1436,"<="&DATE(2025,9,15),payment!A2:A1436,"=TW") -> 0 | F16: =SUMIFS(payment!H2:H1436,payment!I2:I1436,">="&DATE(2025,9,8),payment!I2:I1436,"<="&DATE(2025,9,15),payment!A2:A1436,"=VARNISHED") -> 0 | G16: =SUMIFS(payment!H2:H1436,payment!I2:I1436,">="&DATE(2025,9,8),payment!I2:I1436,"<="&DATE(2025,9,15),payment!A2:A1436,"=NBE") -> 0 | H16: =SUMIFS(payment!H2:H1436,payment!I2:I1436,">="&DATE(2025,9,8),payment!I2:I1436,"<="&DATE(2025,9,15),payment!A2:A1436,"=PT") -> 0 | I16: =SUMIFS(payment!H2:H1436,payment!I2:I1436,">="&DATE(2025,9,8),payment!I2:I1436,"<="&DATE(2025,9,15),payment!A2:A1436,"=IN") -> 0 | J16: =SUMIFS(payment!H2:H1436,payment!I2:I1436,">="&DATE(2025,9,8),payment!I2:I1436,"<="&DATE(2025,9,15),payment!A2:A1436,"=NF") -> 0 | K16: =J16*7.1 -> 0 | L16: =SUMIFS(payment!H2:H1453,payment!L2:L1453,">="&DATE(2025,9,8),payment!L2:L1453,"<="&DATE(2025,9,15)) -> 0 | M16: =M15-C16+L16 -> 3512729.1
B17: September 16-23 | C17: =SUMIFS(payment!H2:H1436,payment!I2:I1436,">="&DATE(2025,9,16),payment!I2:I1436,"<="&DATE(2025,9,23)) -> 0.0035 | E17: =SUMIFS(payment!H2:H1436,payment!I2:I1436,">="&DATE(2025,9,16),payment!I2:I1436,"<="&DATE(2025,9,23),payment!A2:A1436,"=TW") -> 0 | F17: =SUMIFS(payment!H2:H1436,payment!I2:I1436,">="&DATE(2025,9,16),payment!I2:I1436,"<="&DATE(2025,9,23),payment!A2:A1436,"=VARNISHED") -> 0 | G17: =SUMIFS(payment!H2:H1436,payment!I2:I1436,">="&DATE(2025,9,16),payment!I2:I1436,"<="&DATE(2025,9,23),payment!A2:A1436,"=NBE") -> 0 | H17: =SUMIFS(payment!H2:H1436,payment!I2:I1436,">="&DATE(2025,9,16),payment!I2:I1436,"<="&DATE(2025,9,23),payment!A2:A1436,"=PT") -> 0 | I17: =SUMIFS(payment!H2:H1436,payment!I2:I1436,">="&DATE(2025,9,16),payment!I2:I1436,"<="&DATE(2025,9,23),payment!A2:A1436,"=IN") -> 0.0035 | J17: =SUMIFS(payment!H2:H1436,payment!I2:I1436,">="&DATE(2025,9,16),payment!I2:I1436,"<="&DATE(2025,9,23),payment!A2:A1436,"=NF") -> 0 | K17: =J17*7.1 -> 0 | L17: =SUMIFS(payment!H2:H1453,payment!L2:L1453,">="&DATE(2025,9,16),payment!L2:L1453,"<="&DATE(2025,9,23)) -> 0 | M17: =M16-C17+L17 -> 3512729.1
B18: September 24-30 | C18: =SUMIFS(payment!H2:H1436,payment!I2:I1436,">="&DATE(2025,9,24),payment!I2:I1436,"<="&DATE(2025,9,30)) -> 0 | E18: =SUMIFS(payment!H2:H1436,payment!I2:I1436,">="&DATE(2025,9,24),payment!I2:I1436,"<="&DATE(2025,9,30),payment!A2:A1436,"=TW") -> 0 | F18: =SUMIFS(payment!H2:H1436,payment!I2:I1436,">="&DATE(2025,9,24),payment!I2:I1436,"<="&DATE(2025,9,30),payment!A2:A1436,"=VARNISHED") -> 0 | G18: =SUMIFS(payment!H2:H1436,payment!I2:I1436,">="&DATE(2025,9,24),payment!I2:I1436,"<="&DATE(2025,9,30),payment!A2:A1436,"=NBE") -> 0 | H18: =SUMIFS(payment!H2:H1436,payment!I2:I1436,">="&DATE(2025,9,24),payment!I2:I1436,"<="&DATE(2025,9,30),payment!A2:A1436,"=PT") -> 0 | I18: =SUMIFS(payment!H2:H1436,payment!I2:I1436,">="&DATE(2025,9,24),payment!I2:I1436,"<="&DATE(2025,9,30),payment!A2:A1436,"=IN") -> 0 | J18: =SUMIFS(payment!H2:H1436,payment!I2:I1436,">="&DATE(2025,9,24),payment!I2:I1436,"<="&DATE(2025,9,30),payment!A2:A1436,"=NF") -> 0 | K18: =J18*7.1 -> 0 | L18: =SUMIFS(payment!H2:H1453,payment!L2:L1453,">="&DATE(2025,9,24),payment!L2:L1453,"<="&DATE(2025,9,30)) -> 0 | M18: =M17-C18+L18 -> 3512729.1
B19: October 1-7 | C19: =SUMIFS(payment!H2:H1436,payment!I2:I1436,">="&DATE(2025,10,1),payment!I2:I1436,"<="&DATE(2025,10,7)) -> 0 | E19: =SUMIFS(payment!H2:H1436,payment!I2:I1436,">="&DATE(2025,10,1),payment!I2:I1436,"<="&DATE(2025,10,7),payment!A2:A1436,"=TW") -> 0 | F19: =SUMIFS(payment!H2:H1436,payment!I2:I1436,">="&DATE(2025,10,1),payment!I2:I1436,"<="&DATE(2025,10,7),payment!A2:A1436,"=VARNISHED") -> 0 | G19: =SUMIFS(payment!H2:H1436,payment!I2:I1436,">="&DATE(2025,10,1),payment!I2:I1436,"<="&DATE(2025,10,7),payment!A2:A1436,"=NBE") -> 0 | H19: =SUMIFS(payment!H2:H1436,payment!I2:I1436,">="&DATE(2025,10,1),payment!I2:I1436,"<="&DATE(2025,10,7),payment!A2:A1436,"=PT") -> 0 | I19: =SUMIFS(payment!H2:H1436,payment!I2:I1436,">="&DATE(2025,10,1),payment!I2:I1436,"<="&DATE(2025,10,7),payment!A2:A1436,"=IN") -> 0 | J19: =SUMIFS(payment!H2:H1436,payment!I2:I1436,">="&DATE(2025,10,1),payment!I2:I1436,"<="&DATE(2025,10,7),payment!A2:A1436,"=NF") -> 0 | K19: =J19*7.1 -> 0 | L19: =SUMIFS(payment!H2:H1453,payment!L2:L1453,">="&DATE(2025,10,1),payment!L2:L1453,"<="&DATE(2025,10,7)) -> 0 | M19: =M18-C19+L19 -> 3512729.1
B20: October 8-15 | C20: =SUMIFS(payment!H2:H1436,payment!I2:I1436,">="&DATE(2025,10,8),payment!I2:I1436,"<="&DATE(2025,10,15)) -> -0.00212 | E20: =SUMIFS(payment!H2:H1436,payment!I2:I1436,">="&DATE(2025,10,8),payment!I2:I1436,"<="&DATE(2025,10,15),payment!A2:A1436,"=TW") -> 0 | F20: =SUMIFS(payment!H2:H1436,payment!I2:I1436,">="&DATE(2025,10,8),payment!I2:I1436,"<="&DATE(2025,10,15),payment!A2:A1436,"=VARNISHED") -> 0 | G20: =SUMIFS(payment!H2:H1436,payment!I2:I1436,">="&DATE(2025,10,8),payment!I2:I1436,"<="&DATE(2025,10,15),payment!A2:A1436,"=NBE") -> 0 | H20: =SUMIFS(payment!H2:H1436,payment!I2:I1436,">="&DATE(2025,10,8),payment!I2:I1436,"<="&DATE(2025,10,15),payment!A2:A1436,"=PT") -> -0.00212 | I20: =SUMIFS(payment!H2:H1436,payment!I2:I1436,">="&DATE(2025,10,8),payment!I2:I1436,"<="&DATE(2025,10,15),payment!A2:A1436,"=IN") -> 0 | J20: =SUMIFS(payment!H2:H1436,payment!I2:I1436,">="&DATE(2025,10,8),payment!I2:I1436,"<="&DATE(2025,10,15),payment!A2:A1436,"=NF") -> 0 | K20: =J20*7.1 -> 0 | L20: =SUMIFS(payment!H2:H1453,payment!L2:L1453,">="&DATE(2025,10,8),payment!L2:L1453,"<="&DATE(2025,10,15)) -> 0 | M20: =M19-C20+L20 -> 3512729.1
B21: October 16-23 | C21: =SUMIFS(payment!H2:H1436,payment!I2:I1436,">="&DATE(2025,10,16),payment!I2:I1436,"<="&DATE(2025,10,23)) -> 0 | E21: =SUMIFS(payment!H2:H1436,payment!I2:I1436,">="&DATE(2025,10,16),payment!I2:I1436,"<="&DATE(2025,10,23),payment!A2:A1436,"=TW") -> 0 | F21: =SUMIFS(payment!H2:H1436,payment!I2:I1436,">="&DATE(2025,10,16),payment!I2:I1436,"<="&DATE(2025,10,23),payment!A2:A1436,"=VARNISHED") -> 0 | G21: =SUMIFS(payment!H2:H1436,payment!I2:I1436,">="&DATE(2025,10,16),payment!I2:I1436,"<="&DATE(2025,10,23),payment!A2:A1436,"=NBE") -> 0 | H21: =SUMIFS(payment!H2:H1436,payment!I2:I1436,">="&DATE(2025,10,16),payment!I2:I1436,"<="&DATE(2025,10,23),payment!A2:A1436,"=PT") -> 0 | I21: =SUMIFS(payment!H2:H1436,payment!I2:I1436,">="&DATE(2025,10,16),payment!I2:I1436,"<="&DATE(2025,10,23),payment!A2:A1436,"=IN") -> 0 | J21: =SUMIFS(payment!H2:H1436,payment!I2:I1436,">="&DATE(2025,10,16),payment!I2:I1436,"<="&DATE(2025,10,23),payment!A2:A1436,"=NF") -> 0 | K21: =J21*7.1 -> 0 | L21: =SUMIFS(payment!H2:H1453,payment!L2:L1453,">="&DATE(2025,10,16),payment!L2:L1453,"<="&DATE(2025,10,23)) -> 0 | M21: =M20-C21+L21 -> 3512729.1
B22: October 24-31 | C22: =SUMIFS(payment!H2:H1436,payment!I2:I1436,">="&DATE(2025,10,24),payment!I2:I1436,"<="&DATE(2025,10,31)) -> 3580 | E22: =SUMIFS(payment!H2:H1436,payment!I2:I1436,">="&DATE(2025,10,24),payment!I2:I1436,"<="&DATE(2025,10,31),payment!A2:A1436,"=TW") -> 0 | F22: =SUMIFS(payment!H2:H1436,payment!I2:I1436,">="&DATE(2025,10,24),payment!I2:I1436,"<="&DATE(2025,10,31),payment!A2:A1436,"=VARNISHED") -> 0 | G22: =SUMIFS(payment!H2:H1436,payment!I2:I1436,">="&DATE(2025,10,24),payment!I2:I1436,"<="&DATE(2025,10,31),payment!A2:A1436,"=NBE") -> 0 | H22: =SUMIFS(payment!H2:H1436,payment!I2:I1436,">="&DATE(2025,10,24),payment!I2:I1436,"<="&DATE(2025,10,31),payment!A2:A1436,"=PT") -> 0 | I22: =SUMIFS(payment!H2:H1436,payment!I2:I1436,">="&DATE(2025,10,24),payment!I2:I1436,"<="&DATE(2025,10,31),payment!A2:A1436,"=IN") -> 3580 | J22: =SUMIFS(payment!H2:H1436,payment!I2:I1436,">="&DATE(2025,10,24),payment!I2:I1436,"<="&DATE(2025,10,31),payment!A2:A1436,"=NF") -> 0 | K22: =J22*7.1 -> 0 | L22: =SUMIFS(payment!H2:H1453,payment!L2:L1453,">="&DATE(2025,10,24),payment!L2:L1453,"<="&DATE(2025,10,31)) -> 0 | M22: =M21-C22+L22 -> 3509149.1
B23: November 1-7 | C23: =SUMIFS(payment!H2:H1436,payment!I2:I1436,">="&DATE(2025,11,1),payment!I2:I1436,"<="&DATE(2025,11,7)) -> -0.0054 | E23: =SUMIFS(payment!H2:H1436,payment!I2:I1436,">="&DATE(2025,11,1),payment!I2:I1436,"<="&DATE(2025,11,7),payment!A2:A1436,"=TW") -> 0 | F23: =SUMIFS(payment!H2:H1436,payment!I2:I1436,">="&DATE(2025,11,1),payment!I2:I1436,"<="&DATE(2025,11,7),payment!A2:A1436,"=VARNISHED") -> 0.00099999999 | G23: =SUMIFS(payment!H2:H1436,payment!I2:I1436,">="&DATE(2025,11,1),payment!I2:I1436,"<="&DATE(2025,11,7),payment!A2:A1436,"=NBE") -> -0.004 | H23: =SUMIFS(payment!H2:H1436,payment!I2:I1436,">="&DATE(2025,11,1),payment!I2:I1436,"<="&DATE(2025,11,7),payment!A2:A1436,"=PT") -> 0 | I23: =SUMIFS(payment!H2:H1436,payment!I2:I1436,">="&DATE(2025,11,1),payment!I2:I1436,"<="&DATE(2025,11,7),payment!A2:A1436,"=IN") -> -0.0024 | J23: =SUMIFS(payment!H2:H1436,payment!I2:I1436,">="&DATE(2025,11,1),payment!I2:I1436,"<="&DATE(2025,11,7),payment!A2:A1436,"=NF") -> 0 | K23: =J23*7.1 -> 0 | L23: =SUMIFS(payment!H2:H1453,payment!L2:L1453,">="&DATE(2025,11,1),payment!L2:L1453,"<="&DATE(2025,11,7)) -> 0 | M23: =M22-C23+L23 -> 3509149.1
B24: November 8-15 | C24: =SUMIFS(payment!H2:H1436,payment!I2:I1436,">="&DATE(2025,11,8),payment!I2:I1436,"<="&DATE(2025,11,15)) -> 0 | E24: =SUMIFS(payment!H2:H1436,payment!I2:I1436,">="&DATE(2025,11,8),payment!I2:I1436,"<="&DATE(2025,11,15),payment!A2:A1436,"=TW") -> 0 | F24: =SUMIFS(payment!H2:H1436,payment!I2:I1436,">="&DATE(2025,11,8),payment!I2:I1436,"<="&DATE(2025,11,15),payment!A2:A1436,"=VARNISHED") -> 0 | G24: =SUMIFS(payment!H2:H1436,payment!I2:I1436,">="&DATE(2025,11,8),payment!I2:I1436,"<="&DATE(2025,11,15),payment!A2:A1436,"=NBE") -> 0 | H24: =SUMIFS(payment!H2:H1436,payment!I2:I1436,">="&DATE(2025,11,8),payment!I2:I1436,"<="&DATE(2025,11,15),payment!A2:A1436,"=PT") -> 0 | I24: =SUMIFS(payment!H2:H1436,payment!I2:I1436,">="&DATE(2025,11,8),payment!I2:I1436,"<="&DATE(2025,11,15),payment!A2:A1436,"=IN") -> 0 | J24: =SUMIFS(payment!H2:H1436,payment!I2:I1436,">="&DATE(2025,11,8),payment!I2:I1436,"<="&DATE(2025,11,15),payment!A2:A1436,"=NF") -> 0 | K24: =J24*7.1 -> 0 | L24: =SUMIFS(payment!H2:H1453,payment!L2:L1453,">="&DATE(2025,11,8),payment!L2:L1453,"<="&DATE(2025,11,15)) -> 0 | M24: =M23-C24+L24 -> 3509149.1
B25: November 16-23 | C25: =SUMIFS(payment!H2:H1436,payment!I2:I1436,">="&DATE(2025,11,16),payment!I2:I1436,"<="&DATE(2025,11,23)) -> 0 | E25: =SUMIFS(payment!H2:H1436,payment!I2:I1436,">="&DATE(2025,11,16),payment!I2:I1436,"<="&DATE(2025,11,23),payment!A2:A1436,"=TW") -> 0 | F25: =SUMIFS(payment!H2:H1436,payment!I2:I1436,">="&DATE(2025,11,16),payment!I2:I1436,"<="&DATE(2025,11,23),payment!A2:A1436,"=VARNISHED") -> 0 | G25: =SUMIFS(payment!H2:H1436,payment!I2:I1436,">="&DATE(2025,11,16),payment!I2:I1436,"<="&DATE(2025,11,23),payment!A2:A1436,"=NBE") -> 0 | H25: =SUMIFS(payment!H2:H1436,payment!I2:I1436,">="&DATE(2025,11,16),payment!I2:I1436,"<="&DATE(2025,11,23),payment!A2:A1436,"=PT") -> 0 | I25: =SUMIFS(payment!H2:H1436,payment!I2:I1436,">="&DATE(2025,11,16),payment!I2:I1436,"<="&DATE(2025,11,23),payment!A2:A1436,"=IN") -> 0 | J25: =SUMIFS(payment!H2:H1436,payment!I2:I1436,">="&DATE(2025,11,16),payment!I2:I1436,"<="&DATE(2025,11,23),payment!A2:A1436,"=NF") -> 0 | K25: =J25*7.1 -> 0 | L25: =SUMIFS(payment!H2:H1453,payment!L2:L1453,">="&DATE(2025,11,16),payment!L2:L1453,"<="&DATE(2025,11,23)) -> 0 | M25: =M24-C25+L25 -> 3509149.1
B26: November 24-30 | C26: =SUMIFS(payment!H2:H1436,payment!I2:I1436,">="&DATE(2025,11,24),payment!I2:I1436,"<="&DATE(2025,11,30)) -> 0 | E26: =SUMIFS(payment!H2:H1436,payment!I2:I1436,">="&DATE(2025,11,24),payment!I2:I1436,"<="&DATE(2025,11,30),payment!A2:A1436,"=TW") -> 0 | F26: =SUMIFS(payment!H2:H1436,payment!I2:I1436,">="&DATE(2025,11,24),payment!I2:I1436,"<="&DATE(2025,11,30),payment!A2:A1436,"=VARNISHED") -> 0 | G26: =SUMIFS(payment!H2:H1436,payment!I2:I1436,">="&DATE(2025,11,24),payment!I2:I1436,"<="&DATE(2025,11,30),payment!A2:A1436,"=NBE") -> 0 | H26: =SUMIFS(payment!H2:H1436,payment!I2:I1436,">="&DATE(2025,11,24),payment!I2:I1436,"<="&DATE(2025,11,30),payment!A2:A1436,"=PT") -> 0 | I26: =SUMIFS(payment!H2:H1436,payment!I2:I1436,">="&DATE(2025,11,24),payment!I2:I1436,"<="&DATE(2025,11,30),payment!A2:A1436,"=IN") -> 0 | J26: =SUMIFS(payment!H2:H1436,payment!I2:I1436,">="&DATE(2025,11,24),payment!I2:I1436,"<="&DATE(2025,11,30),payment!A2:A1436,"=NF") -> 0 | K26: =J26*7.1 -> 0 | L26: =SUMIFS(payment!H2:H1453,payment!L2:L1453,">="&DATE(2025,11,24),payment!L2:L1453,"<="&DATE(2025,11,30)) -> 0 | M26: =M25-C26+L26 -> 3509149.1
B27: December 1-7 | C27: =SUMIFS(payment!H2:H1436,payment!I2:I1436,">="&DATE(2025,12,1),payment!I2:I1436,"<="&DATE(2025,12,7)) -> 0 | E27: =SUMIFS(payment!H2:H1436,payment!I2:I1436,">="&DATE(2025,12,1),payment!I2:I1436,"<="&DATE(2025,12,7),payment!A2:A1436,"=TW") -> 0 | F27: =SUMIFS(payment!H2:H1436,payment!I2:I1436,">="&DATE(2025,12,1),payment!I2:I1436,"<="&DATE(2025,12,7),payment!A2:A1436,"=VARNISHED") -> 0 | G27: =SUMIFS(payment!H2:H1436,payment!I2:I1436,">="&DATE(2025,12,1),payment!I2:I1436,"<="&DATE(2025,12,7),payment!A2:A1436,"=NBE") -> 0 | H27: =SUMIFS(payment!H2:H1436,payment!I2:I1436,">="&DATE(2025,12,1),payment!I2:I1436,"<="&DATE(2025,12,7),payment!A2:A1436,"=PT") -> 0 | I27: =SUMIFS(payment!H2:H1436,payment!I2:I1436,">="&DATE(2025,12,1),payment!I2:I1436,"<="&DATE(2025,12,7),payment!A2:A1436,"=IN") -> 0 | J27: =SUMIFS(payment!H2:H1436,payment!I2:I1436,">="&DATE(2025,12,1),payment!I2:I1436,"<="&DATE(2025,12,7),payment!A2:A1436,"=NF") -> 0 | K27: =J27*7.1 -> 0 | L27: =SUMIFS(payment!H2:H1453,payment!L2:L1453,">="&DATE(2025,12,1),payment!L2:L1453,"<="&DATE(2025,12,7)) -> 0 | M27: =M26-C27+L27 -> 3509149.1
B28: December 8-15 | C28: =SUMIFS(payment!H2:H1436,payment!I2:I1436,">="&DATE(2025,12,8),payment!I2:I1436,"<="&DATE(2025,12,15)) -> 0 | E28: =SUMIFS(payment!H2:H1436,payment!I2:I1436,">="&DATE(2025,12,8),payment!I2:I1436,"<="&DATE(2025,12,15),payment!A2:A1436,"=TW") -> 0 | F28: =SUMIFS(payment!H2:H1436,payment!I2:I1436,">="&DATE(2025,12,8),payment!I2:I1436,"<="&DATE(2025,12,15),payment!A2:A1436,"=VARNISHED") -> 0 | G28: =SUMIFS(payment!H2:H1436,payment!I2:I1436,">="&DATE(2025,12,8),payment!I2:I1436,"<="&DATE(2025,12,15),payment!A2:A1436,"=NBE") -> 0 | H28: =SUMIFS(payment!H2:H1436,payment!I2:I1436,">="&DATE(2025,12,8),payment!I2:I1436,"<="&DATE(2025,12,15),payment!A2:A1436,"=PT") -> 0 | I28: =SUMIFS(payment!H2:H1436,payment!I2:I1436,">="&DATE(2025,12,8),payment!I2:I1436,"<="&DATE(2025,12,15),payment!A2:A1436,"=IN") -> 0 | J28: =SUMIFS(payment!H2:H1436,payment!I2:I1436,">="&DATE(2025,12,8),payment!I2:I1436,"<="&DATE(2025,12,15),payment!A2:A1436,"=NF") -> 0 | K28: =J28*7.1 -> 0 | L28: =SUMIFS(payment!H2:H1453,payment!L2:L1453,">="&DATE(2025,12,8),payment!L2:L1453,"<="&DATE(2025,12,15)) -> 0 | M28: =M27-C28+L28 -> 3509149.1
B29: December 16-23 | C29: =SUMIFS(payment!H2:H1436,payment!I2:I1436,">="&DATE(2025,12,16),payment!I2:I1436,"<="&DATE(2025,12,23)) -> 0.003 | E29: =SUMIFS(payment!H2:H1436,payment!I2:I1436,">="&DATE(2025,12,16),payment!I2:I1436,"<="&DATE(2025,12,23),payment!A2:A1436,"=TW") -> 0 | F29: =SUMIFS(payment!H2:H1436,payment!I2:I1436,">="&DATE(2025,12,16),payment!I2:I1436,"<="&DATE(2025,12,23),payment!A2:A1436,"=VARNISHED") -> 0 | G29: =SUMIFS(payment!H2:H1436,payment!I2:I1436,">="&DATE(2025,12,16),payment!I2:I1436,"<="&DATE(2025,12,23),payment!A2:A1436,"=NBE") -> 0 | H29: =SUMIFS(payment!H2:H1436,payment!I2:I1436,">="&DATE(2025,12,16),payment!I2:I1436,"<="&DATE(2025,12,23),payment!A2:A1436,"=PT") -> 0.003 | I29: =SUMIFS(payment!H2:H1436,payment!I2:I1436,">="&DATE(2025,12,16),payment!I2:I1436,"<="&DATE(2025,12,23),payment!A2:A1436,"=IN") -> 0 | J29: =SUMIFS(payment!H2:H1436,payment!I2:I1436,">="&DATE(2025,12,16),payment!I2:I1436,"<="&DATE(2025,12,23),payment!A2:A1436,"=NF") -> 0 | K29: =J29*7.1 -> 0 | L29: =SUMIFS(payment!H2:H1453,payment!L2:L1453,">="&DATE(2025,12,16),payment!L2:L1453,"<="&DATE(2025,12,23)) -> 0 | M29: =M28-C29+L29 -> 3509149.1
B30: December 24-31 | C30: =SUMIFS(payment!H2:H1436,payment!I2:I1436,">="&DATE(2025,12,24),payment!I2:I1436,"<="&DATE(2025,12,31)) -> 114000 | E30: =SUMIFS(payment!H2:H1436,payment!I2:I1436,">="&DATE(2025,12,24),payment!I2:I1436,"<="&DATE(2025,12,31),payment!A2:A1436,"=TW") -> 4.9112714e-11 | F30: =SUMIFS(payment!H2:H1436,payment!I2:I1436,">="&DATE(2025,12,24),payment!I2:I1436,"<="&DATE(2025,12,31),payment!A2:A1436,"=VARNISHED") -> 0 | G30: =SUMIFS(payment!H2:H1436,payment!I2:I1436,">="&DATE(2025,12,24),payment!I2:I1436,"<="&DATE(2025,12,31),payment!A2:A1436,"=NBE") -> 0 | H30: =SUMIFS(payment!H2:H1436,payment!I2:I1436,">="&DATE(2025,12,24),payment!I2:I1436,"<="&DATE(2025,12,31),payment!A2:A1436,"=PT") -> 114000 | I30: =SUMIFS(payment!H2:H1436,payment!I2:I1436,">="&DATE(2025,12,24),payment!I2:I1436,"<="&DATE(2025,12,31),payment!A2:A1436,"=IN") -> 0 | J30: =SUMIFS(payment!H2:H1436,payment!I2:I1436,">="&DATE(2025,12,24),payment!I2:I1436,"<="&DATE(2025,12,31),payment!A2:A1436,"=NF") -> 0 | K30: =J30*7.1 -> 0 | L30: =SUMIFS(payment!H2:H1453,payment!L2:L1453,">="&DATE(2025,12,24),payment!L2:L1453,"<="&DATE(2025,12,31)) -> 0 | M30: =M29-C30+L30 -> 3395149.1
A31: 2026 | B31: January 1-7 | C31: =SUMIFS(payment!H2:H1436,payment!I2:I1436,">="&DATE(2026,1,1),payment!I2:I1436,"<="&DATE(2026,1,7)) -> 0 | E31: =SUMIFS(payment!H2:H1436,payment!I2:I1436,">="&DATE(2026,1,1),payment!I2:I1436,"<="&DATE(2026,1,7),payment!A2:A1436,"=TW") -> 0 | F31: =SUMIFS(payment!H2:H1436,payment!I2:I1436,">="&DATE(2026,1,1),payment!I2:I1436,"<="&DATE(2026,1,7),payment!A2:A1436,"=VARNISHED") -> 0 | G31: =SUMIFS(payment!H2:H1436,payment!I2:I1436,">="&DATE(2026,1,1),payment!I2:I1436,"<="&DATE(2026,1,7),payment!A2:A1436,"=NBE") -> 0 | H31: =SUMIFS(payment!H2:H1436,payment!I2:I1436,">="&DATE(2026,1,1),payment!I2:I1436,"<="&DATE(2026,1,7),payment!A2:A1436,"=PT") -> 0 | I31: =SUMIFS(payment!H2:H1436,payment!I2:I1436,">="&DATE(2026,1,1),payment!I2:I1436,"<="&DATE(2026,1,7),payment!A2:A1436,"=IN") -> 0 | J31: =SUMIFS(payment!H2:H1436,payment!I2:I1436,">="&DATE(2026,1,1),payment!I2:I1436,"<="&DATE(2026,1,7),payment!A2:A1436,"=NF") -> 0 | K31: =J31*7.1 -> 0 | L31: =SUMIFS(payment!H2:H1453,payment!L2:L1453,">="&DATE(2026,1,1),payment!L2:L1453,"<="&DATE(2026,1,7)) -> 0 | M31: =M30-C31+L31 -> 3395149.1
B32: January 8-15 | C32: =SUMIFS(payment!H2:H1436,payment!I2:I1436,">="&DATE(2026,1,8),payment!I2:I1436,"<="&DATE(2026,1,15)) -> -0.004 | E32: =SUMIFS(payment!H2:H1436,payment!I2:I1436,">="&DATE(2026,1,8),payment!I2:I1436,"<="&DATE(2026,1,15),payment!A2:A1436,"=TW") -> 0 | F32: =SUMIFS(payment!H2:H1436,payment!I2:I1436,">="&DATE(2026,1,8),payment!I2:I1436,"<="&DATE(2026,1,15),payment!A2:A1436,"=VARNISHED") -> 0 | G32: =SUMIFS(payment!H2:H1436,payment!I2:I1436,">="&DATE(2026,1,8),payment!I2:I1436,"<="&DATE(2026,1,15),payment!A2:A1436,"=NBE") -> 0 | H32: =SUMIFS(payment!H2:H1436,payment!I2:I1436,">="&DATE(2026,1,8),payment!I2:I1436,"<="&DATE(2026,1,15),payment!A2:A1436,"=PT") -> -0.004 | I32: =SUMIFS(payment!H2:H1436,payment!I2:I1436,">="&DATE(2026,1,8),payment!I2:I1436,"<="&DATE(2026,1,15),payment!A2:A1436,"=IN") -> 0 | J32: =SUMIFS(payment!H2:H1436,payment!I2:I1436,">="&DATE(2026,1,8),payment!I2:I1436,"<="&DATE(2026,1,15),payment!A2:A1436,"=NF") -> 0 | K32: =J32*7.1 -> 0 | L32: =SUMIFS(payment!H2:H1453,payment!L2:L1453,">="&DATE(2026,1,8),payment!L2:L1453,"<="&DATE(2026,1,15)) -> 0 | M32: =M31-C32+L32 -> 3395149.1
B33: January 16-23 | C33: =SUMIFS(payment!H2:H1436,payment!I2:I1436,">="&DATE(2026,1,16),payment!I2:I1436,"<="&DATE(2026,1,23)) -> 1.1277734e-10 | E33: =SUMIFS(payment!H2:H1436,payment!I2:I1436,">="&DATE(2026,1,16),payment!I2:I1436,"<="&DATE(2026,1,23),payment!A2:A1436,"=TW") -> 1.1277734e-10 | F33: =SUMIFS(payment!H2:H1436,payment!I2:I1436,">="&DATE(2026,1,16),payment!I2:I1436,"<="&DATE(2026,1,23),payment!A2:A1436,"=VARNISHED") -> 0 | G33: =SUMIFS(payment!H2:H1436,payment!I2:I1436,">="&DATE(2026,1,16),payment!I2:I1436,"<="&DATE(2026,1,23),payment!A2:A1436,"=NBE") -> 0 | H33: =SUMIFS(payment!H2:H1436,payment!I2:I1436,">="&DATE(2026,1,16),payment!I2:I1436,"<="&DATE(2026,1,23),payment!A2:A1436,"=PT") -> 0 | I33: =SUMIFS(payment!H2:H1436,payment!I2:I1436,">="&DATE(2026,1,16),payment!I2:I1436,"<="&DATE(2026,1,23),payment!A2:A1436,"=IN") -> 0 | J33: =SUMIFS(payment!H2:H1436,payment!I2:I1436,">="&DATE(2026,1,16),payment!I2:I1436,"<="&DATE(2026,1,23),payment!A2:A1436,"=NF") -> 0 | K33: =J33*7.1 -> 0 | L33: =SUMIFS(payment!H2:H1453,payment!L2:L1453,">="&DATE(2026,1,16),payment!L2:L1453,"<="&DATE(2026,1,23)) -> 114000 | M33: =M32-C33+L33 -> 3509149.1
B34: January 24-31 | C34: =SUMIFS(payment!H2:H1436,payment!I2:I1436,">="&DATE(2026,1,24),payment!I2:I1436,"<="&DATE(2026,1,31)) -> -0.0024 | E34: =SUMIFS(payment!H2:H1436,payment!I2:I1436,">="&DATE(2026,1,24),payment!I2:I1436,"<="&DATE(2026,1,31),payment!A2:A1436,"=TW") -> -0.0024 | F34: =SUMIFS(payment!H2:H1436,payment!I2:I1436,">="&DATE(2026,1,24),payment!I2:I1436,"<="&DATE(2026,1,31),payment!A2:A1436,"=VARNISHED") -> 0 | G34: =SUMIFS(payment!H2:H1436,payment!I2:I1436,">="&DATE(2026,1,24),payment!I2:I1436,"<="&DATE(2026,1,31),payment!A2:A1436,"=NBE") -> 0 | H34: =SUMIFS(payment!H2:H1436,payment!I2:I1436,">="&DATE(2026,1,24),payment!I2:I1436,"<="&DATE(2026,1,31),payment!A2:A1436,"=PT") -> 0 | I34: =SUMIFS(payment!H2:H1436,payment!I2:I1436,">="&DATE(2026,1,24),payment!I2:I1436,"<="&DATE(2026,1,31),payment!A2:A1436,"=IN") -> 0 | J34: =SUMIFS(payment!H2:H1436,payment!I2:I1436,">="&DATE(2026,1,24),payment!I2:I1436,"<="&DATE(2026,1,31),payment!A2:A1436,"=NF") -> 0 | K34: =J34*7.1 -> 0 | L34: =SUMIFS(payment!H2:H1453,payment!L2:L1453,">="&DATE(2026,1,24),payment!L2:L1453,"<="&DATE(2026,1,31)) -> 0 | M34: =M33-C34+L34 -> 3509149.1
B35: February 1-7 | C35: =SUMIFS(payment!H6:H1440,payment!I6:I1440,">="&DATE(2026,2,1),payment!I6:I1440,"<="&DATE(2026,2,7)) -> 4.4999993e-05 | E35: =SUMIFS(payment!H6:H1440,payment!I6:I1440,">="&DATE(2026,2,1),payment!I6:I1440,"<="&DATE(2026,2,7),payment!A6:A1440,"=TW") -> 4.4999993e-05 | F35: =SUMIFS(payment!H6:H1440,payment!I6:I1440,">="&DATE(2026,2,1),payment!I6:I1440,"<="&DATE(2026,2,7),payment!A6:A1440,"=VARNISHED") -> 0 | G35: =SUMIFS(payment!H6:H1440,payment!I6:I1440,">="&DATE(2026,2,1),payment!I6:I1440,"<="&DATE(2026,2,7),payment!A6:A1440,"=NBE") -> 0 | H35: =SUMIFS(payment!H6:H1440,payment!I6:I1440,">="&DATE(2026,2,1),payment!I6:I1440,"<="&DATE(2026,2,7),payment!A6:A1440,"=PT") -> 0 | I35: =SUMIFS(payment!H6:H1440,payment!I6:I1440,">="&DATE(2026,2,1),payment!I6:I1440,"<="&DATE(2026,2,7),payment!A6:A1440,"=IN") -> 0 | J35: =SUMIFS(payment!I6:I1440,payment!J6:J1440,">="&DATE(2026,2,1),payment!J6:J1440,"<="&DATE(2026,2,7),payment!B6:B1440,"=NF") -> 0 | K35: =J35*7.1 -> 0 | L35: =SUMIFS(payment!H6:H1457,payment!L6:L1457,">="&DATE(2026,2,1),payment!L6:L1457,"<="&DATE(2026,2,7)) -> 0 | M35: =M34-C35+L35 -> 3509149.1
B36: February 8-15 | C36: =SUMIFS(payment!H6:H1440,payment!I6:I1440,">="&DATE(2026,2,8),payment!I6:I1440,"<="&DATE(2026,2,15)) -> -0.0015 | E36: =SUMIFS(payment!H6:H1440,payment!I6:I1440,">="&DATE(2026,2,8),payment!I6:I1440,"<="&DATE(2026,2,15),payment!A6:A1440,"=TW") -> 0 | F36: =SUMIFS(payment!H6:H1440,payment!I6:I1440,">="&DATE(2026,2,8),payment!I6:I1440,"<="&DATE(2026,2,15),payment!A6:A1440,"=VARNISHED") -> 0 | G36: =SUMIFS(payment!H6:H1440,payment!I6:I1440,">="&DATE(2026,2,8),payment!I6:I1440,"<="&DATE(2026,2,15),payment!A6:A1440,"=NBE") -> 0 | H36: =SUMIFS(payment!H6:H1440,payment!I6:I1440,">="&DATE(2026,2,8),payment!I6:I1440,"<="&DATE(2026,2,15),payment!A6:A1440,"=PT") -> -0.0015 | I36: =SUMIFS(payment!H6:H1440,payment!I6:I1440,">="&DATE(2026,2,8),payment!I6:I1440,"<="&DATE(2026,2,15),payment!A6:A1440,"=IN") -> 0 | J36: =SUMIFS(payment!I6:I1440,payment!J6:J1440,">="&DATE(2026,2,8),payment!J6:J1440,"<="&DATE(2026,2,15),payment!B6:B1440,"=NF") -> 0 | K36: =J36*7.1 -> 0 | L36: =SUMIFS(payment!H6:H1457,payment!L6:L1457,">="&DATE(2026,2,8),payment!L6:L1457,"<="&DATE(2026,2,15)) -> 0 | M36: =M35-C36+L36 -> 3509149.1
B37: February 16-23 | C37: =SUMIFS(payment!H6:H1440,payment!I6:I1440,">="&DATE(2026,2,16),payment!I6:I1440,"<="&DATE(2026,2,23)) -> 0.0036000004 | E37: =SUMIFS(payment!H6:H1440,payment!I6:I1440,">="&DATE(2026,2,16),payment!I6:I1440,"<="&DATE(2026,2,23),payment!A6:A1440,"=TW") -> 0 | F37: =SUMIFS(payment!H6:H1440,payment!I6:I1440,">="&DATE(2026,2,16),payment!I6:I1440,"<="&DATE(2026,2,23),payment!A6:A1440,"=VARNISHED") -> 0 | G37: =SUMIFS(payment!H6:H1440,payment!I6:I1440,">="&DATE(2026,2,16),payment!I6:I1440,"<="&DATE(2026,2,23),payment!A6:A1440,"=NBE") -> 0 | H37: =SUMIFS(payment!H6:H1440,payment!I6:I1440,">="&DATE(2026,2,16),payment!I6:I1440,"<="&DATE(2026,2,23),payment!A6:A1440,"=PT") -> 0.0036000004 | I37: =SUMIFS(payment!H6:H1440,payment!I6:I1440,">="&DATE(2026,2,16),payment!I6:I1440,"<="&DATE(2026,2,23),payment!A6:A1440,"=IN") -> 0 | J37: =SUMIFS(payment!I6:I1440,payment!J6:J1440,">="&DATE(2026,2,16),payment!J6:J1440,"<="&DATE(2026,2,23),payment!B6:B1440,"=NF") -> 0 | K37: =J37*7.1 -> 0 | L37: =SUMIFS(payment!H6:H1457,payment!L6:L1457,">="&DATE(2026,2,16),payment!L6:L1457,"<="&DATE(2026,2,23)) -> 0 | M37: =M36-C37+L37 -> 3509149.1
B38: February 24-31 | C38: =SUMIFS(payment!H6:H1440,payment!I6:I1440,">="&DATE(2026,2,24),payment!I6:I1440,"<="&DATE(2026,2,31)) -> -0.004 | E38: =SUMIFS(payment!H6:H1440,payment!I6:I1440,">="&DATE(2026,2,24),payment!I6:I1440,"<="&DATE(2026,2,28),payment!A6:A1440,"=TW") -> 0 | F38: =SUMIFS(payment!H6:H1440,payment!I6:I1440,">="&DATE(2026,2,24),payment!I6:I1440,"<="&DATE(2026,2,28),payment!A6:A1440,"=VARNISHED") -> 0 | G38: =SUMIFS(payment!H6:H1440,payment!I6:I1440,">="&DATE(2026,2,24),payment!I6:I1440,"<="&DATE(2026,2,28),payment!A6:A1440,"=NBE") -> 0 | H38: =SUMIFS(payment!H6:H1440,payment!I6:I1440,">="&DATE(2026,2,24),payment!I6:I1440,"<="&DATE(2026,2,28),payment!A6:A1440,"=PT") -> 0 | I38: =SUMIFS(payment!H6:H1440,payment!I6:I1440,">="&DATE(2026,2,24),payment!I6:I1440,"<="&DATE(2026,2,28),payment!A6:A1440,"=IN") -> 0 | J38: =SUMIFS(payment!I6:I1440,payment!J6:J1440,">="&DATE(2026,2,24),payment!J6:J1440,"<="&DATE(2026,2,28),payment!B6:B1440,"=NF") -> 0 | K38: =J38*7.1 -> 0 | L38: =SUMIFS(payment!H6:H1457,payment!L6:L1457,">="&DATE(2026,2,24),payment!L6:L1457,"<="&DATE(2026,2,28)) -> -0.00099999996 | M38: =M37-C38+L38 -> 3509149.1
B39: March 1-7 | C39: =SUMIFS(payment!H10:H1444,payment!I10:I1444,">="&DATE(2026,3,1),payment!I10:I1444,"<="&DATE(2026,3,7)) -> -0.004 | E39: =SUMIFS(payment!H10:H1444,payment!I10:I1444,">="&DATE(2026,3,1),payment!I10:I1444,"<="&DATE(2026,3,7),payment!A10:A1444,"=TW") -> 0 | F39: =SUMIFS(payment!H10:H1444,payment!I10:I1444,">="&DATE(2026,3,1),payment!I10:I1444,"<="&DATE(2026,3,7),payment!A10:A1444,"=VARNISHED") -> 0 | G39: =SUMIFS(payment!H10:H1444,payment!I10:I1444,">="&DATE(2026,3,1),payment!I10:I1444,"<="&DATE(2026,3,7),payment!A10:A1444,"=NBE") -> -0.004 | H39: =SUMIFS(payment!H10:H1444,payment!I10:I1444,">="&DATE(2026,3,1),payment!I10:I1444,"<="&DATE(2026,3,7),payment!A10:A1444,"=PT") -> 0 | I39: =SUMIFS(payment!H10:H1444,payment!I10:I1444,">="&DATE(2026,3,1),payment!I10:I1444,"<="&DATE(2026,3,7),payment!A10:A1444,"=IN") -> 0 | J39: =SUMIFS(payment!I10:I1444,payment!J10:J1444,">="&DATE(2026,3,1),payment!J10:J1444,"<="&DATE(2026,3,7),payment!B10:B1444,"=NF") -> 0 | K39: =J39*7.1 -> 0 | L39: =SUMIFS(payment!H10:H1461,payment!L10:L1461,">="&DATE(2026,3,1),payment!L10:L1461,"<="&DATE(2026,2,7)) -> 0 | M39: =M38-C39+L39 -> 3509149.1
B40: March 8-15 | C40: =SUMIFS(payment!H10:H1444,payment!I10:I1444,">="&DATE(2026,3,8),payment!I10:I1444,"<="&DATE(2026,3,15)) -> -0.009075 | E40: =SUMIFS(payment!H10:H1444,payment!I10:I1444,">="&DATE(2026,3,8),payment!I10:I1444,"<="&DATE(2026,3,15),payment!A10:A1444,"=TW") -> 0 | F40: =SUMIFS(payment!H10:H1444,payment!I10:I1444,">="&DATE(2026,3,8),payment!I10:I1444,"<="&DATE(2026,3,15),payment!A10:A1444,"=VARNISHED") -> 0 | G40: =SUMIFS(payment!H10:H1444,payment!I10:I1444,">="&DATE(2026,3,8),payment!I10:I1444,"<="&DATE(2026,3,15),payment!A10:A1444,"=NBE") -> 0 | H40: =SUMIFS(payment!H10:H1444,payment!I10:I1444,">="&DATE(2026,3,8),payment!I10:I1444,"<="&DATE(2026,3,15),payment!A10:A1444,"=PT") -> -0.009075 | I40: =SUMIFS(payment!H10:H1444,payment!I10:I1444,">="&DATE(2026,3,8),payment!I10:I1444,"<="&DATE(2026,3,15),payment!A10:A1444,"=IN") -> 0 | J40: =SUMIFS(payment!I10:I1444,payment!J10:J1444,">="&DATE(2026,3,8),payment!J10:J1444,"<="&DATE(2026,3,15),payment!B10:B1444,"=NF") -> 0 | K40: =J40*7.1 -> 0 | L40: =SUMIFS(payment!H10:H1461,payment!L10:L1461,">="&DATE(2026,3,8),payment!L10:L1461,"<="&DATE(2026,3,15)) -> 0 | M40: =M39-C40+L40 -> 3509149.1
B41: March 16-23 | C41: =SUMIFS(payment!H10:H1444,payment!I10:I1444,">="&DATE(2026,3,16),payment!I10:I1444,"<="&DATE(2026,3,23)) -> 0 | E41: =SUMIFS(payment!H10:H1444,payment!I10:I1444,">="&DATE(2026,3,16),payment!I10:I1444,"<="&DATE(2026,3,23),payment!A10:A1444,"=TW") -> 0 | F41: =SUMIFS(payment!H10:H1444,payment!I10:I1444,">="&DATE(2026,3,16),payment!I10:I1444,"<="&DATE(2026,3,23),payment!A10:A1444,"=VARNISHED") -> 0 | G41: =SUMIFS(payment!H10:H1444,payment!I10:I1444,">="&DATE(2026,3,16),payment!I10:I1444,"<="&DATE(2026,3,23),payment!A10:A1444,"=NBE") -> 0 | H41: =SUMIFS(payment!H10:H1444,payment!I10:I1444,">="&DATE(2026,3,16),payment!I10:I1444,"<="&DATE(2026,3,23),payment!A10:A1444,"=PT") -> 0 | I41: =SUMIFS(payment!H10:H1444,payment!I10:I1444,">="&DATE(2026,3,16),payment!I10:I1444,"<="&DATE(2026,3,23),payment!A10:A1444,"=IN") -> 0 | J41: =SUMIFS(payment!I10:I1444,payment!J10:J1444,">="&DATE(2026,3,16),payment!J10:J1444,"<="&DATE(2026,3,23),payment!B10:B1444,"=NF") -> 0 | K41: =J41*7.1 -> 0 | L41: =SUMIFS(payment!H10:H1461,payment!L10:L1461,">="&DATE(2026,3,16),payment!L10:L1461,"<="&DATE(2026,3,23)) -> 0 | M41: =M40-C41+L41 -> 3509149.1
B42: March 24-31 | C42: =SUMIFS(payment!H10:H1444,payment!I10:I1444,">="&DATE(2026,3,24),payment!I10:I1444,"<="&DATE(2026,3,31)) -> 0 | E42: =SUMIFS(payment!H10:H1444,payment!I10:I1444,">="&DATE(2026,3,24),payment!I10:I1444,"<="&DATE(2026,3,31),payment!A10:A1444,"=TW") -> 0 | F42: =SUMIFS(payment!H10:H1444,payment!I10:I1444,">="&DATE(2026,3,24),payment!I10:I1444,"<="&DATE(2026,3,31),payment!A10:A1444,"=VARNISHED") -> 0 | G42: =SUMIFS(payment!H10:H1444,payment!I10:I1444,">="&DATE(2026,3,24),payment!I10:I1444,"<="&DATE(2026,3,31),payment!A10:A1444,"=NBE") -> 0 | H42: =SUMIFS(payment!H10:H1444,payment!I10:I1444,">="&DATE(2026,3,24),payment!I10:I1444,"<="&DATE(2026,3,31),payment!A10:A1444,"=PT") -> 0 | I42: =SUMIFS(payment!H10:H1444,payment!I10:I1444,">="&DATE(2026,3,24),payment!I10:I1444,"<="&DATE(2026,3,31),payment!A10:A1444,"=IN") -> 0 | J42: =SUMIFS(payment!I10:I1444,payment!J10:J1444,">="&DATE(2026,3,24),payment!J10:J1444,"<="&DATE(2026,3,31),payment!B10:B1444,"=NF") -> 0 | K42: =J42*7.1 -> 0 | L42: =SUMIFS(payment!H10:H1461,payment!L10:L1461,">="&DATE(2026,3,24),payment!L10:L1461,"<="&DATE(2026,3,31)) -> -0.0015 | M42: =M41-C42+L42 -> 3509149.1
B43: April 1-7 | C43: =SUMIFS(payment!H14:H1448,payment!I14:I1448,">="&DATE(2026,4,1),payment!I14:I1448,"<="&DATE(2026,4,7)) -> 0.308 | E43: =SUMIFS(payment!H14:H1448,payment!I14:I1448,">="&DATE(2026,4,1),payment!I14:I1448,"<="&DATE(2026,4,7),payment!A14:A1448,"=TW") -> 0 | F43: =SUMIFS(payment!H14:H1448,payment!I14:I1448,">="&DATE(2026,4,1),payment!I14:I1448,"<="&DATE(2026,4,7),payment!A14:A1448,"=VARNISHED") -> 0 | G43: =SUMIFS(payment!H14:H1448,payment!I14:I1448,">="&DATE(2026,4,1),payment!I14:I1448,"<="&DATE(2026,4,7),payment!A14:A1448,"=NBE") -> 0.304 | H43: =SUMIFS(payment!H14:H1448,payment!I14:I1448,">="&DATE(2026,4,1),payment!I14:I1448,"<="&DATE(2026,4,7),payment!A14:A1448,"=PT") -> 0 | I43: =SUMIFS(payment!H14:H1448,payment!I14:I1448,">="&DATE(2026,4,1),payment!I14:I1448,"<="&DATE(2026,4,7),payment!A14:A1448,"=IN") -> 0.004 | J43: =SUMIFS(payment!I14:I1448,payment!J14:J1448,">="&DATE(2026,4,1),payment!J14:J1448,"<="&DATE(2026,4,7),payment!B14:B1448,"=NF") -> 0 | K43: =J43*7.1 -> 0 | L43: =SUMIFS(payment!H14:H1465,payment!L14:L1465,">="&DATE(2026,4,1),payment!L14:L1465,"<="&DATE(2026,4,7)) -> 0 | M43: =M42-C43+L43 -> 3509148.8
B44: April 8-15 | C44: =SUMIFS(payment!H14:H1448,payment!I14:I1448,">="&DATE(2026,4,8),payment!I14:I1448,"<="&DATE(2026,4,15)) -> 0.004 | E44: =SUMIFS(payment!H14:H1448,payment!I14:I1448,">="&DATE(2026,4,8),payment!I14:I1448,"<="&DATE(2026,4,15),payment!A14:A1448,"=TW") -> 0 | F44: =SUMIFS(payment!H14:H1448,payment!I14:I1448,">="&DATE(2026,4,8),payment!I14:I1448,"<="&DATE(2026,4,15),payment!A14:A1448,"=VARNISHED") -> 0 | G44: =SUMIFS(payment!H14:H1448,payment!I14:I1448,">="&DATE(2026,4,8),payment!I14:I1448,"<="&DATE(2026,4,15),payment!A14:A1448,"=NBE") -> 0 | H44: =SUMIFS(payment!H14:H1448,payment!I14:I1448,">="&DATE(2026,4,8),payment!I14:I1448,"<="&DATE(2026,4,15),payment!A14:A1448,"=PT") -> 0 | I44: =SUMIFS(payment!H14:H1448,payment!I14:I1448,">="&DATE(2026,4,8),payment!I14:I1448,"<="&DATE(2026,4,15),payment!A14:A1448,"=IN") -> 0.004 | J44: =SUMIFS(payment!I14:I1448,payment!J14:J1448,">="&DATE(2026,4,8),payment!J14:J1448,"<="&DATE(2026,4,15),payment!B14:B1448,"=NF") -> 0 | K44: =J44*7.1 -> 0 | L44: =SUMIFS(payment!H14:H1465,payment!L14:L1465,">="&DATE(2026,4,8),payment!L14:L1465,"<="&DATE(2026,4,15)) -> 0 | M44: =M43-C44+L44 -> 3509148.8
B45: April 16-23 | C45: =SUMIFS(payment!H14:H1448,payment!I14:I1448,">="&DATE(2026,4,16),payment!I14:I1448,"<="&DATE(2026,4,23)) -> 21506.25 | E45: =SUMIFS(payment!H14:H1448,payment!I14:I1448,">="&DATE(2026,4,16),payment!I14:I1448,"<="&DATE(2026,4,23),payment!A14:A1448,"=TW") -> 21506.25 | F45: =SUMIFS(payment!H14:H1448,payment!I14:I1448,">="&DATE(2026,4,16),payment!I14:I1448,"<="&DATE(2026,4,23),payment!A14:A1448,"=VARNISHED") -> 0 | G45: =SUMIFS(payment!H14:H1448,payment!I14:I1448,">="&DATE(2026,4,16),payment!I14:I1448,"<="&DATE(2026,4,23),payment!A14:A1448,"=NBE") -> 0 | H45: =SUMIFS(payment!H14:H1448,payment!I14:I1448,">="&DATE(2026,4,16),payment!I14:I1448,"<="&DATE(2026,4,23),payment!A14:A1448,"=PT") -> 0 | I45: =SUMIFS(payment!H14:H1448,payment!I14:I1448,">="&DATE(2026,4,16),payment!I14:I1448,"<="&DATE(2026,4,23),payment!A14:A1448,"=IN") -> 0 | J45: =SUMIFS(payment!I14:I1448,payment!J14:J1448,">="&DATE(2026,4,16),payment!J14:J1448,"<="&DATE(2026,4,23),payment!B14:B1448,"=NF") -> 0 | K45: =J45*7.1 -> 0 | L45: =SUMIFS(payment!H14:H1465,payment!L14:L1465,">="&DATE(2026,4,16),payment!L14:L1465,"<="&DATE(2026,4,23)) -> 0 | M45: =M44-C45+L45 -> 3487642.5
B46: April 24-31 | C46: =SUMIFS(payment!H14:H1448,payment!I14:I1448,">="&DATE(2026,4,24),payment!I14:I1448,"<="&DATE(2026,4,31)) -> 41474.165 | E46: =SUMIFS(payment!H14:H1448,payment!I14:I1448,">="&DATE(2026,4,24),payment!I14:I1448,"<="&DATE(2026,4,30),payment!A14:A1448,"=TW") -> 0 | F46: =SUMIFS(payment!H14:H1448,payment!I14:I1448,">="&DATE(2026,4,24),payment!I14:I1448,"<="&DATE(2026,4,30),payment!A14:A1448,"=VARNISHED") -> 0 | G46: =SUMIFS(payment!H14:H1448,payment!I14:I1448,">="&DATE(2026,4,24),payment!I14:I1448,"<="&DATE(2026,4,30),payment!A14:A1448,"=NBE") -> 0 | H46: =SUMIFS(payment!H14:H1448,payment!I14:I1448,">="&DATE(2026,4,24),payment!I14:I1448,"<="&DATE(2026,4,30),payment!A14:A1448,"=PT") -> 41474.165 | I46: =SUMIFS(payment!H14:H1448,payment!I14:I1448,">="&DATE(2026,4,24),payment!I14:I1448,"<="&DATE(2026,4,30),payment!A14:A1448,"=IN") -> 0 | J46: =SUMIFS(payment!I14:I1448,payment!J14:J1448,">="&DATE(2026,4,24),payment!J14:J1448,"<="&DATE(2026,4,30),payment!B14:B1448,"=NF") -> 0 | K46: =J46*7.1 -> 0 | L46: =SUMIFS(payment!H14:H1465,payment!L14:L1465,">="&DATE(2026,4,24),payment!L14:L1465,"<="&DATE(2026,4,30)) -> -0.0054749996 | M46: =M45-C46+L46 -> 3446168.3
B47: May 1-7 | C47: =SUMIFS(payment!H18:H1452,payment!I18:I1452,">="&DATE(2026,5,1),payment!I18:I1452,"<="&DATE(2026,5,7)) -> -0.00099999993 | E47: =SUMIFS(payment!H18:H1452,payment!I18:I1452,">="&DATE(2026,5,1),payment!I18:I1452,"<="&DATE(2026,5,7),payment!A18:A1452,"=TW") -> 0 | F47: =SUMIFS(payment!H18:H1452,payment!I18:I1452,">="&DATE(2026,5,1),payment!I18:I1452,"<="&DATE(2026,5,7),payment!A18:A1452,"=VARNISHED") -> 0 | G47: =SUMIFS(payment!H18:H1452,payment!I18:I1452,">="&DATE(2026,5,1),payment!I18:I1452,"<="&DATE(2026,5,7),payment!A18:A1452,"=NBE") -> 0 | H47: =SUMIFS(payment!H18:H1452,payment!I18:I1452,">="&DATE(2026,5,1),payment!I18:I1452,"<="&DATE(2026,5,7),payment!A18:A1452,"=PT") -> -0.00099999993 | I47: =SUMIFS(payment!H18:H1452,payment!I18:I1452,">="&DATE(2026,5,1),payment!I18:I1452,"<="&DATE(2026,5,7),payment!A18:A1452,"=IN") -> 0 | J47: =SUMIFS(payment!I18:I1452,payment!J18:J1452,">="&DATE(2026,5,1),payment!J18:J1452,"<="&DATE(2026,5,7),payment!B18:B1452,"=NF") -> 0 | K47: =J47*7.1 -> 0 | L47: =SUMIFS(payment!H18:H1469,payment!L18:L1469,">="&DATE(2026,5,1),payment!L18:L1469,"<="&DATE(2026,5,7)) -> 0 | M47: =M46-C47+L47 -> 3446168.3
B48: May 8-15 | C48: =SUMIFS(payment!H18:H1452,payment!I18:I1452,">="&DATE(2026,5,8),payment!I18:I1452,"<="&DATE(2026,5,15)) -> 239250 | E48: =SUMIFS(payment!H18:H1452,payment!I18:I1452,">="&DATE(2026,5,8),payment!I18:I1452,"<="&DATE(2026,5,15),payment!A18:A1452,"=TW") -> 239250 | F48: =SUMIFS(payment!H18:H1452,payment!I18:I1452,">="&DATE(2026,5,8),payment!I18:I1452,"<="&DATE(2026,5,15),payment!A18:A1452,"=VARNISHED") -> 0 | G48: =SUMIFS(payment!H18:H1452,payment!I18:I1452,">="&DATE(2026,5,8),payment!I18:I1452,"<="&DATE(2026,5,15),payment!A18:A1452,"=NBE") -> 0 | H48: =SUMIFS(payment!H18:H1452,payment!I18:I1452,">="&DATE(2026,5,8),payment!I18:I1452,"<="&DATE(2026,5,15),payment!A18:A1452,"=PT") -> 0 | I48: =SUMIFS(payment!H18:H1452,payment!I18:I1452,">="&DATE(2026,5,8),payment!I18:I1452,"<="&DATE(2026,5,15),payment!A18:A1452,"=IN") -> 0 | J48: =SUMIFS(payment!I18:I1452,payment!J18:J1452,">="&DATE(2026,5,8),payment!J18:J1452,"<="&DATE(2026,5,15),payment!B18:B1452,"=NF") -> 0 | K48: =J48*7.1 -> 0 | L48: =SUMIFS(payment!H18:H1469,payment!L18:L1469,">="&DATE(2026,5,8),payment!L18:L1469,"<="&DATE(2026,5,15)) -> 0 | M48: =M47-C48+L48 -> 3206918.3
B49: May 16-23 | C49: =SUMIFS(payment!H18:H1452,payment!I18:I1452,">="&DATE(2026,5,16),payment!I18:I1452,"<="&DATE(2026,5,23)) -> 8965.888 | E49: =SUMIFS(payment!H18:H1452,payment!I18:I1452,">="&DATE(2026,5,16),payment!I18:I1452,"<="&DATE(2026,5,23),payment!A18:A1452,"=TW") -> 8965.88 | F49: =SUMIFS(payment!H18:H1452,payment!I18:I1452,">="&DATE(2026,5,16),payment!I18:I1452,"<="&DATE(2026,5,23),payment!A18:A1452,"=VARNISHED") -> 0 | G49: =SUMIFS(payment!H18:H1452,payment!I18:I1452,">="&DATE(2026,5,16),payment!I18:I1452,"<="&DATE(2026,5,23),payment!A18:A1452,"=NBE") -> 0 | H49: =SUMIFS(payment!H18:H1452,payment!I18:I1452,">="&DATE(2026,5,16),payment!I18:I1452,"<="&DATE(2026,5,23),payment!A18:A1452,"=PT") -> 0.0080000001 | I49: =SUMIFS(payment!H18:H1452,payment!I18:I1452,">="&DATE(2026,5,16),payment!I18:I1452,"<="&DATE(2026,5,23),payment!A18:A1452,"=IN") -> 0 | J49: =SUMIFS(payment!I18:I1452,payment!J18:J1452,">="&DATE(2026,5,16),payment!J18:J1452,"<="&DATE(2026,5,23),payment!B18:B1452,"=NF") -> 0 | K49: =J49*7.1 -> 0 | L49: =SUMIFS(payment!H18:H1469,payment!L18:L1469,">="&DATE(2026,5,16),payment!L18:L1469,"<="&DATE(2026,5,23)) -> 0 | M49: =M48-C49+L49 -> 3197952.5
B50: May 24-31 | C50: =SUMIFS(payment!H18:H1452,payment!I18:I1452,">="&DATE(2026,5,24),payment!I18:I1452,"<="&DATE(2026,5,31)) -> 512008.4 | E50: =SUMIFS(payment!H18:H1452,payment!I18:I1452,">="&DATE(2026,5,24),payment!I18:I1452,"<="&DATE(2026,5,31),payment!A18:A1452,"=TW") -> 29750.004 | F50: =SUMIFS(payment!H18:H1452,payment!I18:I1452,">="&DATE(2026,5,24),payment!I18:I1452,"<="&DATE(2026,5,31),payment!A18:A1452,"=VARNISHED") -> 0 | G50: =SUMIFS(payment!H18:H1452,payment!I18:I1452,">="&DATE(2026,5,24),payment!I18:I1452,"<="&DATE(2026,5,31),payment!A18:A1452,"=NBE") -> 0 | H50: =SUMIFS(payment!H18:H1452,payment!I18:I1452,">="&DATE(2026,5,24),payment!I18:I1452,"<="&DATE(2026,5,31),payment!A18:A1452,"=PT") -> 0 | I50: =SUMIFS(payment!H18:H1452,payment!I18:I1452,">="&DATE(2026,5,24),payment!I18:I1452,"<="&DATE(2026,5,31),payment!A18:A1452,"=IN") -> 482258.4 | J50: =SUMIFS(payment!I18:I1452,payment!J18:J1452,">="&DATE(2026,5,24),payment!J18:J1452,"<="&DATE(2026,5,31),payment!B18:B1452,"=NF") -> 0 | K50: =J50*7.1 -> 0 | L50: =SUMIFS(payment!H18:H1469,payment!L18:L1469,">="&DATE(2026,5,24),payment!L18:L1469,"<="&DATE(2026,5,31)) -> 0 | M50: =M49-C50+L50 -> 2685944.1
B51: June 1-7 | C51: =SUMIFS(payment!H22:H1456,payment!I22:I1456,">="&DATE(2026,6,1),payment!I22:I1456,"<="&DATE(2026,6,7)) -> 83059.292 | E51: =SUMIFS(payment!H22:H1456,payment!I22:I1456,">="&DATE(2026,6,1),payment!I22:I1456,"<="&DATE(2026,6,7),payment!A22:A1456,"=TW") -> 56312.495 | F51: =SUMIFS(payment!H22:H1456,payment!I22:I1456,">="&DATE(2026,6,1),payment!I22:I1456,"<="&DATE(2026,6,7),payment!A22:A1456,"=VARNISHED") -> 0 | G51: =SUMIFS(payment!H22:H1456,payment!I22:I1456,">="&DATE(2026,6,1),payment!I22:I1456,"<="&DATE(2026,6,7),payment!A22:A1456,"=NBE") -> 26746.797 | H51: =SUMIFS(payment!H22:H1456,payment!I22:I1456,">="&DATE(2026,6,1),payment!I22:I1456,"<="&DATE(2026,6,7),payment!A22:A1456,"=PT") -> 0 | I51: =SUMIFS(payment!H22:H1456,payment!I22:I1456,">="&DATE(2026,6,1),payment!I22:I1456,"<="&DATE(2026,6,7),payment!A22:A1456,"=IN") -> 0 | J51: =SUMIFS(payment!I22:I1456,payment!J22:J1456,">="&DATE(2026,6,1),payment!J22:J1456,"<="&DATE(2026,6,7),payment!B22:B1456,"=NF") -> 0 | K51: =J51*7.1 -> 0 | L51: =SUMIFS(payment!H22:H1473,payment!L22:L1473,">="&DATE(2026,6,1),payment!L22:L1473,"<="&DATE(2026,6,7)) -> 0 | M51: =M50-C51+L51 -> 2602884.8
B52: June 8-15 | C52: =SUMIFS(payment!H22:H1456,payment!I22:I1456,">="&DATE(2026,6,8),payment!I22:I1456,"<="&DATE(2026,6,15)) -> 332989.94 | E52: =SUMIFS(payment!H22:H1456,payment!I22:I1456,">="&DATE(2026,6,8),payment!I22:I1456,"<="&DATE(2026,6,15),payment!A22:A1456,"=TW") -> 332989.94 | F52: =SUMIFS(payment!H22:H1456,payment!I22:I1456,">="&DATE(2026,6,8),payment!I22:I1456,"<="&DATE(2026,6,15),payment!A22:A1456,"=VARNISHED") -> 0 | G52: =SUMIFS(payment!H22:H1456,payment!I22:I1456,">="&DATE(2026,6,8),payment!I22:I1456,"<="&DATE(2026,6,15),payment!A22:A1456,"=NBE") -> 0 | H52: =SUMIFS(payment!H22:H1456,payment!I22:I1456,">="&DATE(2026,6,8),payment!I22:I1456,"<="&DATE(2026,6,15),payment!A22:A1456,"=PT") -> 0 | I52: =SUMIFS(payment!H22:H1456,payment!I22:I1456,">="&DATE(2026,6,8),payment!I22:I1456,"<="&DATE(2026,6,15),payment!A22:A1456,"=IN") -> 0 | J52: =SUMIFS(payment!I22:I1456,payment!J22:J1456,">="&DATE(2026,6,8),payment!J22:J1456,"<="&DATE(2026,6,15),payment!B22:B1456,"=NF") -> 0 | K52: =J52*7.1 -> 0 | L52: =SUMIFS(payment!H22:H1473,payment!L22:L1473,">="&DATE(2026,6,8),payment!L22:L1473,"<="&DATE(2026,6,15)) -> 0 | M52: =M51-C52+L52 -> 2269894.8
B53: June 16-23 | C53: =SUMIFS(payment!H22:H1456,payment!I22:I1456,">="&DATE(2026,6,16),payment!I22:I1456,"<="&DATE(2026,6,23)) -> 0 | E53: =SUMIFS(payment!H22:H1456,payment!I22:I1456,">="&DATE(2026,6,16),payment!I22:I1456,"<="&DATE(2026,6,23),payment!A22:A1456,"=TW") -> 0 | F53: =SUMIFS(payment!H22:H1456,payment!I22:I1456,">="&DATE(2026,6,16),payment!I22:I1456,"<="&DATE(2026,6,23),payment!A22:A1456,"=VARNISHED") -> 0 | G53: =SUMIFS(payment!H22:H1456,payment!I22:I1456,">="&DATE(2026,6,16),payment!I22:I1456,"<="&DATE(2026,6,23),payment!A22:A1456,"=NBE") -> 0 | H53: =SUMIFS(payment!H22:H1456,payment!I22:I1456,">="&DATE(2026,6,16),payment!I22:I1456,"<="&DATE(2026,6,23),payment!A22:A1456,"=PT") -> 0 | I53: =SUMIFS(payment!H22:H1456,payment!I22:I1456,">="&DATE(2026,6,16),payment!I22:I1456,"<="&DATE(2026,6,23),payment!A22:A1456,"=IN") -> 0 | J53: =SUMIFS(payment!I22:I1456,payment!J22:J1456,">="&DATE(2026,6,16),payment!J22:J1456,"<="&DATE(2026,6,23),payment!B22:B1456,"=NF") -> 0 | K53: =J53*7.1 -> 0 | L53: =SUMIFS(payment!H22:H1473,payment!L22:L1473,">="&DATE(2026,6,16),payment!L22:L1473,"<="&DATE(2026,6,23)) -> 0 | M53: =M52-C53+L53 -> 2269894.8
B54: June 24-30 | C54: =SUMIFS(payment!H22:H1456,payment!I22:I1456,">="&DATE(2026,6,24),payment!I22:I1456,"<="&DATE(2026,6,31)) -> 1143822 | E54: =SUMIFS(payment!H22:H1456,payment!I22:I1456,">="&DATE(2026,6,24),payment!I22:I1456,"<="&DATE(2026,6,30),payment!A22:A1456,"=TW") -> 650748.87 | F54: =SUMIFS(payment!H22:H1456,payment!I22:I1456,">="&DATE(2026,6,24),payment!I22:I1456,"<="&DATE(2026,6,30),payment!A22:A1456,"=VARNISHED") -> 0 | G54: =SUMIFS(payment!H22:H1456,payment!I22:I1456,">="&DATE(2026,6,24),payment!I22:I1456,"<="&DATE(2026,6,30),payment!A22:A1456,"=NBE") -> 0 | H54: =SUMIFS(payment!H22:H1456,payment!I22:I1456,">="&DATE(2026,6,24),payment!I22:I1456,"<="&DATE(2026,6,30),payment!A22:A1456,"=PT") -> 0 | I54: =SUMIFS(payment!H22:H1456,payment!I22:I1456,">="&DATE(2026,6,24),payment!I22:I1456,"<="&DATE(2026,6,30),payment!A22:A1456,"=IN") -> 482258.4 | J54: =SUMIFS(payment!I22:I1456,payment!J22:J1456,">="&DATE(2026,6,24),payment!J22:J1456,"<="&DATE(2026,6,30),payment!B22:B1456,"=NF") -> 0 | K54: =J54*7.1 -> 0 | L54: =SUMIFS(payment!H22:H1473,payment!L22:L1473,">="&DATE(2026,6,24),payment!L22:L1473,"<="&DATE(2026,6,30)) -> 0 | M54: =M53-C54+L54 -> 1126072.8
B55: July 1-7 | C55: =SUMIFS(payment!H26:H1460,payment!I26:I1460,">="&DATE(2026,7,1),payment!I26:I1460,"<="&DATE(2026,7,7)) -> 77540.495 | E55: =SUMIFS(payment!H26:H1460,payment!I26:I1460,">="&DATE(2026,7,1),payment!I26:I1460,"<="&DATE(2026,7,7),payment!A26:A1460,"=TW") -> 77540.495 | F55: =SUMIFS(payment!H26:H1460,payment!I26:I1460,">="&DATE(2026,7,1),payment!I26:I1460,"<="&DATE(2026,7,7),payment!A26:A1460,"=VARNISHED") -> 0 | G55: =SUMIFS(payment!H26:H1460,payment!I26:I1460,">="&DATE(2026,7,1),payment!I26:I1460,"<="&DATE(2026,7,7),payment!A26:A1460,"=NBE") -> 0 | H55: =SUMIFS(payment!H26:H1460,payment!I26:I1460,">="&DATE(2026,7,1),payment!I26:I1460,"<="&DATE(2026,7,7),payment!A26:A1460,"=PT") -> 0 | I55: =SUMIFS(payment!H26:H1460,payment!I26:I1460,">="&DATE(2026,7,1),payment!I26:I1460,"<="&DATE(2026,7,7),payment!A26:A1460,"=IN") -> 0 | J55: =SUMIFS(payment!I26:I1460,payment!J26:J1460,">="&DATE(2026,7,1),payment!J26:J1460,"<="&DATE(2026,7,7),payment!B26:B1460,"=NF") -> 0 | K55: =J55*7.1 -> 0 | L55: =SUMIFS(payment!H26:H1477,payment!L26:L1477,">="&DATE(2026,7,1),payment!L26:L1477,"<="&DATE(2026,7,7)) -> 0 | M55: =M54-C55+L55 -> 1048532.3
B56: July 8-15 | C56: =SUMIFS(payment!H26:H1460,payment!I26:I1460,">="&DATE(2026,7,8),payment!I26:I1460,"<="&DATE(2026,7,15)) -> 566486.38 | E56: =SUMIFS(payment!H26:H1460,payment!I26:I1460,">="&DATE(2026,7,8),payment!I26:I1460,"<="&DATE(2026,7,15),payment!A26:A1460,"=TW") -> 553575 | F56: =SUMIFS(payment!H26:H1460,payment!I26:I1460,">="&DATE(2026,7,8),payment!I26:I1460,"<="&DATE(2026,7,15),payment!A26:A1460,"=VARNISHED") -> 0 | G56: =SUMIFS(payment!H26:H1460,payment!I26:I1460,">="&DATE(2026,7,8),payment!I26:I1460,"<="&DATE(2026,7,15),payment!A26:A1460,"=NBE") -> 12911.38 | H56: =SUMIFS(payment!H26:H1460,payment!I26:I1460,">="&DATE(2026,7,8),payment!I26:I1460,"<="&DATE(2026,7,15),payment!A26:A1460,"=PT") -> -0.0020000001 | I56: =SUMIFS(payment!H26:H1460,payment!I26:I1460,">="&DATE(2026,7,8),payment!I26:I1460,"<="&DATE(2026,7,15),payment!A26:A1460,"=IN") -> 0 | J56: =SUMIFS(payment!I26:I1460,payment!J26:J1460,">="&DATE(2026,7,8),payment!J26:J1460,"<="&DATE(2026,7,15),payment!B26:B1460,"=NF") -> 0 | K56: =J56*7.1 -> 0 | L56: =SUMIFS(payment!H26:H1477,payment!L26:L1477,">="&DATE(2026,7,8),payment!L26:L1477,"<="&DATE(2026,7,15)) -> 0 | M56: =M55-C56+L56 -> 482045.96
B57: July 16-23 | C57: =SUMIFS(payment!H26:H1460,payment!I26:I1460,">="&DATE(2026,7,16),payment!I26:I1460,"<="&DATE(2026,7,23)) -> 144982.84 | E57: =SUMIFS(payment!H26:H1460,payment!I26:I1460,">="&DATE(2026,7,16),payment!I26:I1460,"<="&DATE(2026,7,23),payment!A26:A1460,"=TW") -> 0 | F57: =SUMIFS(payment!H26:H1460,payment!I26:I1460,">="&DATE(2026,7,16),payment!I26:I1460,"<="&DATE(2026,7,23),payment!A26:A1460,"=VARNISHED") -> 0 | G57: =SUMIFS(payment!H26:H1460,payment!I26:I1460,">="&DATE(2026,7,16),payment!I26:I1460,"<="&DATE(2026,7,23),payment!A26:A1460,"=NBE") -> 144982.84 | H57: =SUMIFS(payment!H26:H1460,payment!I26:I1460,">="&DATE(2026,7,16),payment!I26:I1460,"<="&DATE(2026,7,23),payment!A26:A1460,"=PT") -> 0 | I57: =SUMIFS(payment!H26:H1460,payment!I26:I1460,">="&DATE(2026,7,16),payment!I26:I1460,"<="&DATE(2026,7,23),payment!A26:A1460,"=IN") -> 0 | J57: =SUMIFS(payment!I26:I1460,payment!J26:J1460,">="&DATE(2026,7,16),payment!J26:J1460,"<="&DATE(2026,7,23),payment!B26:B1460,"=NF") -> 0 | K57: =J57*7.1 -> 0 | L57: =SUMIFS(payment!H26:H1477,payment!L26:L1477,">="&DATE(2026,7,16),payment!L26:L1477,"<="&DATE(2026,7,23)) -> 0 | M57: =M56-C57+L57 -> 337063.12
B58: July 24-31 | C58: =SUMIFS(payment!H26:H1460,payment!I26:I1460,">="&DATE(2026,7,24),payment!I26:I1460,"<="&DATE(2026,7,31)) -> 2018205.5 | E58: =SUMIFS(payment!H26:H1460,payment!I26:I1460,">="&DATE(2026,7,24),payment!I26:I1460,"<="&DATE(2026,7,31),payment!A26:A1460,"=TW") -> 0 | F58: =SUMIFS(payment!H26:H1460,payment!I26:I1460,">="&DATE(2026,7,24),payment!I26:I1460,"<="&DATE(2026,7,31),payment!A26:A1460,"=VARNISHED") -> 0 | G58: =SUMIFS(payment!H26:H1460,payment!I26:I1460,">="&DATE(2026,7,24),payment!I26:I1460,"<="&DATE(2026,7,31),payment!A26:A1460,"=NBE") -> 1535947.1 | H58: =SUMIFS(payment!H26:H1460,payment!I26:I1460,">="&DATE(2026,7,24),payment!I26:I1460,"<="&DATE(2026,7,31),payment!A26:A1460,"=PT") -> 0 | I58: =SUMIFS(payment!H26:H1460,payment!I26:I1460,">="&DATE(2026,7,24),payment!I26:I1460,"<="&DATE(2026,7,31),payment!A26:A1460,"=IN") -> 482258.4 | J58: =SUMIFS(payment!I26:I1460,payment!J26:J1460,">="&DATE(2026,7,24),payment!J26:J1460,"<="&DATE(2026,7,31),payment!B26:B1460,"=NF") -> 0 | K58: =J58*7.1 -> 0 | L58: =SUMIFS(payment!H26:H1477,payment!L26:L1477,">="&DATE(2026,7,24),payment!L26:L1477,"<="&DATE(2026,7,31)) -> 0.012 | M58: =M57-C58+L58 -> -1681142.4
B59: August 1-7 | C59: =SUMIFS(payment!H30:H1464,payment!I30:I1464,">="&DATE(2026,8,1),payment!I30:I1464,"<="&DATE(2026,8,7)) -> 4436495 | E59: =SUMIFS(payment!H30:H1464,payment!I30:I1464,">="&DATE(2026,8,1),payment!I30:I1464,"<="&DATE(2026,8,7),payment!A30:A1464,"=TW") -> 2548544.5 | F59: =SUMIFS(payment!H30:H1464,payment!I30:I1464,">="&DATE(2026,8,1),payment!I30:I1464,"<="&DATE(2026,8,7),payment!A30:A1464,"=VARNISHED") -> 0 | G59: =SUMIFS(payment!H30:H1464,payment!I30:I1464,">="&DATE(2026,8,1),payment!I30:I1464,"<="&DATE(2026,8,7),payment!A30:A1464,"=NBE") -> 0 | H59: =SUMIFS(payment!H30:H1464,payment!I30:I1464,">="&DATE(2026,8,1),payment!I30:I1464,"<="&DATE(2026,8,7),payment!A30:A1464,"=PT") -> 1887950.5 | I59: =SUMIFS(payment!H30:H1464,payment!I30:I1464,">="&DATE(2026,8,1),payment!I30:I1464,"<="&DATE(2026,8,7),payment!A30:A1464,"=IN") -> 0 | J59: =SUMIFS(payment!I30:I1464,payment!J30:J1464,">="&DATE(2026,8,1),payment!J30:J1464,"<="&DATE(2026,8,7),payment!B30:B1464,"=NF") -> 0 | K59: =J59*7.1 -> 0 | L59: =SUMIFS(payment!H30:H1481,payment!L30:L1481,">="&DATE(2026,8,1),payment!L30:L1481,"<="&DATE(2026,8,7)) -> 0 | M59: =M58-C59+L59 -> -6117637.4
B60: August 8-15 | C60: =SUMIFS(payment!H30:H1464,payment!I30:I1464,">="&DATE(2026,8,8),payment!I30:I1464,"<="&DATE(2026,8,15)) -> 538383.69 | E60: =SUMIFS(payment!H30:H1464,payment!I30:I1464,">="&DATE(2026,8,8),payment!I30:I1464,"<="&DATE(2026,8,15),payment!A30:A1464,"=TW") -> 311850 | F60: =SUMIFS(payment!H30:H1464,payment!I30:I1464,">="&DATE(2026,8,8),payment!I30:I1464,"<="&DATE(2026,8,15),payment!A30:A1464,"=VARNISHED") -> 0 | G60: =SUMIFS(payment!H30:H1464,payment!I30:I1464,">="&DATE(2026,8,8),payment!I30:I1464,"<="&DATE(2026,8,15),payment!A30:A1464,"=NBE") -> 0 | H60: =SUMIFS(payment!H30:H1464,payment!I30:I1464,">="&DATE(2026,8,8),payment!I30:I1464,"<="&DATE(2026,8,15),payment!A30:A1464,"=PT") -> 226533.69 | I60: =SUMIFS(payment!H30:H1464,payment!I30:I1464,">="&DATE(2026,8,8),payment!I30:I1464,"<="&DATE(2026,8,15),payment!A30:A1464,"=IN") -> 0 | J60: =SUMIFS(payment!I30:I1464,payment!J30:J1464,">="&DATE(2026,8,8),payment!J30:J1464,"<="&DATE(2026,8,15),payment!B30:B1464,"=NF") -> 0 | K60: =J60*7.1 -> 0 | L60: =SUMIFS(payment!H30:H1481,payment!L30:L1481,">="&DATE(2026,8,8),payment!L30:L1481,"<="&DATE(2026,8,15)) -> 0 | M60: =M59-C60+L60 -> -6656021.1
B61: August 16-23 | C61: =SUMIFS(payment!H30:H1464,payment!I30:I1464,">="&DATE(2026,8,16),payment!I30:I1464,"<="&DATE(2026,8,23)) -> 1195837.9 | E61: =SUMIFS(payment!H30:H1464,payment!I30:I1464,">="&DATE(2026,8,16),payment!I30:I1464,"<="&DATE(2026,8,23),payment!A30:A1464,"=TW") -> 1195837.9 | F61: =SUMIFS(payment!H30:H1464,payment!I30:I1464,">="&DATE(2026,8,16),payment!I30:I1464,"<="&DATE(2026,8,23),payment!A30:A1464,"=VARNISHED") -> 0 | G61: =SUMIFS(payment!H30:H1464,payment!I30:I1464,">="&DATE(2026,8,16),payment!I30:I1464,"<="&DATE(2026,8,23),payment!A30:A1464,"=NBE") -> 0 | H61: =SUMIFS(payment!H30:H1464,payment!I30:I1464,">="&DATE(2026,8,16),payment!I30:I1464,"<="&DATE(2026,8,23),payment!A30:A1464,"=PT") -> 0 | I61: =SUMIFS(payment!H30:H1464,payment!I30:I1464,">="&DATE(2026,8,16),payment!I30:I1464,"<="&DATE(2026,8,23),payment!A30:A1464,"=IN") -> 0 | J61: =SUMIFS(payment!I30:I1464,payment!J30:J1464,">="&DATE(2026,8,16),payment!J30:J1464,"<="&DATE(2026,8,23),payment!B30:B1464,"=NF") -> 0 | K61: =J61*7.1 -> 0 | L61: =SUMIFS(payment!H30:H1481,payment!L30:L1481,">="&DATE(2026,8,16),payment!L30:L1481,"<="&DATE(2026,8,23)) -> 0 | M61: =M60-C61+L61 -> -7851859
B62: August 24-31 | C62: =SUMIFS(payment!H30:H1464,payment!I30:I1464,">="&DATE(2026,8,24),payment!I30:I1464,"<="&DATE(2026,8,31)) -> 3522593.8 | E62: =SUMIFS(payment!H30:H1464,payment!I30:I1464,">="&DATE(2026,8,24),payment!I30:I1464,"<="&DATE(2026,8,31),payment!A30:A1464,"=TW") -> 1781586.9 | F62: =SUMIFS(payment!H30:H1464,payment!I30:I1464,">="&DATE(2026,8,24),payment!I30:I1464,"<="&DATE(2026,8,31),payment!A30:A1464,"=VARNISHED") -> 0 | G62: =SUMIFS(payment!H30:H1464,payment!I30:I1464,">="&DATE(2026,8,24),payment!I30:I1464,"<="&DATE(2026,8,31),payment!A30:A1464,"=NBE") -> 0 | H62: =SUMIFS(payment!H30:H1464,payment!I30:I1464,">="&DATE(2026,8,24),payment!I30:I1464,"<="&DATE(2026,8,31),payment!A30:A1464,"=PT") -> 0 | I62: =SUMIFS(payment!H30:H1464,payment!I30:I1464,">="&DATE(2026,8,24),payment!I30:I1464,"<="&DATE(2026,8,31),payment!A30:A1464,"=IN") -> 146124 | J62: =SUMIFS(payment!I30:I1464,payment!J30:J1464,">="&DATE(2026,8,24),payment!J30:J1464,"<="&DATE(2026,8,31),payment!B30:B1464,"=NF") -> 0 | K62: =J62*7.1 -> 0 | L62: =SUMIFS(payment!H30:H1481,payment!L30:L1481,">="&DATE(2026,8,24),payment!L30:L1481,"<="&DATE(2026,8,31)) -> 0 | M62: =M61-C62+L62 -> -11374453
B63: September 1-7 | C63: =SUMIFS(payment!H34:H1468,payment!I34:I1468,">="&DATE(2026,9,1),payment!I34:I1468,"<="&DATE(2026,9,7)) -> 639158 | E63: =SUMIFS(payment!H34:H1468,payment!I34:I1468,">="&DATE(2026,9,1),payment!I34:I1468,"<="&DATE(2026,9,7),payment!A34:A1468,"=TW") -> 639158 | F63: =SUMIFS(payment!H34:H1468,payment!I34:I1468,">="&DATE(2026,9,1),payment!I34:I1468,"<="&DATE(2026,9,7),payment!A34:A1468,"=VARNISHED") -> 0 | G63: =SUMIFS(payment!H34:H1468,payment!I34:I1468,">="&DATE(2026,9,1),payment!I34:I1468,"<="&DATE(2026,9,7),payment!A34:A1468,"=NBE") -> 0 | H63: =SUMIFS(payment!H34:H1468,payment!I34:I1468,">="&DATE(2026,9,1),payment!I34:I1468,"<="&DATE(2026,9,7),payment!A34:A1468,"=PT") -> 0 | I63: =SUMIFS(payment!H34:H1468,payment!I34:I1468,">="&DATE(2026,9,1),payment!I34:I1468,"<="&DATE(2026,9,7),payment!A34:A1468,"=IN") -> 0 | J63: =SUMIFS(payment!I34:I1468,payment!J34:J1468,">="&DATE(2026,9,1),payment!J34:J1468,"<="&DATE(2026,9,7),payment!B34:B1468,"=NF") -> 0 | K63: =J63*7.1 -> 0 | L63: =SUMIFS(payment!H34:H1485,payment!L34:L1485,">="&DATE(2026,9,1),payment!L34:L1485,"<="&DATE(2026,9,7)) -> 0 | M63: =M62-C63+L63 -> -12013611
B64: September 8-15 | C64: =SUMIFS(payment!H34:H1468,payment!I34:I1468,">="&DATE(2026,9,8),payment!I34:I1468,"<="&DATE(2026,9,15)) -> 3282384.8 | E64: =SUMIFS(payment!H34:H1468,payment!I34:I1468,">="&DATE(2026,9,8),payment!I34:I1468,"<="&DATE(2026,9,15),payment!A34:A1468,"=TW") -> 1579536.8 | F64: =SUMIFS(payment!H34:H1468,payment!I34:I1468,">="&DATE(2026,9,8),payment!I34:I1468,"<="&DATE(2026,9,15),payment!A34:A1468,"=VARNISHED") -> 1702848 | G64: =SUMIFS(payment!H34:H1468,payment!I34:I1468,">="&DATE(2026,9,8),payment!I34:I1468,"<="&DATE(2026,9,15),payment!A34:A1468,"=NBE") -> 0 | H64: =SUMIFS(payment!H34:H1468,payment!I34:I1468,">="&DATE(2026,9,8),payment!I34:I1468,"<="&DATE(2026,9,15),payment!A34:A1468,"=PT") -> 0 | I64: =SUMIFS(payment!H34:H1468,payment!I34:I1468,">="&DATE(2026,9,8),payment!I34:I1468,"<="&DATE(2026,9,15),payment!A34:A1468,"=IN") -> 0 | J64: =SUMIFS(payment!I34:I1468,payment!J34:J1468,">="&DATE(2026,9,8),payment!J34:J1468,"<="&DATE(2026,9,15),payment!B34:B1468,"=NF") -> 0 | K64: =J64*7.1 -> 0 | L64: =SUMIFS(payment!H34:H1485,payment!L34:L1485,">="&DATE(2026,9,8),payment!L34:L1485,"<="&DATE(2026,9,15)) -> 0 | M64: =M63-C64+L64 -> -15295996
B65: September 16-23 | C65: =SUMIFS(payment!H34:H1468,payment!I34:I1468,">="&DATE(2026,9,16),payment!I34:I1468,"<="&DATE(2026,9,23)) -> 0 | E65: =SUMIFS(payment!H34:H1468,payment!I34:I1468,">="&DATE(2026,9,16),payment!I34:I1468,"<="&DATE(2026,9,23),payment!A34:A1468,"=TW") -> 0 | F65: =SUMIFS(payment!H34:H1468,payment!I34:I1468,">="&DATE(2026,9,16),payment!I34:I1468,"<="&DATE(2026,9,23),payment!A34:A1468,"=VARNISHED") -> 0 | G65: =SUMIFS(payment!H34:H1468,payment!I34:I1468,">="&DATE(2026,9,16),payment!I34:I1468,"<="&DATE(2026,9,23),payment!A34:A1468,"=NBE") -> 0 | H65: =SUMIFS(payment!H34:H1468,payment!I34:I1468,">="&DATE(2026,9,16),payment!I34:I1468,"<="&DATE(2026,9,23),payment!A34:A1468,"=PT") -> 0 | I65: =SUMIFS(payment!H34:H1468,payment!I34:I1468,">="&DATE(2026,9,16),payment!I34:I1468,"<="&DATE(2026,9,23),payment!A34:A1468,"=IN") -> 0 | J65: =SUMIFS(payment!I34:I1468,payment!J34:J1468,">="&DATE(2026,9,16),payment!J34:J1468,"<="&DATE(2026,9,23),payment!B34:B1468,"=NF") -> 0 | K65: =J65*7.1 -> 0 | L65: =SUMIFS(payment!H34:H1485,payment!L34:L1485,">="&DATE(2026,9,16),payment!L34:L1485,"<="&DATE(2026,9,23)) -> 0 | M65: =M64-C65+L65 -> -15295996
B66: September 24-30 | C66: =SUMIFS(payment!H34:H1468,payment!I34:I1468,">="&DATE(2026,9,24),payment!I34:I1468,"<="&DATE(2026,9,31)) -> 1770835.9 | E66: =SUMIFS(payment!H34:H1468,payment!I34:I1468,">="&DATE(2026,9,24),payment!I34:I1468,"<="&DATE(2026,9,31),payment!A34:A1468,"=TW") -> 1050166.4 | F66: =SUMIFS(payment!H34:H1468,payment!I34:I1468,">="&DATE(2026,9,24),payment!I34:I1468,"<="&DATE(2026,9,31),payment!A34:A1468,"=VARNISHED") -> 0 | G66: =SUMIFS(payment!H34:H1468,payment!I34:I1468,">="&DATE(2026,9,24),payment!I34:I1468,"<="&DATE(2026,9,31),payment!A34:A1468,"=NBE") -> 0 | H66: =SUMIFS(payment!H34:H1468,payment!I34:I1468,">="&DATE(2026,9,24),payment!I34:I1468,"<="&DATE(2026,9,31),payment!A34:A1468,"=PT") -> 0 | I66: =SUMIFS(payment!H34:H1468,payment!I34:I1468,">="&DATE(2026,9,24),payment!I34:I1468,"<="&DATE(2026,9,31),payment!A34:A1468,"=IN") -> 720669.57 | J66: =SUMIFS(payment!I34:I1468,payment!J34:J1468,">="&DATE(2026,9,24),payment!J34:J1468,"<="&DATE(2026,9,31),payment!B34:B1468,"=NF") -> 0 | K66: =J66*7.1 -> 0 | L66: =SUMIFS(payment!H34:H1485,payment!L34:L1485,">="&DATE(2026,9,24),payment!L34:L1485,"<="&DATE(2026,9,31)) -> 1887950.5 | M66: =M65-C66+L66 -> -15178881
B67: October 1-7 | C67: =SUMIFS(payment!H38:H1472,payment!I38:I1472,">="&DATE(2026,10,1),payment!I38:I1472,"<="&DATE(2026,10,7)) -> 720669.57 | E67: =SUMIFS(payment!H38:H1472,payment!I38:I1472,">="&DATE(2026,10,1),payment!I38:I1472,"<="&DATE(2026,10,7),payment!A38:A1472,"=TW") -> 0 | F67: =SUMIFS(payment!H38:H1472,payment!I38:I1472,">="&DATE(2026,10,1),payment!I38:I1472,"<="&DATE(2026,10,7),payment!A38:A1472,"=VARNISHED") -> 0 | G67: =SUMIFS(payment!H38:H1472,payment!I38:I1472,">="&DATE(2026,10,1),payment!I38:I1472,"<="&DATE(2026,10,7),payment!A38:A1472,"=NBE") -> 0 | H67: =SUMIFS(payment!H38:H1472,payment!I38:I1472,">="&DATE(2026,10,1),payment!I38:I1472,"<="&DATE(2026,10,7),payment!A38:A1472,"=PT") -> 0 | I67: =SUMIFS(payment!H38:H1472,payment!I38:I1472,">="&DATE(2026,10,1),payment!I38:I1472,"<="&DATE(2026,10,7),payment!A38:A1472,"=IN") -> 720669.57 | J67: =SUMIFS(payment!I38:I1472,payment!J38:J1472,">="&DATE(2026,10,1),payment!J38:J1472,"<="&DATE(2026,10,7),payment!B38:B1472,"=NF") -> 0 | K67: =J67*7.1 -> 0 | L67: =SUMIFS(payment!H38:H1489,payment!L38:L1489,">="&DATE(2026,10,1),payment!L38:L1489,"<="&DATE(2026,10,7)) -> 0 | M67: =M66-C67+L67 -> -15899551
B68: October 8-15 | C68: =SUMIFS(payment!H38:H1472,payment!I38:I1472,">="&DATE(2026,10,8),payment!I38:I1472,"<="&DATE(2026,10,15)) -> 29798.08 | E68: =SUMIFS(payment!H38:H1472,payment!I38:I1472,">="&DATE(2026,10,8),payment!I38:I1472,"<="&DATE(2026,10,15),payment!A38:A1472,"=TW") -> 0 | F68: =SUMIFS(payment!H38:H1472,payment!I38:I1472,">="&DATE(2026,10,8),payment!I38:I1472,"<="&DATE(2026,10,15),payment!A38:A1472,"=VARNISHED") -> 0 | G68: =SUMIFS(payment!H38:H1472,payment!I38:I1472,">="&DATE(2026,10,8),payment!I38:I1472,"<="&DATE(2026,10,15),payment!A38:A1472,"=NBE") -> 0 | H68: =SUMIFS(payment!H38:H1472,payment!I38:I1472,">="&DATE(2026,10,8),payment!I38:I1472,"<="&DATE(2026,10,15),payment!A38:A1472,"=PT") -> 0 | I68: =SUMIFS(payment!H38:H1472,payment!I38:I1472,">="&DATE(2026,10,8),payment!I38:I1472,"<="&DATE(2026,10,15),payment!A38:A1472,"=IN") -> 0 | J68: =SUMIFS(payment!I38:I1472,payment!J38:J1472,">="&DATE(2026,10,8),payment!J38:J1472,"<="&DATE(2026,10,15),payment!B38:B1472,"=NF") -> 0 | K68: =J68*7.1 -> 0 | L68: =SUMIFS(payment!H38:H1489,payment!L38:L1489,">="&DATE(2026,10,8),payment!L38:L1489,"<="&DATE(2026,10,15)) -> 0 | M68: =M67-C68+L68 -> -15929349
B69: October 16-23 | C69: =SUMIFS(payment!H38:H1472,payment!I38:I1472,">="&DATE(2026,10,16),payment!I38:I1472,"<="&DATE(2026,10,23)) -> 0 | E69: =SUMIFS(payment!H38:H1472,payment!I38:I1472,">="&DATE(2026,10,16),payment!I38:I1472,"<="&DATE(2026,10,23),payment!A38:A1472,"=TW") -> 0 | F69: =SUMIFS(payment!H38:H1472,payment!I38:I1472,">="&DATE(2026,10,16),payment!I38:I1472,"<="&DATE(2026,10,23),payment!A38:A1472,"=VARNISHED") -> 0 | G69: =SUMIFS(payment!H38:H1472,payment!I38:I1472,">="&DATE(2026,10,16),payment!I38:I1472,"<="&DATE(2026,10,23),payment!A38:A1472,"=NBE") -> 0 | H69: =SUMIFS(payment!H38:H1472,payment!I38:I1472,">="&DATE(2026,10,16),payment!I38:I1472,"<="&DATE(2026,10,23),payment!A38:A1472,"=PT") -> 0 | I69: =SUMIFS(payment!H38:H1472,payment!I38:I1472,">="&DATE(2026,10,16),payment!I38:I1472,"<="&DATE(2026,10,23),payment!A38:A1472,"=IN") -> 0 | J69: =SUMIFS(payment!I38:I1472,payment!J38:J1472,">="&DATE(2026,10,16),payment!J38:J1472,"<="&DATE(2026,10,23),payment!B38:B1472,"=NF") -> 0 | K69: =J69*7.1 -> 0 | L69: =SUMIFS(payment!H38:H1489,payment!L38:L1489,">="&DATE(2026,10,16),payment!L38:L1489,"<="&DATE(2026,10,23)) -> 0 | M69: =M68-C69+L69 -> -15929349
B70: October 24-31 | C70: =SUMIFS(payment!H38:H1472,payment!I38:I1472,">="&DATE(2026,10,24),payment!I38:I1472,"<="&DATE(2026,10,31)) -> 0 | E70: =SUMIFS(payment!H38:H1472,payment!I38:I1472,">="&DATE(2026,10,24),payment!I38:I1472,"<="&DATE(2026,10,31),payment!A38:A1472,"=TW") -> 0 | F70: =SUMIFS(payment!H38:H1472,payment!I38:I1472,">="&DATE(2026,10,24),payment!I38:I1472,"<="&DATE(2026,10,31),payment!A38:A1472,"=VARNISHED") -> 0 | G70: =SUMIFS(payment!H38:H1472,payment!I38:I1472,">="&DATE(2026,10,24),payment!I38:I1472,"<="&DATE(2026,10,31),payment!A38:A1472,"=NBE") -> 0 | H70: =SUMIFS(payment!H38:H1472,payment!I38:I1472,">="&DATE(2026,10,24),payment!I38:I1472,"<="&DATE(2026,10,31),payment!A38:A1472,"=PT") -> 0 | I70: =SUMIFS(payment!H38:H1472,payment!I38:I1472,">="&DATE(2026,10,24),payment!I38:I1472,"<="&DATE(2026,10,31),payment!A38:A1472,"=IN") -> 0 | J70: =SUMIFS(payment!I38:I1472,payment!J38:J1472,">="&DATE(2026,10,24),payment!J38:J1472,"<="&DATE(2026,10,31),payment!B38:B1472,"=NF") -> 0 | K70: =J70*7.1 -> 0 | L70: =SUMIFS(payment!H38:H1489,payment!L38:L1489,">="&DATE(2026,10,24),payment!L38:L1489,"<="&DATE(2026,10,31)) -> 226533.69 | M70: =M69-C70+L70 -> -15702815
B71: November 1-7 | C71: =SUMIFS(payment!H42:H1476,payment!I42:I1476,">="&DATE(2026,11,1),payment!I42:I1476,"<="&DATE(2026,11,7)) -> 900218 | E71: =SUMIFS(payment!H42:H1476,payment!I42:I1476,">="&DATE(2026,11,1),payment!I42:I1476,"<="&DATE(2026,11,7),payment!A42:A1476,"=TW") -> 0 | F71: =SUMIFS(payment!H42:H1476,payment!I42:I1476,">="&DATE(2026,11,1),payment!I42:I1476,"<="&DATE(2026,11,7),payment!A42:A1476,"=VARNISHED") -> 0 | G71: =SUMIFS(payment!H42:H1476,payment!I42:I1476,">="&DATE(2026,11,1),payment!I42:I1476,"<="&DATE(2026,11,7),payment!A42:A1476,"=NBE") -> 0 | H71: =SUMIFS(payment!H42:H1476,payment!I42:I1476,">="&DATE(2026,11,1),payment!I42:I1476,"<="&DATE(2026,11,7),payment!A42:A1476,"=PT") -> 0 | I71: =SUMIFS(payment!H42:H1476,payment!I42:I1476,">="&DATE(2026,11,1),payment!I42:I1476,"<="&DATE(2026,11,7),payment!A42:A1476,"=IN") -> 900218 | J71: =SUMIFS(payment!I42:I1476,payment!J42:J1476,">="&DATE(2026,11,1),payment!J42:J1476,"<="&DATE(2026,11,7),payment!B42:B1476,"=NF") -> 0 | K71: =J71*7.1 -> 0 | L71: =SUMIFS(payment!H42:H1493,payment!L42:L1493,">="&DATE(2026,11,1),payment!L42:L1493,"<="&DATE(2026,11,7)) -> 0 | M71: =M70-C71+L71 -> -16603033
B72: November 8-15 | C72: =SUMIFS(payment!H42:H1476,payment!I42:I1476,">="&DATE(2026,11,8),payment!I42:I1476,"<="&DATE(2026,11,15)) -> 154000 | E72: =SUMIFS(payment!H42:H1476,payment!I42:I1476,">="&DATE(2026,11,8),payment!I42:I1476,"<="&DATE(2026,11,15),payment!A42:A1476,"=TW") -> 154000 | F72: =SUMIFS(payment!H42:H1476,payment!I42:I1476,">="&DATE(2026,11,8),payment!I42:I1476,"<="&DATE(2026,11,15),payment!A42:A1476,"=VARNISHED") -> 0 | G72: =SUMIFS(payment!H42:H1476,payment!I42:I1476,">="&DATE(2026,11,8),payment!I42:I1476,"<="&DATE(2026,11,15),payment!A42:A1476,"=NBE") -> 0 | H72: =SUMIFS(payment!H42:H1476,payment!I42:I1476,">="&DATE(2026,11,8),payment!I42:I1476,"<="&DATE(2026,11,15),payment!A42:A1476,"=PT") -> 0 | I72: =SUMIFS(payment!H42:H1476,payment!I42:I1476,">="&DATE(2026,11,8),payment!I42:I1476,"<="&DATE(2026,11,15),payment!A42:A1476,"=IN") -> 0 | J72: =SUMIFS(payment!I42:I1476,payment!J42:J1476,">="&DATE(2026,11,8),payment!J42:J1476,"<="&DATE(2026,11,15),payment!B42:B1476,"=NF") -> 0 | K72: =J72*7.1 -> 0 | L72: =SUMIFS(payment!H42:H1493,payment!L42:L1493,">="&DATE(2026,11,8),payment!L42:L1493,"<="&DATE(2026,11,15)) -> 0 | M72: =M71-C72+L72 -> -16757033
B73: November 16-23 | C73: =SUMIFS(payment!H42:H1476,payment!I42:I1476,">="&DATE(2026,11,16),payment!I42:I1476,"<="&DATE(2026,11,23)) -> 0 | E73: =SUMIFS(payment!H42:H1476,payment!I42:I1476,">="&DATE(2026,11,16),payment!I42:I1476,"<="&DATE(2026,11,23),payment!A42:A1476,"=TW") -> 0 | F73: =SUMIFS(payment!H42:H1476,payment!I42:I1476,">="&DATE(2026,11,16),payment!I42:I1476,"<="&DATE(2026,11,23),payment!A42:A1476,"=VARNISHED") -> 0 | G73: =SUMIFS(payment!H42:H1476,payment!I42:I1476,">="&DATE(2026,11,16),payment!I42:I1476,"<="&DATE(2026,11,23),payment!A42:A1476,"=NBE") -> 0 | H73: =SUMIFS(payment!H42:H1476,payment!I42:I1476,">="&DATE(2026,11,16),payment!I42:I1476,"<="&DATE(2026,11,23),payment!A42:A1476,"=PT") -> 0 | I73: =SUMIFS(payment!H42:H1476,payment!I42:I1476,">="&DATE(2026,11,16),payment!I42:I1476,"<="&DATE(2026,11,23),payment!A42:A1476,"=IN") -> 0 | J73: =SUMIFS(payment!I42:I1476,payment!J42:J1476,">="&DATE(2026,11,16),payment!J42:J1476,"<="&DATE(2026,11,23),payment!B42:B1476,"=NF") -> 0 | K73: =J73*7.1 -> 0 | L73: =SUMIFS(payment!H42:H1493,payment!L42:L1493,">="&DATE(2026,11,16),payment!L42:L1493,"<="&DATE(2026,11,23)) -> 0 | M73: =M72-C73+L73 -> -16757033
B74: November 24-30 | C74: =SUMIFS(payment!H42:H1476,payment!I42:I1476,">="&DATE(2026,11,24),payment!I42:I1476,"<="&DATE(2026,11,31)) -> 900218 | E74: =SUMIFS(payment!H42:H1476,payment!I42:I1476,">="&DATE(2026,11,24),payment!I42:I1476,"<="&DATE(2026,11,31),payment!A42:A1476,"=TW") -> 0 | F74: =SUMIFS(payment!H42:H1476,payment!I42:I1476,">="&DATE(2026,12,24),payment!I42:I1476,"<="&DATE(2026,12,31),payment!A42:A1476,"=VARNISHED") -> 0 | G74: =SUMIFS(payment!H42:H1476,payment!I42:I1476,">="&DATE(2026,11,24),payment!I42:I1476,"<="&DATE(2026,11,31),payment!A42:A1476,"=NBE") -> 0 | H74: =SUMIFS(payment!H42:H1476,payment!I42:I1476,">="&DATE(2026,11,24),payment!I42:I1476,"<="&DATE(2026,11,31),payment!A42:A1476,"=PT") -> 0 | I74: =SUMIFS(payment!H42:H1476,payment!I42:I1476,">="&DATE(2026,11,24),payment!I42:I1476,"<="&DATE(2026,11,31),payment!A42:A1476,"=IN") -> 900218 | J74: =SUMIFS(payment!I42:I1476,payment!J42:J1476,">="&DATE(2026,11,24),payment!J42:J1476,"<="&DATE(2026,11,31),payment!B42:B1476,"=NF") -> 0 | K74: =J74*7.1 -> 0 | L74: =SUMIFS(payment!H42:H1493,payment!L42:L1493,">="&DATE(2026,11,24),payment!L42:L1493,"<="&DATE(2026,11,31)) -> 0 | M74: =M73-C74+L74 -> -17657251
B75: December 1-7 | C75: =SUMIFS(payment!H46:H1480,payment!I46:I1480,">="&DATE(2026,12,1),payment!I46:I1480,"<="&DATE(2026,12,7)) -> 900218 | E75: =SUMIFS(payment!H46:H1480,payment!I46:I1480,">="&DATE(2026,12,1),payment!I46:I1480,"<="&DATE(2026,12,7),payment!A46:A1480,"=TW") -> 0 | F75: =SUMIFS(payment!H46:H1480,payment!I46:I1480,">="&DATE(2026,12,1),payment!I46:I1480,"<="&DATE(2026,12,7),payment!A46:A1480,"=VARNISHED") -> 0 | G75: =SUMIFS(payment!H46:H1480,payment!I46:I1480,">="&DATE(2026,12,1),payment!I46:I1480,"<="&DATE(2026,12,7),payment!A46:A1480,"=NBE") -> 0 | H75: =SUMIFS(payment!H46:H1480,payment!I46:I1480,">="&DATE(2026,12,1),payment!I46:I1480,"<="&DATE(2026,12,7),payment!A46:A1480,"=PT") -> 0 | I75: =SUMIFS(payment!H46:H1480,payment!I46:I1480,">="&DATE(2026,12,1),payment!I46:I1480,"<="&DATE(2026,12,7),payment!A46:A1480,"=IN") -> 900218 | J75: =SUMIFS(payment!I46:I1480,payment!J46:J1480,">="&DATE(2026,12,1),payment!J46:J1480,"<="&DATE(2026,12,7),payment!B46:B1480,"=NF") -> 0 | K75: =J75*7.1 -> 0 | L75: =SUMIFS(payment!H46:H1497,payment!L46:L1497,">="&DATE(2026,12,1),payment!L46:L1497,"<="&DATE(2026,12,7)) -> 0 | M75: =M74-C75+L75 -> -18557469
B76: December 8-15 | C76: =SUMIFS(payment!H46:H1480,payment!I46:I1480,">="&DATE(2026,12,8),payment!I46:I1480,"<="&DATE(2026,12,15)) -> 154000 | E76: =SUMIFS(payment!H46:H1480,payment!I46:I1480,">="&DATE(2026,12,8),payment!I46:I1480,"<="&DATE(2026,12,15),payment!A46:A1480,"=TW") -> 154000 | F76: =SUMIFS(payment!H46:H1480,payment!I46:I1480,">="&DATE(2026,12,8),payment!I46:I1480,"<="&DATE(2026,12,15),payment!A46:A1480,"=VARNISHED") -> 0 | G76: =SUMIFS(payment!H46:H1480,payment!I46:I1480,">="&DATE(2026,12,8),payment!I46:I1480,"<="&DATE(2026,12,15),payment!A46:A1480,"=NBE") -> 0 | H76: =SUMIFS(payment!H46:H1480,payment!I46:I1480,">="&DATE(2026,12,8),payment!I46:I1480,"<="&DATE(2026,12,15),payment!A46:A1480,"=PT") -> 0 | I76: =SUMIFS(payment!H46:H1480,payment!I46:I1480,">="&DATE(2026,12,8),payment!I46:I1480,"<="&DATE(2026,12,15),payment!A46:A1480,"=IN") -> 0 | J76: =SUMIFS(payment!I46:I1480,payment!J46:J1480,">="&DATE(2026,12,8),payment!J46:J1480,"<="&DATE(2026,12,15),payment!B46:B1480,"=NF") -> 0 | K76: =J76*7.1 -> 0 | L76: =SUMIFS(payment!H46:H1497,payment!L46:L1497,">="&DATE(2026,12,8),payment!L46:L1497,"<="&DATE(2026,12,15)) -> 0 | M76: =M75-C76+L76 -> -18711469
B77: December 16-23 | C77: =SUMIFS(payment!H46:H1480,payment!I46:I1480,">="&DATE(2026,12,16),payment!I46:I1480,"<="&DATE(2026,12,23)) -> 0 | E77: =SUMIFS(payment!H46:H1480,payment!I46:I1480,">="&DATE(2026,12,16),payment!I46:I1480,"<="&DATE(2026,12,23),payment!A46:A1480,"=TW") -> 0 | F77: =SUMIFS(payment!H46:H1480,payment!I46:I1480,">="&DATE(2026,12,16),payment!I46:I1480,"<="&DATE(2026,12,23),payment!A46:A1480,"=VARNISHED") -> 0 | G77: =SUMIFS(payment!H46:H1480,payment!I46:I1480,">="&DATE(2026,12,16),payment!I46:I1480,"<="&DATE(2026,12,23),payment!A46:A1480,"=NBE") -> 0 | H77: =SUMIFS(payment!H46:H1480,payment!I46:I1480,">="&DATE(2026,12,16),payment!I46:I1480,"<="&DATE(2026,12,23),payment!A46:A1480,"=PT") -> 0 | I77: =SUMIFS(payment!H46:H1480,payment!I46:I1480,">="&DATE(2026,12,16),payment!I46:I1480,"<="&DATE(2026,12,23),payment!A46:A1480,"=IN") -> 0 | J77: =SUMIFS(payment!I46:I1480,payment!J46:J1480,">="&DATE(2026,12,16),payment!J46:J1480,"<="&DATE(2026,12,23),payment!B46:B1480,"=NF") -> 0 | K77: =J77*7.1 -> 0 | L77: =SUMIFS(payment!H46:H1497,payment!L46:L1497,">="&DATE(2026,12,16),payment!L46:L1497,"<="&DATE(2026,12,23)) -> 0 | M77: =M76-C77+L77 -> -18711469
B78: December 24-31 | C78: =SUMIFS(payment!H46:H1480,payment!I46:I1480,">="&DATE(2026,12,24),payment!I46:I1480,"<="&DATE(2026,12,31)) -> 0 | E78: =SUMIFS(payment!H46:H1480,payment!I46:I1480,">="&DATE(2026,12,24),payment!I46:I1480,"<="&DATE(2026,12,31),payment!A46:A1480,"=TW") -> 0 | F78: =SUMIFS(payment!H46:H1480,payment!I46:I1480,">="&DATE(2026,12,24),payment!I46:I1480,"<="&DATE(2026,12,31),payment!A46:A1480,"=VARNISHED") -> 0 | G78: =SUMIFS(payment!H46:H1480,payment!I46:I1480,">="&DATE(2026,12,24),payment!I46:I1480,"<="&DATE(2026,12,31),payment!A46:A1480,"=NBE") -> 0 | H78: =SUMIFS(payment!H46:H1480,payment!I46:I1480,">="&DATE(2026,12,24),payment!I46:I1480,"<="&DATE(2026,12,31),payment!A46:A1480,"=PT") -> 0 | I78: =SUMIFS(payment!H46:H1480,payment!I46:I1480,">="&DATE(2026,12,24),payment!I46:I1480,"<="&DATE(2026,12,31),payment!A46:A1480,"=IN") -> 0 | J78: =SUMIFS(payment!I46:I1480,payment!J46:J1480,">="&DATE(2026,12,24),payment!J46:J1480,"<="&DATE(2026,12,31),payment!B46:B1480,"=NF") -> 0 | K78: =J78*7.1 -> 0 | L78: =SUMIFS(payment!H46:H1497,payment!L46:L1497,">="&DATE(2026,12,24),payment!L46:L1497,"<="&DATE(2026,12,31)) -> 0 | M78: =M77-C78+L78 -> -18711469
E79: =SUM(E2:E78) -> 11385319 | F79: =SUM(F2:F78) -> 2199615.4 | G79: =SUM(G2:G78) -> 1720588.4 | H79: =SUM(H2:H78) -> 2269958.3 | I79: =SUM(I2:I78) -> 5738472.3 | J79: =SUM(J2:J78) -> 0 | K79: =SUM(K2:K78) -> 0 | L79: =SUM(L2:L78) -> 2228484.2

Sheet copper payment
A1: 发票号 Инвойс | B1: 规格 Спецификация | C1: 净重 Вес нетто / Тонн | D1: 单价(CNY) Цена | E1: 报关金额 Сумма экспорта | F1: 已付 Оплачено | G1: 未付 Неоплачено | H1: 货到港口日期 Дата прибытия | I1: 付款日期 Дата оплаты | J1: 备注 Примечание
A2: TW-1 | B2: OPPER GRANULES <99% | C2: 5 | D2: 55991 | E2: =D2*C2 -> 279955 | F2: 279955 | G2: =F2-E2 -> 0
A3: TW-218 | B3: OPPER GRANULES <99% | C3: 25.536 | D3: 65333.4 | E3: =D3*C3 -> 1668353.7 | F3: =100000+1518353.7+50000 -> 1668353.7 | G3: =F3-E3 -> -0.0024000001
A4: TW-296 | B4: RECYCLING MATERIALS FOR COPPER(RCu-1C) | C4: 3.5 | D4: =8600*7.19 -> 61834 | E4: =D4*C4 -> 216419 | F4: 1502249.8 | G4: =SUM(E4:E5)-F4 -> 0 | H4: 45789 | I4: =H4+14 -> 45803
B5: RECYCLING MATERIALS FOR COPPER(RCu-2B) | C5: 21.29 | D5: =8400*7.19 -> 60396 | E5: =D5*C5 -> 1285830.8
A6: TW-297 | E6: =D6*C6 -> 0 | J6: 退运 Возврат
A7: TW-298 | B7: RECYCLING MATERIALS FOR COPPER(RCu-1C) | C7: 11.171 | D7: 61920 | E7: =D7*C7 -> 691708.32 | F7: =1751691.3+100000+900000+83972.54 -> 2835663.8 | G7: =SUM(E7:E8)-F7 -> 0 | H7: 45744 | I7: =H7+14 -> 45758
B8: RECYCLING MATERIALS FOR COPPER(RCu-2B) | C8: 35.449 | D8: 60480 | E8: =D8*C8 -> 2143955.5
A9: TW-307 | B9: RECYCLING MATERIALS FOR COPPER(RCu-1C) | C9: 9.7895 | D9: =8600*7.18 -> 61748 | E9: =D9*C9 -> 604482.05 | F9: =2000000+1482175+750000+199736.72 -> 4431911.7 | G9: =SUM(E9:E10)-F9 -> 0.0020000003 | H9: 45812 | I9: =H9+14 -> 45826
B10: RECYCLING MATERIALS FOR COPPER(RCu-2B) | C10: 63.4605 | D10: =8400*7.18 -> 60312 | E10: =D10*C10 -> 3827429.7
A11: TW-355 | B11: Copper recycled material（Rcu-1B） | C11: 6.11 | D11: 65140 | E11: =D11*C11 -> 398005.4 | F11: =1500000+29956.22 -> 1529956.2 | G11: =SUM(E11:E12)-F11 -> 0 | H11: 45947 | I11: 45966
B12: Copper recycled material（Rcu-2B） | C12: 18.33 | D12: 61754 | E12: =D12*C12 -> 1131950.8
F13: =SUM(F2:F12) -> 12248090 | G13: =SUM(G2:G12) -> -0.00039999979
